Workbook

Sheet Bilan - Actifs
A1: WORKSHEET: Corporate - Standard | B1: Créé le | D1: Analyste : | F1: Site : | G1: ALGERIE
A3: Source de données | B3: OWN | C3: OWN | D3: OWN
A4: Type | B4: Annuel | C4: Annuel | D4: Annuel
A5: Date de clôture
A6: Date de début
A7: Durée
A8: Durée | B8: 12 mois | C8: 12 mois | D8: 12 mois
A9: Statut de la consolidation | B9: Social | C9: Social | D9: Social
A10: Norme comptable | B10: Local Gaap | C10: Local Gaap | D10: Local Gaap
A11: Unité/ Devise affichée | B11: Million DZD | C11: Million DZD | D11: Million DZD
A12: Opinion | B12: Comptes non audités | C12: Comptes non audités | D12: Comptes non audités
A13: Date de Publication
B14: Valeur | C14: Valeur | D14: Valeur
A16: Ecarts d'acquisition | B16: =IF(ROUND('Saisie actif'!R10,3)=0,"",ROUND('Saisie actif'!R10,3)/1000) | C16: =IF(ROUND('Saisie actif'!O10,3)=0,"",ROUND('Saisie actif'!O10,3)/1000) | D16: =IF(ROUND('Saisie actif'!L10,3)=0,"",ROUND('Saisie actif'!L10,3)/1000)
A17: Immobilisations incorporelles nettes | B17: =IF(ROUND('Saisie actif'!R11,3)=0,"",ROUND('Saisie actif'!R11,3)/1000) | C17: =IF(ROUND('Saisie actif'!O11,3)=0,"",ROUND('Saisie actif'!O11,3)/1000) | D17: =IF(ROUND('Saisie actif'!L11,3)=0,"",ROUND('Saisie actif'!L11,3)/1000)
A18: dont coûts de développement capitalisés
A19: Immobilisations corporelles nettes | B19: =IF(OR(ISNUMBER(B20),OR(ISNUMBER(B23),OR(ISNUMBER(B26),ISNUMBER(B29)))),N(B20)+N(B23)+N(B26)+N(B29),"") | C19: =IF(OR(ISNUMBER(C20),OR(ISNUMBER(C23),OR(ISNUMBER(C26),ISNUMBER(C29)))),N(C20)+N(C23)+N(C26)+N(C29),"") | D19: =IF(OR(ISNUMBER(D20),OR(ISNUMBER(D23),OR(ISNUMBER(D26),ISNUMBER(D29)))),N(D20)+N(D23)+N(D26)+N(D29),"")
A20: dont propriété Net, Usine, Equipement | B20: =IF(COUNT(B21,B22)=0,"",SUM(B21,B22)) | C20: =IF(COUNT(C21,C22)=0,"",SUM(C21,C22)) | D20: =IF(COUNT(D21,D22)=0,"",SUM(D21,D22))
A21: Propriété brut Usine et équipement | B21: =IF(ROUND('Saisie actif'!P13 + 'Saisie actif'!P14 + 'Saisie actif'!P15,3)=0,"",ROUND('Saisie actif'!P13 + 'Saisie actif'!P14 + 'Saisie actif'!P15,3)/1000) | C21: =IF(ROUND('Saisie actif'!M13 + 'Saisie actif'!M14 + 'Saisie actif'!M15,3)=0,"",ROUND('Saisie actif'!M13 + 'Saisie actif'!M14 + 'Saisie actif'!M15,3)/1000) | D21: =IF(ROUND('Saisie actif'!J13 + 'Saisie actif'!J14 + 'Saisie actif'!J15,3)=0,"",ROUND('Saisie actif'!J13 + 'Saisie actif'!J14 + 'Saisie actif'!J15,3)/1000)
A22: Dépréciations cumulées | B22: =IF(ROUND(-('Saisie actif'!Q13 + 'Saisie actif'!Q14 + 'Saisie actif'!Q15),3)=0,"",ROUND(-('Saisie actif'!Q13 + 'Saisie actif'!Q14 + 'Saisie actif'!Q15),3)/1000) | C22: =IF(ROUND(-('Saisie actif'!N13 + 'Saisie actif'!N14 + 'Saisie actif'!N15),3)=0,"",ROUND(-('Saisie actif'!N13 + 'Saisie actif'!N14 + 'Saisie actif'!N15),3)/1000) | D22: =IF(ROUND(-('Saisie actif'!K13 + 'Saisie actif'!K14 + 'Saisie actif'!K15),3)=0,"",ROUND(-('Saisie actif'!K13 + 'Saisie actif'!K14 + 'Saisie actif'!K15),3)/1000)
A23: dont Contrats de location financement - preneur | B23: =IF(COUNT(B24,B25)=0,"",SUM(B24,B25)) | C23: =IF(COUNT(C24,C25)=0,"",SUM(C24,C25)) | D23: =IF(COUNT(D24,D25)=0,"",SUM(D24,D25))
A24: Total brut des loyers de lease
A25: Dépréciations cumulées
A26: dont Contrat de location simple - loueur | B26: =IF(COUNT(B27,B28)=0,"",SUM(B27,B28)) | C26: =IF(COUNT(C27,C28)=0,"",SUM(C27,C28)) | D26: =IF(COUNT(D27,D28)=0,"",SUM(D27,D28))
A27: Total brut des loyers
A28: Dépréciations cumulées
A29: Dont autres immobilisations corporelles | B29: =IF(ROUND('Saisie actif'!R17,3)=0,"",ROUND('Saisie actif'!R17,3)/1000) | C29: =IF(ROUND('Saisie actif'!O17,3)=0,"",ROUND('Saisie actif'!O17,3)/1000) | D29: =IF(ROUND('Saisie actif'!L17,3)=0,"",ROUND('Saisie actif'!L17,3)/1000)
A30: Concessions | B30: =IF(COUNT(B31,B32)=0,"",SUM(B31,B32)) | C30: =IF(COUNT(C31,C32)=0,"",SUM(C31,C32)) | D30: =IF(COUNT(D31,D32)=0,"",SUM(D31,D32))
A31: dont Concessions (Actif incorporel) | B31: =IF(ROUND('Saisie actif'!R16,3)=0,"",ROUND('Saisie actif'!R16,3)/1000) | C31: =IF(ROUND('Saisie actif'!O16,3)=0,"",ROUND('Saisie actif'!O16,3)/1000) | D31: =IF(ROUND('Saisie actif'!L16,3)=0,"",ROUND('Saisie actif'!L16,3)/1000)
A32: dont Concessions (Actif financier)
A33: Immobilisations financières nettes | B33: =IF(COUNT(B34,B35,B36,B37)=0,"",SUM(B34,B35,B36,B37)) | C33: =IF(COUNT(C34,C35,C36,C37)=0,"",SUM(C34,C35,C36,C37)) | D33: =IF(COUNT(D34,D35,D36,D37)=0,"",SUM(D34,D35,D36,D37))
A34: dont Titres de participation | B34: =IF(ROUND('Saisie actif'!R20,3)=0,"",ROUND('Saisie actif'!R20,3)/1000) | C34: =IF(ROUND('Saisie actif'!O20,3)=0,"",ROUND('Saisie actif'!O20,3)/1000) | D34: =IF(ROUND('Saisie actif'!L20,3)=0,"",ROUND('Saisie actif'!L20,3)/1000)
A35: dont Investissements dans les sociétés du groupe | B35: =IF(ROUND('Saisie actif'!R19,3)=0,"",ROUND('Saisie actif'!R19,3)/1000) | C35: =IF(ROUND('Saisie actif'!O19,3)=0,"",ROUND('Saisie actif'!O19,3)/1000) | D35: =IF(ROUND('Saisie actif'!L19,3)=0,"",ROUND('Saisie actif'!L19,3)/1000)
A36: dont Avances à des entités du groupe
A37: dont autres Immobilisations financières nettes | B37: =IF(ROUND('Saisie actif'!R21 + 'Saisie actif'!R22,3)=0,"",ROUND('Saisie actif'!R21 + 'Saisie actif'!R22,3)/1000) | C37: =IF(ROUND('Saisie actif'!O21 + 'Saisie actif'!O22,3)=0,"",ROUND('Saisie actif'!O21 + 'Saisie actif'!O22,3)/1000) | D37: =IF(ROUND('Saisie actif'!L21 + 'Saisie actif'!L22,3)=0,"",ROUND('Saisie actif'!L21 + 'Saisie actif'!L22,3)/1000)
A38: Impôts différés | B38: =IF(COUNT(B39,B40)=0,"",SUM(B39,B40)) | C38: =IF(COUNT(C39,C40)=0,"",SUM(C39,C40)) | D38: =IF(COUNT(D39,D40)=0,"",SUM(D39,D40))
A39: dont Impôts différés non courants | B39: =IF(ROUND('Saisie actif'!R23,3)=0,"",ROUND('Saisie actif'!R23,3)/1000) | C39: =IF(ROUND('Saisie actif'!O23,3)=0,"",ROUND('Saisie actif'!O23,3)/1000) | D39: =IF(ROUND('Saisie actif'!L23,3)=0,"",ROUND('Saisie actif'!L23,3)/1000)
A40: dont Impôts différés courants
A41: Dérivés | B41: =IF(COUNT(B42,B43)=0,"",SUM(B42,B43)) | C41: =IF(COUNT(C42,C43)=0,"",SUM(C42,C43)) | D41: =IF(COUNT(D42,D43)=0,"",SUM(D42,D43))
A42: dont Produits dérivés non courants
A43: dont Produits dérivés courants
A44: dont Créances financières non courantes | B44: =IF(COUNT(B45,B46,B47,B48)=0,"",SUM(B45:B48)) | C44: =IF(COUNT(C45,C46,C47,C48)=0,"",SUM(C45:C48)) | D44: =IF(COUNT(D45,D46,D47,D48)=0,"",SUM(D45:D48))
A45: dont part non cour. des créances financières non cour.
A46: dont part cour. des créances financières non cour.
A47: dont créances liées aux opérations de lease
A48: dont Part Cour. Créances Liées Aux Op. Lease
A49: Autres actifs non courants | B49: =IF(COUNT(B39,B42,B45,B47,B50,B53,B54)=0,"",SUM(B39,B42,B45,B47,B50,B53,B54)) | C49: =IF(COUNT(C39,C42,C45,C47,C50,C53,C54)=0,"",SUM(C39,C42,C45,C47,C50,C53,C54)) | D49: =IF(COUNT(D39,D42,D45,D47,D50,D53,D54)=0,"",SUM(D39,D42,D45,D47,D50,D53,D54))
A50: dont Créances non courantes | B50: =IF(COUNT(B51,B52)=0,"",SUM(B51,B52)) | C50: =IF(COUNT(C51,C52)=0,"",SUM(C51,C52)) | D50: =IF(COUNT(D51,D52)=0,"",SUM(D51,D52))
A51: dont part non courante des créances non courantes
A52: dont part courantes des créances non courantes
A53: dont actifs couverture régimes retraite/en excès
A54: dont autres
A55: Stocks | B55: =IF(COUNT(B56,B59,B62,B65)=0,"",SUM(B56,B59,B62,B65)) | C55: =IF(COUNT(C56,C59,C62,C65)=0,"",SUM(C56,C59,C62,C65)) | D55: =IF(COUNT(D56,D59,D62,D65)=0,"",SUM(D56,D59,D62,D65))
A56: dont Matières premières nettes | B56: =IF(COUNT(B57,B58)=0,"",SUM(B57,B58)) | C56: =IF(COUNT(C57,C58)=0,"",SUM(C57,C58)) | D56: =IF(COUNT(D57,D58)=0,"",SUM(D57,D58))
A57: Brut | B57: =IF(ROUND('Saisie actif'!P26,3)=0,"",ROUND('Saisie actif'!P26,3)/1000) | C57: =IF(ROUND('Saisie actif'!M26,3)=0,"",ROUND('Saisie actif'!M26,3)/1000) | D57: =IF(ROUND('Saisie actif'!J26,3)=0,"",ROUND('Saisie actif'!J26,3)/1000)
A58: Dépréciations cumulées | B58: =IF(ROUND(-'Saisie actif'!Q26,3)=0,"",ROUND(-'Saisie actif'!Q26,3)/1000) | C58: =IF(ROUND(-'Saisie actif'!N26,3)=0,"",ROUND(-'Saisie actif'!N26,3)/1000) | D58: =IF(ROUND(-'Saisie actif'!K26,3)=0,"",ROUND(-'Saisie actif'!K26,3)/1000)
A59: dont Travaux en cours nets | B59: =IF(COUNT(B60,B61)=0,"",SUM(B60,B61)) | C59: =IF(COUNT(C60,C61)=0,"",SUM(C60,C61)) | D59: =IF(COUNT(D60,D61)=0,"",SUM(D60,D61))
A60: Brut
A61: Dépréciations cumulées
A62: dont Produits finis nets | B62: =IF(COUNT(B63,B64)=0,"",SUM(B63,B64)) | C62: =IF(COUNT(C63,C64)=0,"",SUM(C63,C64)) | D62: =IF(COUNT(D63,D64)=0,"",SUM(D63,D64))
A63: Brut
A64: Dépréciations cumulées
A65: dont Marchandises nettes | B65: =IF(COUNT(B66,B67)=0,"",SUM(B66,B67)) | C65: =IF(COUNT(C66,C67)=0,"",SUM(C66,C67)) | D65: =IF(COUNT(D66,D67)=0,"",SUM(D66,D67))
A66: Brut
A67: Dépréciations cumulées
A68: Créances d'exploitation et autres | B68: =IF(COUNT(B69,B70)=0,"",SUM(B69,B70)) | C68: =IF(COUNT(C69,C70)=0,"",SUM(C69,C70)) | D68: =IF(COUNT(D69,D70)=0,"",SUM(D69,D70))
A69: dont Brut | B69: =IF(ROUND('Saisie actif'!P28,3)=0,"",ROUND('Saisie actif'!P28,3)/1000) | C69: =IF(ROUND('Saisie actif'!M28,3)=0,"",ROUND('Saisie actif'!M28,3)/1000) | D69: =IF(ROUND('Saisie actif'!J28,3)=0,"",ROUND('Saisie actif'!J28,3)/1000)
A70: dont dotation aux provisions | B70: =IF(ROUND(-'Saisie actif'!Q28,3)=0,"",ROUND(-'Saisie actif'!Q28,3)/1000) | C70: =IF(ROUND(-'Saisie actif'!N28,3)=0,"",ROUND(-'Saisie actif'!N28,3)/1000) | D70: =IF(ROUND(-'Saisie actif'!K28,3)=0,"",ROUND(-'Saisie actif'!K28,3)/1000)
A71: Avances et charges constatées d'avance | B71: =IF(COUNT(B72,B73,B74)=0,"",SUM(B72,B73,B74)) | C71: =IF(COUNT(C72,C73,C74)=0,"",SUM(C72,C73,C74)) | D71: =IF(COUNT(D72,D73,D74)=0,"",SUM(D72,D73,D74))
A72: dont Montant Dûs aux Clients sur Contrats de LT
A73: dont Avances sur Travaux en Cours
A74: dont autres
A75: Autres actifs courants | B75: =IF(COUNT(B76,B77,B78,B79)=0,"",SUM(B76,B77,B78,B79)) | C75: =IF(COUNT(C76,C77,C78,C79)=0,"",SUM(C76,C77,C78,C79)) | D75: =IF(COUNT(D76,D77,D78,D79)=0,"",SUM(D76,D77,D78,D79))
A76: dont Créance d'impôt courant | B76: =IF(ROUND('Saisie actif'!R30,3)=0,"",ROUND('Saisie actif'!R30,3)/1000) | C76: =IF(ROUND('Saisie actif'!O30,3)=0,"",ROUND('Saisie actif'!O30,3)/1000) | D76: =IF(ROUND('Saisie actif'!L30,3)=0,"",ROUND('Saisie actif'!L30,3)/1000)
A77: dont Autres créances d'impôts
A78: dont autres actifs circulants
A79: dont autres | B79: =IF(ROUND('Saisie actif'!R29 + 'Saisie actif'!R31,3)=0,"",ROUND('Saisie actif'!R29 + 'Saisie actif'!R31,3)/1000) | C79: =IF(ROUND('Saisie actif'!O29 + 'Saisie actif'!O31,3)=0,"",ROUND('Saisie actif'!O29 + 'Saisie actif'!O31,3)/1000) | D79: =IF(ROUND('Saisie actif'!L29 + 'Saisie actif'!L31,3)=0,"",ROUND('Saisie actif'!L29 + 'Saisie actif'!L31,3)/1000)
A80: Actifs financiers courants (hors investissements)
A81: Trésorerie, équivalents de trésorerie et VMP (< 3 mois) | B81: =IF(COUNT(B82,B83)=0,"",SUM(B82,B83)) | C81: =IF(COUNT(C82,C83)=0,"",SUM(C82,C83)) | D81: =IF(COUNT(D82,D83)=0,"",SUM(D82,D83))
A82: dont VMP, nettes | B82: =IF(ROUND('Saisie actif'!R33,3)=0,"",ROUND('Saisie actif'!R33,3)/1000) | C82: =IF(ROUND('Saisie actif'!O33,3)=0,"",ROUND('Saisie actif'!O33,3)/1000) | D82: =IF(ROUND('Saisie actif'!L33,3)=0,"",ROUND('Saisie actif'!L33,3)/1000)
A83: dont Trésorerie et équivalents de trésorerie | B83: =IF(ROUND('Saisie actif'!R34,3)=0,"",ROUND('Saisie actif'!R34,3)/1000) | C83: =IF(ROUND('Saisie actif'!O34,3)=0,"",ROUND('Saisie actif'!O34,3)/1000) | D83: =IF(ROUND('Saisie actif'!L34,3)=0,"",ROUND('Saisie actif'!L34,3)/1000)
A84: TOTAL ACTIFS NON COURANTS | B84: =IF(COUNT(B16,B17,B19,B30,B33,B42,B44,B49)=0,"",SUM(B16,B17,B19,B30,B33,B42,B44,B49)) | C84: =IF(COUNT(C16,C17,C19,C30,C33,C42,C44,C49)=0,"",SUM(C16,C17,C19,C30,C33,C42,C44,C49)) | D84: =IF(COUNT(D16,D17,D19,D30,D33,D42,D44,D49)=0,"",SUM(D16,D17,D19,D30,D33,D42,D44,D49))
A85: TOTAL ACTIFS COURANTS | B85: =IF(COUNT(B43,B55,B68,B71,B75,B80,B81)=0,"",SUM(B43,B55,B68,B71,B75,B80,B81)) | C85: =IF(COUNT(C43,C55,C68,C71,C75,C80,C81)=0,"",SUM(C43,C55,C68,C71,C75,C80,C81)) | D85: =IF(COUNT(D43,D55,D68,D71,D75,D80,D81)=0,"",SUM(D43,D55,D68,D71,D75,D80,D81))
A86: Actifs Détenus en Vue de la Vente
A87: TOTAL ACTIF | B87: =IF(COUNT(B84,B85,B86)=0,"",SUM(B84,B85,B86)) | C87: =IF(COUNT(C84,C85,C86)=0,"",SUM(C84,C85,C86)) | D87: =IF(COUNT(D84,D85,D86)=0,"",SUM(D84,D85,D86))

Sheet Bilan - Passifs
A1: WORKSHEET: Corporate - Standard | B1: Créé le | D1: Analyste : | E1: =IF('Bilan - Actifs'!E1="","",'Bilan - Actifs'!E1) | F1: Site : | G1: ALGERIE
A3: Source de données | B3: OWN | C3: OWN | D3: OWN
A4: Type | B4: Annuel | C4: Annuel | D4: Annuel
A5: Date de clôture
A6: Date de début
A7: Durée
A8: Durée | B8: 12 mois | C8: 12 mois | D8: 12 mois
A9: Statut de la consolidation | B9: Social | C9: Social | D9: Social
A10: Norme comptable | B10: Local Gaap | C10: Local Gaap | D10: Local Gaap
A11: Unité/ Devise affichée | B11: Million DZD | C11: Million DZD | D11: Million DZD
A12: Opinion | B12: Comptes non audités | C12: Comptes non audités | D12: Comptes non audités
A13: Date de Publication
B16: Valeur | C16: Valeur | D16: Valeur
A18: Capital | B18: =B19+B20 | C18: =C19+C20 | D18: =D19+D20
A19: dont Actions ordinaires | B19: =IF(ROUND('Saisie passif'!H6 - 'Saisie passif'!H7,3)=0,"",ROUND('Saisie passif'!H6 - 'Saisie passif'!H7,3)/1000) | C19: =IF(ROUND('Saisie passif'!G6 - 'Saisie passif'!G7,3)=0,"",ROUND('Saisie passif'!G6 - 'Saisie passif'!G7,3)/1000) | D19: =IF(ROUND('Saisie passif'!F6 - 'Saisie passif'!F7,3)=0,"",ROUND('Saisie passif'!F6 - 'Saisie passif'!F7,3)/1000)
A20: dont Actions de préférence
A21: Primes
A22: Actions d'autocontrôle
A23: Réserves (non distribuables) | B23: =IF(ROUND('Saisie passif'!H8,3)=0,"",ROUND('Saisie passif'!H8,3)/1000) | C23: =IF(ROUND('Saisie passif'!G8,3)=0,"",ROUND('Saisie passif'!G8,3)/1000) | D23: =IF(ROUND('Saisie passif'!F8,3)=0,"",ROUND('Saisie passif'!F8,3)/1000)
A24: Réserves distribuables | B24: =IF(ROUND('Saisie passif'!H12,3)=0,"",ROUND('Saisie passif'!H12,3)/1000) | C24: =IF(ROUND('Saisie passif'!G12,3)=0,"",ROUND('Saisie passif'!G12,3)/1000) | D24: =IF(ROUND('Saisie passif'!F12,3)=0,"",ROUND('Saisie passif'!F12,3)/1000)
A25: Intérêts minoritaires
A26: Résultat Net Publié, Part du Groupe | B26: =IF(ROUND('Saisie passif'!H11,3)=0,"",ROUND('Saisie passif'!H11,3)/1000) | C26: =IF(ROUND('Saisie passif'!G11,3)=0,"",ROUND('Saisie passif'!G11,3)/1000) | D26: =IF(ROUND('Saisie passif'!F11,3)=0,"",ROUND('Saisie passif'!F11,3)/1000)
A27: Capitaux Propres (Cp) Av. élém. Constatés en Cp | B27: =IF(COUNT(B18,B21,B22,B23,B24,B25,B26)=0,"",SUM(B18,B21,B22,B23,B24,B25,B26)) | C27: =IF(COUNT(C18,C21,C22,C23,C24,C25,C26)=0,"",SUM(C18,C21,C22,C23,C24,C25,C26)) | D27: =IF(COUNT(D18,D21,D22,D23,D24,D25,D26)=0,"",SUM(D18,D21,D22,D23,D24,D25,D26))
A28: Elements constatés direct. en cap.propres | B28: =IF(COUNT(B29,B30,B31,B32,B33,B34)=0,"",SUM(B29,B30,B31,B32,B33,B34)) | C28: =IF(COUNT(C29,C30,C31,C32,C33,C34)=0,"",SUM(C29,C30,C31,C32,C33,C34)) | D28: =IF(COUNT(D29,D30,D31,D32,D33,D34)=0,"",SUM(D29,D30,D31,D32,D33,D34))
A29: dont différence de conversion
A30: dont variation JV actifs détenus en vue de la vente
A31: dont var. juste valeur (JV) dérivés de couverture
A32: dont passifs liés aux régimes de retraites
A33: dont Impôts différés
A34: dont autres | B34: =IF(ROUND('Saisie passif'!H9 + 'Saisie passif'!H10,3)=0,"",ROUND('Saisie passif'!H9 + 'Saisie passif'!H10,3)/1000) | C34: =IF(ROUND('Saisie passif'!G9 + 'Saisie passif'!G10,3)=0,"",ROUND('Saisie passif'!G9 + 'Saisie passif'!G10,3)/1000) | D34: =IF(ROUND('Saisie passif'!F9 + 'Saisie passif'!F10,3)=0,"",ROUND('Saisie passif'!F9 + 'Saisie passif'!F10,3)/1000)
A35: TOTAL CAPITAUX PROPRES | B35: =IF(COUNT(B27,B28)=0,"",SUM(B27,B28)) | C35: =IF(COUNT(C27,C28)=0,"",SUM(C27,C28)) | D35: =IF(COUNT(D27,D28)=0,"",SUM(D27,D28))
A36: dont part du groupe | B36: =IF(COUNT(B35,B25)=0,"",B35-SUM(B25)) | C36: =IF(COUNT(C35,C25)=0,"",C35-SUM(C25)) | D36: =IF(COUNT(D35,D25)=0,"",D35-SUM(D25))
A37: Provisions | B37: =IF(COUNT(B38,B39,B40,B41,B42)=0,"",SUM(B38,B39,B40,B41,B42)) | C37: =IF(COUNT(C38,C39,C40,C41,C42)=0,"",SUM(C38,C39,C40,C41,C42)) | D37: =IF(COUNT(D38,D39,D40,D41,D42)=0,"",SUM(D38,D39,D40,D41,D42))
A38: dont avantages au personnel
A39: dont provisions de restructuration
A40: dont Provisions pour contentieux juridiques
A41: dont Réhabilitation d'actifs
A42: dont Autres | B42: =IF(ROUND('Saisie passif'!H20,3)=0,"",ROUND('Saisie passif'!H20,3)/1000) | C42: =IF(ROUND('Saisie passif'!G20,3)=0,"",ROUND('Saisie passif'!G20,3)/1000) | D42: =IF(ROUND('Saisie passif'!F20,3)=0,"",ROUND('Saisie passif'!F20,3)/1000)
A43: Emprunts non courants | B43: =IF(COUNT(B44,B45,B46,B47,B48,B49,B50,B51)=0,"",SUM(B44,B45,B46,B47,B48,B49,B50,B51)) | C43: =IF(COUNT(C44,C45,C46,C47,C48,C49,C50,C51)=0,"",SUM(C44,C45,C46,C47,C48,C49,C50,C51)) | D43: =IF(COUNT(D44,D45,D46,D47,D48,D49,D50,D51)=0,"",SUM(D44,D45,D46,D47,D48,D49,D50,D51))
A44: dont Emprunts senior auprès étab. Fi.&autres | B44: =IF(ROUND('Saisie passif'!H17,3)=0,"",ROUND('Saisie passif'!H17,3)/1000) | C44: =IF(ROUND('Saisie passif'!G17,3)=0,"",ROUND('Saisie passif'!G17,3)/1000) | D44: =IF(ROUND('Saisie passif'!F17,3)=0,"",ROUND('Saisie passif'!F17,3)/1000)
A45: dont Engagts liés ctrs loc.-fin.
A46: dont Dette liée aux participations
A47: dont Dette Liée aux Entités Fin. du Groupe
A48: dont Obligations émises
A49: dont Dette subordonnée
A50: dont Dette hybride
A51: dont Autres dettes | B51: =IF(ROUND('Saisie passif'!H19,3)=0,"",ROUND('Saisie passif'!H19,3)/1000) | C51: =IF(ROUND('Saisie passif'!G19,3)=0,"",ROUND('Saisie passif'!G19,3)/1000) | D51: =IF(ROUND('Saisie passif'!F19,3)=0,"",ROUND('Saisie passif'!F19,3)/1000)
A52: dont Coupons courus
A53: Emprunts et autres passifs financiers courants | B53: =IF(COUNT(B54,B55,B56,B57,B58)=0,"",SUM(B54,B55,B56,B57,B58)) | C53: =IF(COUNT(C54,C55,C56,C57,C58)=0,"",SUM(C54,C55,C56,C57,C58)) | D53: =IF(COUNT(D54,D55,D56,D57,D58)=0,"",SUM(D54,D55,D56,D57,D58))
A54: dont dette bancaire courante | B54: =IF(ROUND('Saisie passif'!H26,3)=0,"",ROUND('Saisie passif'!H26,3)/1000) | C54: =IF(ROUND('Saisie passif'!G26,3)=0,"",ROUND('Saisie passif'!G26,3)/1000) | D54: =IF(ROUND('Saisie passif'!F26,3)=0,"",ROUND('Saisie passif'!F26,3)/1000)
A55: dont dette de marché courante
A56: dont part courante des emprunts à long terme
A57: dont Dette Courante Liée Aux Entités Fin. du Groupe
A58: dont autres dettes financières courantes
A59: Impôts différés | B59: =IF(COUNT(B60,B61)=0,"",SUM(B60,B61)) | C59: =IF(COUNT(C60,C61)=0,"",SUM(C60,C61)) | D59: =IF(COUNT(D60,D61)=0,"",SUM(D60,D61))
A60: dont Impôts différés non courants | B60: =IF(ROUND('Saisie passif'!H18,3)=0,"",ROUND('Saisie passif'!H18,3)/1000) | C60: =IF(ROUND('Saisie passif'!G18,3)=0,"",ROUND('Saisie passif'!G18,3)/1000) | D60: =IF(ROUND('Saisie passif'!F18,3)=0,"",ROUND('Saisie passif'!F18,3)/1000)
A61: dont Impôts différés courants
A62: Dérivés | B62: =IF(COUNT(B63,B64)=0,"",SUM(B63,B64)) | C62: =IF(COUNT(C63,C64)=0,"",SUM(C63,C64)) | D62: =IF(COUNT(D63,D64)=0,"",SUM(D63,D64))
A63: dont Produits dérivés non courants
A64: dont Produits dérivés courants
A65: Autres Passifs | B65: =IF(COUNT(B66)=0,"",SUM(B66)) | C65: =IF(COUNT(C66)=0,"",SUM(C66)) | D65: =IF(COUNT(D66)=0,"",SUM(D66))
A66: dont Autres
A67: Dettes fournisseurs | B67: =IF(ROUND('Saisie passif'!H23,3)=0,"",ROUND('Saisie passif'!H23,3)/1000) | C67: =IF(ROUND('Saisie passif'!G23,3)=0,"",ROUND('Saisie passif'!G23,3)/1000) | D67: =IF(ROUND('Saisie passif'!F23,3)=0,"",ROUND('Saisie passif'!F23,3)/1000)
A68: Produits différés & Autres dettes d'exploitation | B68: =IF(COUNT(B69,B70,B71,B72,B73,B74)=0,"",SUM(B69,B70,B71,B72,B73,B74)) | C68: =IF(COUNT(C69,C70,C71,C72,C73,C74)=0,"",SUM(C69,C70,C71,C72,C73,C74)) | D68: =IF(COUNT(D69,D70,D71,D72,D73,D74)=0,"",SUM(D69,D70,D71,D72,D73,D74))
A69: dont Montant Dûs aux Clients sur Contrats de LT
A70: dont Avances Clients
A71: dont passifs sur travaux en cours
A72: dont Produits différés
A73: dont Dividendes exigibles
A74: dont Autres | B74: =IF(ROUND('Saisie passif'!H25,3)=0,"",ROUND('Saisie passif'!H25,3)/1000) | C74: =IF(ROUND('Saisie passif'!G25,3)=0,"",ROUND('Saisie passif'!G25,3)/1000) | D74: =IF(ROUND('Saisie passif'!F25,3)=0,"",ROUND('Saisie passif'!F25,3)/1000)
A75: dont autres passifs courants | B75: =IF(COUNT(B76,B77,B78,B79)=0,"",SUM(B76,B77,B78,B79)) | C75: =IF(COUNT(C76,C77,C78,C79)=0,"",SUM(C76,C77,C78,C79)) | D75: =IF(COUNT(D76,D77,D78,D79)=0,"",SUM(D76,D77,D78,D79))
A76: dette d'impôts courants | B76: =IF(ROUND('Saisie passif'!H24,3)=0,"",ROUND('Saisie passif'!H24,3)/1000) | C76: =IF(ROUND('Saisie passif'!G24,3)=0,"",ROUND('Saisie passif'!G24,3)/1000) | D76: =IF(ROUND('Saisie passif'!F24,3)=0,"",ROUND('Saisie passif'!F24,3)/1000)
A77: dont autres dettes d'impôts
A78: dont autres passifs circulants
A79: dont autres
A80: TOTAL PASSIFS NON COURANTS | B80: =IF(COUNT(B37,B43,B60,B63,B65)=0,"",SUM(B37,B43,B60,B63,B65)) | C80: =IF(COUNT(C37,C43,C60,C63,C65)=0,"",SUM(C37,C43,C60,C63,C65)) | D80: =IF(COUNT(D37,D43,D60,D63,D65)=0,"",SUM(D37,D43,D60,D63,D65))
A81: TOTAL PASSIFS COURANTS | B81: =IF(COUNT(B53,B61,B64,B67,B68,B75)=0,"",SUM(B53,B61,B64,B67,B68,B75)) | C81: =IF(COUNT(C53,C61,C64,C67,C68,C75)=0,"",SUM(C53,C61,C64,C67,C68,C75)) | D81: =IF(COUNT(D53,D61,D64,D67,D68,D75)=0,"",SUM(D53,D61,D64,D67,D68,D75))
A82: Passifs liés à la cession d'actifs
A83: TOTAL ENGAGEMENTS | B83: =IF(COUNT(B80,B81,B82)=0,"",SUM(B80,B81,B82)) | C83: =IF(COUNT(C80,C81,C82)=0,"",SUM(C80,C81,C82)) | D83: =IF(COUNT(D80,D81,D82)=0,"",SUM(D80,D81,D82))
A84: TOTAL PASSIF | B84: =IF(COUNT(B35,B83)=0,"",SUM(B35,B83)) | C84: =IF(COUNT(C35,C83)=0,"",SUM(C35,C83)) | D84: =IF(COUNT(D35,D83)=0,"",SUM(D35,D83))

Sheet Compte de résultat
A1: WORKSHEET: Corporate - Standard | B1: Créé le | D1: Analyste : | E1: =IF('Bilan - Actifs'!E1="","",'Bilan - Actifs'!E1) | F1: Site : | G1: ALGERIE
A3: Source de données | B3: OWN | C3: OWN | D3: OWN
A4: Type | B4: Annuel | C4: Annuel | D4: Annuel
A5: Date de clôture
A6: Date de début
A7: Durée
A8: Durée | B8: 12 mois | C8: 12 mois | D8: 12 mois
A9: Statut de la consolidation | B9: Social | C9: Social | D9: Social
A10: Norme comptable | B10: Local Gaap | C10: Local Gaap | D10: Local Gaap
A11: Unité/ Devise affichée | B11: Million DZD | C11: Million DZD | D11: Million DZD
A12: Opinion | B12: Comptes non audités | C12: Comptes non audités | D12: Comptes non audités
A13: Date de Publication
B14: Valeur | C14: Valeur | D14: Valeur
A16: Chiffre D'Affaires | B16: =IF(ROUND(('Saisie TCR'!N12-'Saisie TCR'!M12),3)=0,"",ROUND(('Saisie TCR'!N12-'Saisie TCR'!M12),3)/1000) | C16: =IF(ROUND(('Saisie TCR'!L12-'Saisie TCR'!K12),3)=0,"",ROUND(('Saisie TCR'!L12-'Saisie TCR'!K12),3)/1000) | D16: =IF(ROUND(('Saisie TCR'!J12-'Saisie TCR'!I12),3)=0,"",ROUND(('Saisie TCR'!J12-'Saisie TCR'!I12),3)/1000)
A17: Variation des stocks de produits finis | B17: =IF(ROUND(('Saisie TCR'!N13-'Saisie TCR'!M13),3)=0,"",ROUND(('Saisie TCR'!N13-'Saisie TCR'!M13),3)/1000) | C17: =IF(ROUND(('Saisie TCR'!L13-'Saisie TCR'!K13),3)=0,"",ROUND(('Saisie TCR'!L13-'Saisie TCR'!K13),3)/1000) | D17: =IF(ROUND(('Saisie TCR'!J13-'Saisie TCR'!I13),3)=0,"",ROUND(('Saisie TCR'!J13-'Saisie TCR'!I13),3)/1000)
A18: Coûts capitalisés (hors charges d'intérêts capitalisés) | B18: =IF(ROUND(('Saisie TCR'!N14-'Saisie TCR'!M14),3)=0,"",ROUND(('Saisie TCR'!N14-'Saisie TCR'!M14),3)/1000) | C18: =IF(ROUND(('Saisie TCR'!L14-'Saisie TCR'!K14),3)=0,"",ROUND(('Saisie TCR'!L14-'Saisie TCR'!K14),3)/1000) | D18: =IF(ROUND(('Saisie TCR'!J14-'Saisie TCR'!I14),3)=0,"",ROUND(('Saisie TCR'!J14-'Saisie TCR'!I14),3)/1000)
A19: Valeur de la production | B19: =IF(COUNT(B16,B17,B18)=0,"",SUM(B16,B17,B18)) | C19: =IF(COUNT(C16,C17,C18)=0,"",SUM(C16,C17,C18)) | D19: =IF(COUNT(D16,D17,D18)=0,"",SUM(D16,D17,D18))
A20: Achats de matières premières | B20: =IF(ROUND(('Saisie TCR'!N18-'Saisie TCR'!M18) + ('Saisie TCR'!N19-'Saisie TCR'!M19),3)=0,"",ROUND(('Saisie TCR'!N18-'Saisie TCR'!M18) + ('Saisie TCR'!N19-'Saisie TCR'!M19),3)/1000) | C20: =IF(ROUND(('Saisie TCR'!L18-'Saisie TCR'!K18) + ('Saisie TCR'!L19-'Saisie TCR'!K19),3)=0,"",ROUND(('Saisie TCR'!L18-'Saisie TCR'!K18) + ('Saisie TCR'!L19-'Saisie TCR'!K19),3)/1000) | D20: =IF(ROUND(('Saisie TCR'!J18-'Saisie TCR'!I18) + ('Saisie TCR'!J19-'Saisie TCR'!I19),3)=0,"",ROUND(('Saisie TCR'!J18-'Saisie TCR'!I18) + ('Saisie TCR'!J19-'Saisie TCR'!I19),3)/1000)
A21: Achats de Marchandises | B21: =IF(ROUND(('Saisie TCR'!N17-'Saisie TCR'!M17),3)=0,"",ROUND(('Saisie TCR'!N17-'Saisie TCR'!M17),3)/1000) | C21: =IF(ROUND(('Saisie TCR'!L17-'Saisie TCR'!K17),3)=0,"",ROUND(('Saisie TCR'!L17-'Saisie TCR'!K17),3)/1000) | D21: =IF(ROUND(('Saisie TCR'!J17-'Saisie TCR'!I17),3)=0,"",ROUND(('Saisie TCR'!J17-'Saisie TCR'!I17),3)/1000)
A22: Variation des autres stocks | B22: =IF(COUNT(B23,B24,B25)=0,"",SUM(B23,B24,B25)) | C22: =IF(COUNT(C23,C24,C25)=0,"",SUM(C23,C24,C25)) | D22: =IF(COUNT(D23,D24,D25)=0,"",SUM(D23,D24,D25))
A23: dont variation de stocks de matières premières
A24: dont variation de stocks de marchandises
A25: dont non alloué | B25: =IF(ROUND(('Saisie TCR'!N20-'Saisie TCR'!M20),3)=0,"",ROUND(('Saisie TCR'!N20-'Saisie TCR'!M20),3)/1000) | C25: =IF(ROUND(('Saisie TCR'!L20-'Saisie TCR'!K20),3)=0,"",ROUND(('Saisie TCR'!L20-'Saisie TCR'!K20),3)/1000) | D25: =IF(ROUND(('Saisie TCR'!J20-'Saisie TCR'!I20),3)=0,"",ROUND(('Saisie TCR'!J20-'Saisie TCR'!I20),3)/1000)
A26: Sous traitance & Charges externes | B26: =IF(ROUND(('Saisie TCR'!N21-'Saisie TCR'!M21) + ('Saisie TCR'!N22-'Saisie TCR'!M22) + ('Saisie TCR'!N23-'Saisie TCR'!M23) + ('Saisie TCR'!N24-'Saisie TCR'!M24) + ('Saisie TCR'!N26-'Saisie TCR'!M26) + ('Saisie TCR'!N27-'Saisie TCR'!M27) + ('Saisie TCR'!N30-'Saisie TCR'!M30) + ('Saisie TCR'!N31-'Saisie TCR'!M31) + ('Saisie TCR'!N32-'Saisie TCR'!M32) + ('Saisie TCR'!N33-'Saisie TCR'!M33),3)=0,"",ROUND(('Saisie TCR'!N21-'Saisie TCR'!M21) + ('Saisie TCR'!N22-'Saisie TCR'!M22) + ('Saisie TCR'!N23-'Saisie TCR'!M23) + ('Saisie TCR'!N24-'Saisie TCR'!M24) + ('Saisie TCR'!N26-'Saisie TCR'!M26) + ('Saisie TCR'!N27-'Saisie TCR'!M27) + ('Saisie TCR'!N30-'Saisie TCR'!M30) + ('Saisie TCR'!N31-'Saisie TCR'!M31) + ('Saisie TCR'!N32-'Saisie TCR'!M32) + ('Saisie TCR'!N33-'Saisie TCR'!M33),3)/1000) | C26: =IF(ROUND(('Saisie TCR'!L21-'Saisie TCR'!K21) + ('Saisie TCR'!L22-'Saisie TCR'!K22) + ('Saisie TCR'!L23-'Saisie TCR'!K23) + ('Saisie TCR'!L24-'Saisie TCR'!K24) + ('Saisie TCR'!L26-'Saisie TCR'!K26) + ('Saisie TCR'!L27-'Saisie TCR'!K27) + ('Saisie TCR'!L30-'Saisie TCR'!K30) + ('Saisie TCR'!L31-'Saisie TCR'!K31) + ('Saisie TCR'!L32-'Saisie TCR'!K32) + ('Saisie TCR'!L33-'Saisie TCR'!K33),3)=0,"",ROUND(('Saisie TCR'!L21-'Saisie TCR'!K21) + ('Saisie TCR'!L22-'Saisie TCR'!K22) + ('Saisie TCR'!L23-'Saisie TCR'!K23) + ('Saisie TCR'!L24-'Saisie TCR'!K24) + ('Saisie TCR'!L26-'Saisie TCR'!K26) + ('Saisie TCR'!L27-'Saisie TCR'!K27) + ('Saisie TCR'!L30-'Saisie TCR'!K30) + ('Saisie TCR'!L31-'Saisie TCR'!K31) + ('Saisie TCR'!L32-'Saisie TCR'!K32) + ('Saisie TCR'!L33-'Saisie TCR'!K33),3)/1000) | D26: =IF(ROUND(('Saisie TCR'!J21-'Saisie TCR'!I21) + ('Saisie TCR'!J22-'Saisie TCR'!I22) + ('Saisie TCR'!J23-'Saisie TCR'!I23) + ('Saisie TCR'!J24-'Saisie TCR'!I24) + ('Saisie TCR'!J26-'Saisie TCR'!I26) + ('Saisie TCR'!J27-'Saisie TCR'!I27) + ('Saisie TCR'!J30-'Saisie TCR'!I30) + ('Saisie TCR'!J31-'Saisie TCR'!I31) + ('Saisie TCR'!J32-'Saisie TCR'!I32) + ('Saisie TCR'!J33-'Saisie TCR'!I33),3)=0,"",ROUND(('Saisie TCR'!J21-'Saisie TCR'!I21) + ('Saisie TCR'!J22-'Saisie TCR'!I22) + ('Saisie TCR'!J23-'Saisie TCR'!I23) + ('Saisie TCR'!J24-'Saisie TCR'!I24) + ('Saisie TCR'!J26-'Saisie TCR'!I26) + ('Saisie TCR'!J27-'Saisie TCR'!I27) + ('Saisie TCR'!J30-'Saisie TCR'!I30) + ('Saisie TCR'!J31-'Saisie TCR'!I31) + ('Saisie TCR'!J32-'Saisie TCR'!I32) + ('Saisie TCR'!J33-'Saisie TCR'!I33),3)/1000)
A27: Autres charges & produits (hors dépenses de personnel externe) | B27: =IF(ROUND(('Saisie TCR'!N15-'Saisie TCR'!M15) + ('Saisie TCR'!N37-'Saisie TCR'!M37) + ('Saisie TCR'!N39-'Saisie TCR'!M39) + ('Saisie TCR'!N40-'Saisie TCR'!M40),3)=0,"",ROUND(('Saisie TCR'!N15-'Saisie TCR'!M15) + ('Saisie TCR'!N37-'Saisie TCR'!M37) + ('Saisie TCR'!N39-'Saisie TCR'!M39) + ('Saisie TCR'!N40-'Saisie TCR'!M40),3)/1000) | C27: =IF(ROUND(('Saisie TCR'!L15-'Saisie TCR'!K15) + ('Saisie TCR'!L37-'Saisie TCR'!K37) + ('Saisie TCR'!L39-'Saisie TCR'!K39) + ('Saisie TCR'!L40-'Saisie TCR'!K40),3)=0,"",ROUND(('Saisie TCR'!L15-'Saisie TCR'!K15) + ('Saisie TCR'!L37-'Saisie TCR'!K37) + ('Saisie TCR'!L39-'Saisie TCR'!K39) + ('Saisie TCR'!L40-'Saisie TCR'!K40),3)/1000) | D27: =IF(ROUND(('Saisie TCR'!J15-'Saisie TCR'!I15) + ('Saisie TCR'!J37-'Saisie TCR'!I37) + ('Saisie TCR'!J39-'Saisie TCR'!I39) + ('Saisie TCR'!J40-'Saisie TCR'!I40),3)=0,"",ROUND(('Saisie TCR'!J15-'Saisie TCR'!I15) + ('Saisie TCR'!J37-'Saisie TCR'!I37) + ('Saisie TCR'!J39-'Saisie TCR'!I39) + ('Saisie TCR'!J40-'Saisie TCR'!I40),3)/1000)
A28: Valeur Ajoutée | B28: =IF(COUNT(B19,B20,B21,B22,B26,B27)=0,"",SUM(B19,B20,B21,B22,B26,B27)) | C28: =IF(COUNT(C19,C20,C21,C22,C26,C27)=0,"",SUM(C19,C20,C21,C22,C26,C27)) | D28: =IF(COUNT(D19,D20,D21,D22,D26,D27)=0,"",SUM(D19,D20,D21,D22,D26,D27))
A29: Coût du travail et Dépenses de personnel externalisées (Honoraires, ..) | B29: =IF(ROUND(('Saisie TCR'!N36-'Saisie TCR'!M36) + ('Saisie TCR'!N28-'Saisie TCR'!M28) + ('Saisie TCR'!N29-'Saisie TCR'!M29),3)=0,"",ROUND(('Saisie TCR'!N36-'Saisie TCR'!M36) + ('Saisie TCR'!N28-'Saisie TCR'!M28) + ('Saisie TCR'!N29-'Saisie TCR'!M29),3)/1000) | C29: =IF(ROUND(('Saisie TCR'!L36-'Saisie TCR'!K36) + ('Saisie TCR'!L28-'Saisie TCR'!K28) + ('Saisie TCR'!L29-'Saisie TCR'!K29),3)=0,"",ROUND(('Saisie TCR'!L36-'Saisie TCR'!K36) + ('Saisie TCR'!L28-'Saisie TCR'!K28) + ('Saisie TCR'!L29-'Saisie TCR'!K29),3)/1000) | D29: =IF(ROUND(('Saisie TCR'!J36-'Saisie TCR'!I36) + ('Saisie TCR'!J28-'Saisie TCR'!I28) + ('Saisie TCR'!J29-'Saisie TCR'!I29),3)=0,"",ROUND(('Saisie TCR'!J36-'Saisie TCR'!I36) + ('Saisie TCR'!J28-'Saisie TCR'!I28) + ('Saisie TCR'!J29-'Saisie TCR'!I29),3)/1000)
A30: EBITDAR | B30: =IF(COUNT(B28,B29)=0,"",SUM(B28,B29)) | C30: =IF(COUNT(C28,C29)=0,"",SUM(C28,C29)) | D30: =IF(COUNT(D28,D29)=0,"",SUM(D28,D29))
A31: Loyers de location simple | B31: =IF(ROUND(('Saisie TCR'!N25-'Saisie TCR'!M25),3)=0,"",ROUND(('Saisie TCR'!N25-'Saisie TCR'!M25),3)/1000) | C31: =IF(ROUND(('Saisie TCR'!L25-'Saisie TCR'!K25),3)=0,"",ROUND(('Saisie TCR'!L25-'Saisie TCR'!K25),3)/1000) | D31: =IF(ROUND(('Saisie TCR'!J25-'Saisie TCR'!I25),3)=0,"",ROUND(('Saisie TCR'!J25-'Saisie TCR'!I25),3)/1000)
A32: EBITDA | B32: =IF(COUNT(B30,B31)=0,"",SUM(B30,B31)) | C32: =IF(COUNT(C30,C31)=0,"",SUM(C30,C31)) | D32: =IF(COUNT(D30,D31)=0,"",SUM(D30,D31))
A33: Dotation aux amort. des immo. Corporelles | B33: =IF(ROUND(('Saisie TCR'!N41-'Saisie TCR'!M41),3)=0,"",ROUND(('Saisie TCR'!N41-'Saisie TCR'!M41),3)/1000) | C33: =IF(ROUND(('Saisie TCR'!L41-'Saisie TCR'!K41),3)=0,"",ROUND(('Saisie TCR'!L41-'Saisie TCR'!K41),3)/1000) | D33: =IF(ROUND(('Saisie TCR'!J41-'Saisie TCR'!I41),3)=0,"",ROUND(('Saisie TCR'!J41-'Saisie TCR'!I41),3)/1000)
A34: Dotation aux amortissements des immo. Incorp.
A35: Dépréciation des immo corporelles et incorporelles
A36: Résultat opérationnel courant | B36: =IF(COUNT(B32,B33,B34,B35)=0,"",SUM(B32,B33,B34,B35)) | C36: =IF(COUNT(C32,C33,C34,C35)=0,"",SUM(C32,C33,C34,C35)) | D36: =IF(COUNT(D32,D33,D34,D35)=0,"",SUM(D32,D33,D34,D35))
A37: Dépréciation des actifs corporels et incorporels | B37: =IF(ROUND(('Saisie TCR'!N44-'Saisie TCR'!M44),3)=0,"",ROUND(('Saisie TCR'!N44-'Saisie TCR'!M44),3)/1000) | C37: =IF(ROUND(('Saisie TCR'!L44-'Saisie TCR'!K44),3)=0,"",ROUND(('Saisie TCR'!L44-'Saisie TCR'!K44),3)/1000) | D37: =IF(ROUND(('Saisie TCR'!J44-'Saisie TCR'!I44),3)=0,"",ROUND(('Saisie TCR'!J44-'Saisie TCR'!I44),3)/1000)
A38: Provisions / réserves | B38: =IF(ROUND(('Saisie TCR'!N42-'Saisie TCR'!M42) + ('Saisie TCR'!N43-'Saisie TCR'!M43),3)=0,"",ROUND(('Saisie TCR'!N42-'Saisie TCR'!M42) + ('Saisie TCR'!N43-'Saisie TCR'!M43),3)/1000) | C38: =IF(ROUND(('Saisie TCR'!L42-'Saisie TCR'!K42) + ('Saisie TCR'!L43-'Saisie TCR'!K43),3)=0,"",ROUND(('Saisie TCR'!L42-'Saisie TCR'!K42) + ('Saisie TCR'!L43-'Saisie TCR'!K43),3)/1000) | D38: =IF(ROUND(('Saisie TCR'!J42-'Saisie TCR'!I42) + ('Saisie TCR'!J43-'Saisie TCR'!I43),3)=0,"",ROUND(('Saisie TCR'!J42-'Saisie TCR'!I42) + ('Saisie TCR'!J43-'Saisie TCR'!I43),3)/1000)
A39: Charges de restructuration | B39: =IF(COUNT(B40,B41)=0,"",SUM(B40,B41)) | C39: =IF(COUNT(C40,C41)=0,"",SUM(C40,C41)) | D39: =IF(COUNT(D40,D41)=0,"",SUM(D40,D41))
A40: dont charges cash de l'année
A41: dont variation de provisions
A42: Produits / charges nets de cessions
A43: Autre Produits / Charges non récurrents | B43: =IF(COUNT(B44,B45)=0,"",SUM(B44,B45)) | C43: =IF(COUNT(C44,C45)=0,"",SUM(C44,C45)) | D43: =IF(COUNT(D44,D45)=0,"",SUM(D44,D45))
A44: dont Eléments cash | B44: =IF(ROUND(('Saisie TCR'!N50-'Saisie TCR'!M50) + ('Saisie TCR'!N51-'Saisie TCR'!M51),3)=0,"",ROUND(('Saisie TCR'!N50-'Saisie TCR'!M50) + ('Saisie TCR'!N51-'Saisie TCR'!M51),3)/1000) | C44: =IF(ROUND(('Saisie TCR'!L50-'Saisie TCR'!K50) + ('Saisie TCR'!L51-'Saisie TCR'!K51),3)=0,"",ROUND(('Saisie TCR'!L50-'Saisie TCR'!K50) + ('Saisie TCR'!L51-'Saisie TCR'!K51),3)/1000) | D44: =IF(ROUND(('Saisie TCR'!J50-'Saisie TCR'!I50) + ('Saisie TCR'!J51-'Saisie TCR'!I51),3)=0,"",ROUND(('Saisie TCR'!J50-'Saisie TCR'!I50) + ('Saisie TCR'!J51-'Saisie TCR'!I51),3)/1000)
A45: dont Eléments non cash
A46: Résult. opérationnel (yc élem non cour) | B46: =IF(COUNT(B36,B37,B38,B39,B42,B43)=0,"",SUM(B36,B37,B38,B39,B42,B43)) | C46: =IF(COUNT(C36,C37,C38,C39,C42,C43)=0,"",SUM(C36,C37,C38,C39,C42,C43)) | D46: =IF(COUNT(D36,D37,D38,D39,D42,D43)=0,"",SUM(D36,D37,D38,D39,D42,D43))
A47: Charges d'intérêts | B47: =IF(ROUND(('Saisie TCR'!N47-'Saisie TCR'!M47),3)=0,"",ROUND(('Saisie TCR'!N47-'Saisie TCR'!M47),3)/1000) | C47: =IF(ROUND(('Saisie TCR'!L47-'Saisie TCR'!K47),3)=0,"",ROUND(('Saisie TCR'!L47-'Saisie TCR'!K47),3)/1000) | D47: =IF(ROUND(('Saisie TCR'!J47-'Saisie TCR'!I47),3)=0,"",ROUND(('Saisie TCR'!J47-'Saisie TCR'!I47),3)/1000)
A48: Revenus d'intérêt / dividendes | B48: =IF(COUNT(B49,B50,B51,B52)=0,"",SUM(B49,B50,B51,B52)) | C48: =IF(COUNT(C49,C50,C51,C52)=0,"",SUM(C49,C50,C51,C52)) | D48: =IF(COUNT(D49,D50,D51,D52)=0,"",SUM(D49,D50,D51,D52))
A49: dont produit d'intérêt de la trésorerie
A50: dont Produit d'intérêt | B50: =IF(ROUND(('Saisie TCR'!N46-'Saisie TCR'!M46),3)=0,"",ROUND(('Saisie TCR'!N46-'Saisie TCR'!M46),3)/1000) | C50: =IF(ROUND(('Saisie TCR'!L46-'Saisie TCR'!K46),3)=0,"",ROUND(('Saisie TCR'!L46-'Saisie TCR'!K46),3)/1000) | D50: =IF(ROUND(('Saisie TCR'!J46-'Saisie TCR'!I46),3)=0,"",ROUND(('Saisie TCR'!J46-'Saisie TCR'!I46),3)/1000)
A51: dont dividendes
A52: dont Gains / Pertes en capital sur actifs financiers
A53: Désactualisation de provisions
A54: Réévaluation de la dette hybride
A55: Ajustements de valeur sur actifs financiers | B55: =IF(COUNT(B56,B57)=0,"",SUM(B56,B57)) | C55: =IF(COUNT(C56,C57)=0,"",SUM(C56,C57)) | D55: =IF(COUNT(D56,D57)=0,"",SUM(D56,D57))
A56: dont Dérivés
A57: dont autres
A58: Autres produits et charges financières | B58: =IF(COUNT(B59,B60)=0,"",SUM(B59,B60)) | C58: =IF(COUNT(C59,C60)=0,"",SUM(C59,C60)) | D58: =IF(COUNT(D59,D60)=0,"",SUM(D59,D60))
A59: dont Gains / Pertes liés au change
A60: dont Autres
A61: Résultat financier net | B61: =IF(COUNT(B47,B48,B53,B54,B55,B58)=0,"",SUM(B47,B48,B53,B54,B55,B58)) | C61: =IF(COUNT(C47,C48,C53,C54,C55,C58)=0,"",SUM(C47,C48,C53,C54,C55,C58)) | D61: =IF(COUNT(D47,D48,D53,D54,D55,D58)=0,"",SUM(D47,D48,D53,D54,D55,D58))
A62: Résultat avant impôts | B62: =IF(COUNT(B46,B61)=0,"",SUM(B46,B61)) | C62: =IF(COUNT(C46,C61)=0,"",SUM(C46,C61)) | D62: =IF(COUNT(D46,D61)=0,"",SUM(D46,D61))
A63: Impôts | B63: =IF(COUNT(B64,B65)=0,"",SUM(B64,B65)) | C63: =IF(COUNT(C64,C65)=0,"",SUM(C64,C65)) | D63: =IF(COUNT(D64,D65)=0,"",SUM(D64,D65))
A64: dont Impôts courants | B64: =IF(ROUND(('Saisie TCR'!N53-'Saisie TCR'!M53),3)=0,"",ROUND(('Saisie TCR'!N53-'Saisie TCR'!M53),3)/1000) | C64: =IF(ROUND(('Saisie TCR'!L53-'Saisie TCR'!K53),3)=0,"",ROUND(('Saisie TCR'!L53-'Saisie TCR'!K53),3)/1000) | D64: =IF(ROUND(('Saisie TCR'!J53-'Saisie TCR'!I53),3)=0,"",ROUND(('Saisie TCR'!J53-'Saisie TCR'!I53),3)/1000)
A65: dont Impôts différés | B65: =IF(ROUND(('Saisie TCR'!N54-'Saisie TCR'!M54),3)=0,"",ROUND(('Saisie TCR'!N54-'Saisie TCR'!M54),3)/1000) | C65: =IF(ROUND(('Saisie TCR'!L54-'Saisie TCR'!K54),3)=0,"",ROUND(('Saisie TCR'!L54-'Saisie TCR'!K54),3)/1000) | D65: =IF(ROUND(('Saisie TCR'!J54-'Saisie TCR'!I54),3)=0,"",ROUND(('Saisie TCR'!J54-'Saisie TCR'!I54),3)/1000)
A66: Quote part des résult. soc. mises en équiv.
A67: Résultat des activités cédées ou à céder
A68: Résultat net | B68: =IF(COUNT(B62,B63,B66,B67)=0,"",SUM(B62,B63,B66,B67)) | C68: =IF(COUNT(C62,C63,C66,C67)=0,"",SUM(C62,C63,C66,C67)) | D68: =IF(COUNT(D62,D63,D66,D67)=0,"",SUM(D62,D63,D66,D67))
A69: dont Intérêts minoritaires
A70: dont Résultat net (perte) > part du groupe | B70: =IF(COUNT(B68,B69)=0,"",B68-SUM(B69)) | C70: =IF(COUNT(C68,C69)=0,"",C68-SUM(C69)) | D70: =IF(COUNT(D68,D69)=0,"",D68-SUM(D69))
A71: Dividendes votés
A72: Bénéfice non distribué | B72: =IF(COUNT(B68,B71)=0,"",B68-SUM(B71)) | C72: =IF(COUNT(C68,C71)=0,"",C68-SUM(C71)) | D72: =IF(COUNT(D68,D71)=0,"",D68-SUM(D71))

Sheet Tableau de Flux de Trésorerie
A1: WORKSHEET: Corporate - Standard | B1: Créé le | D1: Analyste : | E1: =IF('Bilan - Actifs'!E1="","",'Bilan - Actifs'!E1) | F1: Site : | G1: ALGERIE
A3: Source de données | B3: OWN | C3: OWN | D3: OWN
A4: Type | B4: Annuel | C4: Annuel | D4: Annuel
A5: Date de clôture
A6: Date de début
A7: Durée
A8: Durée | B8: 12 mois | C8: 12 mois | D8: 12 mois
A9: Statut de la consolidation | B9: Social | C9: Social | D9: Social
A10: Norme comptable | B10: Local Gaap | C10: Local Gaap | D10: Local Gaap
A11: Unité/ Devise affichée | B11: Million DZD | C11: Million DZD | D11: Million DZD
A12: Opinion | B12: Comptes non audités | C12: Comptes non audités | D12: Comptes non audités
A13: Date de Publication
B14: Valeur | C14: Valeur | D14: Valeur
A16: Point de départ = EBITDA
A17: EBITDA (Calcul Add-Back) | B17: =IF(ISNUMBER('Compte de résultat'!B32),'Compte de résultat'!B32,"") | C17: =IF(ISNUMBER('Compte de résultat'!C32),'Compte de résultat'!C32,"") | D17: =IF(ISNUMBER('Compte de résultat'!D32),'Compte de résultat'!D32,"")
A18: Charge d'intérêts versée | B18: =IF(ROUND(('Saisie TCR'!N47-'Saisie TCR'!M47),3)=0,"",ROUND(('Saisie TCR'!N47-'Saisie TCR'!M47),3)/1000) | C18: =IF(ROUND(('Saisie TCR'!L47-'Saisie TCR'!K47),3)=0,"",ROUND(('Saisie TCR'!L47-'Saisie TCR'!K47),3)/1000) | D18: =IF(ROUND(('Saisie TCR'!J47-'Saisie TCR'!I47),3)=0,"",ROUND(('Saisie TCR'!J47-'Saisie TCR'!I47),3)/1000)
A19: Impôts payés | B19: =IF(ISNUMBER('Compte de résultat'!B64),'Compte de résultat'!B64,"") | C19: =IF(ISNUMBER('Compte de résultat'!C64),'Compte de résultat'!C64,"") | D19: =IF(ISNUMBER('Compte de résultat'!D64),'Compte de résultat'!D64,"")
A20: Ajustements non cash | B20: =IF(COUNT(B22,B24,B26,B28,B30)=0,"",SUM(B22,B24,B26,B28,B30)) | C20: =IF(COUNT(C22,C24,C26,C28,C30)=0,"",SUM(C22,C24,C26,C28,C30)) | D20: =IF(COUNT(D22,D24,D26,D28,D30)=0,"",SUM(D22,D24,D26,D28,D30))
A21: libellé dont
A22: donr
A23: libellé dont
A24: donr
A25: libellé dont
A26: donr
A27: libellé dont
A28: donr
A29: libellé dont
A30: donr
A31: Marge brute d'autofinancement | B31: =IF(COUNT(B17,B18,B19,B20)=0,"",SUM(B17,B18,B19,B20)) | C31: =IF(COUNT(C17,C18,C19,C20)=0,"",SUM(C17,C18,C19,C20)) | D31: =IF(COUNT(D17,D18,D19,D20)=0,"",SUM(D17,D18,D19,D20))
A32: Variation du BFR | B32: =IF(COUNT(B33,B34,B35,B36,B37,B38)=0,"",SUM(B33,B34,B35,B36,B37,B38)) | C32: =IF(COUNT(C33,C34,C35,C36,C37,C38)=0,"",SUM(C33,C34,C35,C36,C37,C38)) | D32: =IF(COUNT(D33,D34,D35,D36,D37,D38)=0,"",SUM(D33,D34,D35,D36,D37,D38))
A33: dont Variation de stocks | B33: =IF(ROUND(-('Saisie actif'!P26 - 'Saisie actif'!M26),3)=0,"",ROUND(-('Saisie actif'!P26 - 'Saisie actif'!M26),3)/1000) | C33: =IF(ROUND(-('Saisie actif'!M26 - 'Saisie actif'!J26),3)=0,"",ROUND(-('Saisie actif'!M26 - 'Saisie actif'!J26),3)/1000) | D33: =IF(ROUND(-('Saisie actif'!J26 - 'Saisie actif'!G26),3)=0,"",ROUND(-('Saisie actif'!J26 - 'Saisie actif'!G26),3)/1000)
A34: dont Variation des créances d'exploitation | B34: =IF(ROUND(-('Saisie actif'!P28 - 'Saisie actif'!M28),3)=0,"",ROUND(-('Saisie actif'!P28 - 'Saisie actif'!M28),3)/1000) | C34: =IF(ROUND(-('Saisie actif'!M28 - 'Saisie actif'!J28),3)=0,"",ROUND(-('Saisie actif'!M28 - 'Saisie actif'!J28),3)/1000) | D34: =IF(ROUND(-('Saisie actif'!J28 - 'Saisie actif'!G28),3)=0,"",ROUND(-('Saisie actif'!J28 - 'Saisie actif'!G28),3)/1000)
A35: dont Var. des dettes formes et assim | B35: =IF(ROUND('Saisie passif'!H23 - 'Saisie passif'!G23,3)=0,"",ROUND('Saisie passif'!H23 - 'Saisie passif'!G23,3)/1000) | C35: =IF(ROUND('Saisie passif'!G23 - 'Saisie passif'!F23,3)=0,"",ROUND('Saisie passif'!G23 - 'Saisie passif'!F23,3)/1000) | D35: =IF(ROUND('Saisie passif'!F23 - 'Saisie passif'!E23,3)=0,"",ROUND('Saisie passif'!F23 - 'Saisie passif'!E23,3)/1000)
A36: dont Variation des dettes sur services consommés
A37: dont Autres variations de BFR | B37: =IF(ROUND(-(('Saisie actif'!R29 + 'Saisie actif'!R31) - ('Saisie actif'!O29 + 'Saisie actif'!O31)) + ('Saisie passif'!H24 + 'Saisie passif'!H25) - ('Saisie passif'!G24 + 'Saisie passif'!G25),3)=0,"",ROUND(-(('Saisie actif'!R29 + 'Saisie actif'!R31) - ('Saisie actif'!O29 + 'Saisie actif'!O31)) + ('Saisie passif'!H24 + 'Saisie passif'!H25) - ('Saisie passif'!G24 + 'Saisie passif'!G25),3)/1000) | C37: =IF(ROUND(-(('Saisie actif'!O29 + 'Saisie actif'!O31) - ('Saisie actif'!L29 + 'Saisie actif'!L31)) + ('Saisie passif'!G24 + 'Saisie passif'!G25) - ('Saisie passif'!F24 + 'Saisie passif'!F25),3)=0,"",ROUND(-(('Saisie actif'!O29 + 'Saisie actif'!O31) - ('Saisie actif'!L29 + 'Saisie actif'!L31)) + ('Saisie passif'!G24 + 'Saisie passif'!G25) - ('Saisie passif'!F24 + 'Saisie passif'!F25),3)/1000) | D37: =IF(ROUND(-(('Saisie actif'!L29 + 'Saisie actif'!L31) - ('Saisie actif'!I29 + 'Saisie actif'!I31)) + ('Saisie passif'!F24 + 'Saisie passif'!F25) - ('Saisie passif'!E24 + 'Saisie passif'!E25),3)=0,"",ROUND(-(('Saisie actif'!L29 + 'Saisie actif'!L31) - ('Saisie actif'!I29 + 'Saisie actif'!I31)) + ('Saisie passif'!F24 + 'Saisie passif'!F25) - ('Saisie passif'!E24 + 'Saisie passif'!E25),3)/1000)
A38: dont autres | B38: =IF(ROUND(-('Saisie actif'!R30 - 'Saisie actif'!O30),3)=0,"",ROUND(-('Saisie actif'!R30 - 'Saisie actif'!O30),3)/1000) | C38: =IF(ROUND(-('Saisie actif'!O30 - 'Saisie actif'!L30),3)=0,"",ROUND(-('Saisie actif'!O30 - 'Saisie actif'!L30),3)/1000) | D38: =IF(ROUND(-('Saisie actif'!L30 - 'Saisie actif'!I30),3)=0,"",ROUND(-('Saisie actif'!L30 - 'Saisie actif'!I30),3)/1000)
A39: Cash Flow Opérationnel (CFO) net | B39: =IF(COUNT(B31,B32)=0,"",SUM(B31,B32)) | C39: =IF(COUNT(C31,C32)=0,"",SUM(C31,C32)) | D39: =IF(COUNT(D31,D32)=0,"",SUM(D31,D32))
A40: Dépenses d'investissement (CAPEX) | B40: =IF(COUNT(B41,B42)=0,"",SUM(B41,B42)) | C40: =IF(COUNT(C41,C42)=0,"",SUM(C41,C42)) | D40: =IF(COUNT(D41,D42)=0,"",SUM(D41,D42))
A41: dont investissement de remplacement | B41: =IF(ROUND(-(('Saisie actif'!P11 + 'Saisie actif'!P13 + 'Saisie actif'!P14 + 'Saisie actif'!P15 + 'Saisie actif'!P16 + 'Saisie actif'!P17) - ('Saisie actif'!M11 + 'Saisie actif'!M13 + 'Saisie actif'!M14 + 'Saisie actif'!M15 + 'Saisie actif'!M16 + 'Saisie actif'!M17)),3)=0,"",ROUND(-(('Saisie actif'!P11 + 'Saisie actif'!P13 + 'Saisie actif'!P14 + 'Saisie actif'!P15 + 'Saisie actif'!P16 + 'Saisie actif'!P17) - ('Saisie actif'!M11 + 'Saisie actif'!M13 + 'Saisie actif'!M14 + 'Saisie actif'!M15 + 'Saisie actif'!M16 + 'Saisie actif'!M17)),3)/1000) | C41: =IF(ROUND(-(('Saisie actif'!M11 + 'Saisie actif'!M13 + 'Saisie actif'!M14 + 'Saisie actif'!M15 + 'Saisie actif'!M16 + 'Saisie actif'!M17) - ('Saisie actif'!J11 + 'Saisie actif'!J13 + 'Saisie actif'!J14 + 'Saisie actif'!J15 + 'Saisie actif'!J16 + 'Saisie actif'!J17)),3)=0,"",ROUND(-(('Saisie actif'!M11 + 'Saisie actif'!M13 + 'Saisie actif'!M14 + 'Saisie actif'!M15 + 'Saisie actif'!M16 + 'Saisie actif'!M17) - ('Saisie actif'!J11 + 'Saisie actif'!J13 + 'Saisie actif'!J14 + 'Saisie actif'!J15 + 'Saisie actif'!J16 + 'Saisie actif'!J17)),3)/1000) | D41: =IF(ROUND(-(('Saisie actif'!J11 + 'Saisie actif'!J13 + 'Saisie actif'!J14 + 'Saisie actif'!J15 + 'Saisie actif'!J16 + 'Saisie actif'!J17) - ('Saisie actif'!G11 + 'Saisie actif'!G13 + 'Saisie actif'!G14 + 'Saisie actif'!G15 + 'Saisie actif'!G16 + 'Saisie actif'!G17)),3)=0,"",ROUND(-(('Saisie actif'!J11 + 'Saisie actif'!J13 + 'Saisie actif'!J14 + 'Saisie actif'!J15 + 'Saisie actif'!J16 + 'Saisie actif'!J17) - ('Saisie actif'!G11 + 'Saisie actif'!G13 + 'Saisie actif'!G14 + 'Saisie actif'!G15 + 'Saisie actif'!G16 + 'Saisie actif'!G17)),3)/1000)
A42: dont investissement productif
A43: Revenus d'investissement | B43: =IF(ROUND(('Saisie TCR'!N46-'Saisie TCR'!M46),3)=0,"",ROUND(('Saisie TCR'!N46-'Saisie TCR'!M46),3)/1000) | C43: =IF(ROUND(('Saisie TCR'!L46-'Saisie TCR'!K46),3)=0,"",ROUND(('Saisie TCR'!L46-'Saisie TCR'!K46),3)/1000) | D43: =IF(ROUND(('Saisie TCR'!J46-'Saisie TCR'!I46),3)=0,"",ROUND(('Saisie TCR'!J46-'Saisie TCR'!I46),3)/1000)
A44: Autres revenus / charges (seuls éléments cash)
A45: Remboursements obligatoires de dette | B45: =IF(COUNT(B46,B47)=0,"",SUM(B46,B47)) | C45: =IF(COUNT(C46,C47)=0,"",SUM(C46,C47)) | D45: =IF(COUNT(D46,D47)=0,"",SUM(D46,D47))
A46: dont Remb. oblig. sur contrats loc.-financement
A47: dont autres remboursements obligatoires
A48: Flux de trésorerie disp. après serv. dette | B48: =IF(COUNT(B39,B40,B43,B44,B45)=0,"",SUM(B39,B40,B43,B44,B45)) | C48: =IF(COUNT(C39,C40,C43,C44,C45)=0,"",SUM(C39,C40,C43,C44,C45)) | D48: =IF(COUNT(D39,D40,D43,D44,D45)=0,"",SUM(D39,D40,D43,D44,D45))
A49: Acquisitions
A50: Cessions | B50: =IF(COUNT(B51,B52,B53,B54)=0,"",SUM(B51,B52,B53,B54)) | C50: =IF(COUNT(C51,C52,C53,C54)=0,"",SUM(C51,C52,C53,C54)) | D50: =IF(COUNT(D51,D52,D53,D54)=0,"",SUM(D51,D52,D53,D54))
A51: dont vente d'actifs corporels
A52: dont vente d'actifs incorporels
A53: dont Ventes D'Activités et D'Immobilisations Financières
A54: dont autres (si ventilation indisponible)
A55: Dividendes payés | B55: =IF(ROUND(-('Saisie passif'!G11 - (('Saisie passif'!H8 + 'Saisie passif'!H12) - ('Saisie passif'!G8 + 'Saisie passif'!G12))),3)=0,"",ROUND(-('Saisie passif'!G11 - (('Saisie passif'!H8 + 'Saisie passif'!H12) - ('Saisie passif'!G8 + 'Saisie passif'!G12))),3)/1000) | C55: =IF(ROUND(-('Saisie passif'!F11 - (('Saisie passif'!G8 + 'Saisie passif'!G12) - ('Saisie passif'!F8 + 'Saisie passif'!F12))),3)=0,"",ROUND(-('Saisie passif'!F11 - (('Saisie passif'!G8 + 'Saisie passif'!G12) - ('Saisie passif'!F8 + 'Saisie passif'!F12))),3)/1000) | D55: =IF(ROUND(-('Saisie passif'!E11 - (('Saisie passif'!F8 + 'Saisie passif'!F12) - ('Saisie passif'!E8 + 'Saisie passif'!E12))),3)=0,"",ROUND(-('Saisie passif'!E11 - (('Saisie passif'!F8 + 'Saisie passif'!F12) - ('Saisie passif'!E8 + 'Saisie passif'!E12))),3)/1000)
A56: dont Dividendes exceptionnels
A57: Variation en capital | B57: =IF(COUNT(B58,B59,B60)=0,"",SUM(B58,B59,B60)) | C57: =IF(COUNT(C58,C59,C60)=0,"",SUM(C58,C59,C60)) | D57: =IF(COUNT(D58,D59,D60)=0,"",SUM(D58,D59,D60))
A58: dont Augmentation de Capital | B58: =IF(ROUND(('Saisie passif'!H6 - 'Saisie passif'!H7) - ('Saisie passif'!G6 - 'Saisie passif'!G7),3)=0,"",ROUND(('Saisie passif'!H6 - 'Saisie passif'!H7) - ('Saisie passif'!G6 - 'Saisie passif'!G7),3)/1000) | C58: =IF(ROUND(('Saisie passif'!G6 - 'Saisie passif'!G7) - ('Saisie passif'!F6 - 'Saisie passif'!F7),3)=0,"",ROUND(('Saisie passif'!G6 - 'Saisie passif'!G7) - ('Saisie passif'!F6 - 'Saisie passif'!F7),3)/1000) | D58: =IF(ROUND(('Saisie passif'!F6 - 'Saisie passif'!F7) - ('Saisie passif'!E6 - 'Saisie passif'!E7),3)=0,"",ROUND(('Saisie passif'!F6 - 'Saisie passif'!F7) - ('Saisie passif'!E6 - 'Saisie passif'!E7),3)/1000)
A59: dont Rachat d'actions
A60: dont cessions / acquisitions d'actions d'autocontrôle
A61: Flux liés aux minoritaires | B61: =IF(COUNT(B62,B63)=0,"",SUM(B62,B63)) | C61: =IF(COUNT(C62,C63)=0,"",SUM(C62,C63)) | D61: =IF(COUNT(D62,D63)=0,"",SUM(D62,D63))
A62: dont dividendes
A63: dont Autres
A64: Nouv. dettes&Remb. non oblig. dettes non cour. | B64: =IF(COUNT(B65,B66)=0,"",SUM(B65,B66)) | C64: =IF(COUNT(C65,C66)=0,"",SUM(C65,C66)) | D64: =IF(COUNT(D65,D66)=0,"",SUM(D65,D66))
A65: dont liées aux contrats de location financement
A66: dont autres nouvelles dettes et autres remboursements | B66: =IF(ROUND(('Saisie passif'!H17 + 'Saisie passif'!H19) - ('Saisie passif'!G17 + 'Saisie passif'!G19),3)=0,"",ROUND(('Saisie passif'!H17 + 'Saisie passif'!H19) - ('Saisie passif'!G17 + 'Saisie passif'!G19),3)/1000) | C66: =IF(ROUND(('Saisie passif'!G17 + 'Saisie passif'!G19) - ('Saisie passif'!F17 + 'Saisie passif'!F19),3)=0,"",ROUND(('Saisie passif'!G17 + 'Saisie passif'!G19) - ('Saisie passif'!F17 + 'Saisie passif'!F19),3)/1000) | D66: =IF(ROUND(('Saisie passif'!F17 + 'Saisie passif'!F19) - ('Saisie passif'!E17 + 'Saisie passif'!E19),3)=0,"",ROUND(('Saisie passif'!F17 + 'Saisie passif'!F19) - ('Saisie passif'!E17 + 'Saisie passif'!E19),3)/1000)
A67: Eléments exceptionnels | B67: =IF(ROUND(('Saisie TCR'!N50-'Saisie TCR'!M50) + ('Saisie TCR'!N51-'Saisie TCR'!M51),3)=0,"",ROUND(('Saisie TCR'!N50-'Saisie TCR'!M50) + ('Saisie TCR'!N51-'Saisie TCR'!M51),3)/1000) | C67: =IF(ROUND(('Saisie TCR'!L50-'Saisie TCR'!K50) + ('Saisie TCR'!L51-'Saisie TCR'!K51),3)=0,"",ROUND(('Saisie TCR'!L50-'Saisie TCR'!K50) + ('Saisie TCR'!L51-'Saisie TCR'!K51),3)/1000) | D67: =IF(ROUND(('Saisie TCR'!J50-'Saisie TCR'!I50) + ('Saisie TCR'!J51-'Saisie TCR'!I51),3)=0,"",ROUND(('Saisie TCR'!J50-'Saisie TCR'!I50) + ('Saisie TCR'!J51-'Saisie TCR'!I51),3)/1000)
A68: Flux liés Actifs Détenus en Vue de la Vente
A69: Immobilisations financières nettes | B69: =IF(ROUND(-(('Saisie actif'!R18 - 'Saisie actif'!R23) - ('Saisie actif'!O18 - 'Saisie actif'!O23)),3)=0,"",ROUND(-(('Saisie actif'!R18 - 'Saisie actif'!R23) - ('Saisie actif'!O18 - 'Saisie actif'!O23)),3)/1000) | C69: =IF(ROUND(-(('Saisie actif'!O18 - 'Saisie actif'!O23) - ('Saisie actif'!L18 - 'Saisie actif'!L23)),3)=0,"",ROUND(-(('Saisie actif'!O18 - 'Saisie actif'!O23) - ('Saisie actif'!L18 - 'Saisie actif'!L23)),3)/1000) | D69: =IF(ROUND(-(('Saisie actif'!L18 - 'Saisie actif'!L23) - ('Saisie actif'!I18 - 'Saisie actif'!I23)),3)=0,"",ROUND(-(('Saisie actif'!L18 - 'Saisie actif'!L23) - ('Saisie actif'!I18 - 'Saisie actif'!I23)),3)/1000)
A70: Impact des effets de change
A71: Impact des effets de changement de périmètre
A72: Autres
A73: Sum of Non Recur. Flows Bef. ST Debt's Change | B73: =IF(COUNT(B49,B50,B55,B57,B61,B64,B67,B68,B69,B70,B71,B72)=0,"",SUM(B49,B50,B55,B57,B61,B64,B67,B68,B69,B70,B71,B72)) | C73: =IF(COUNT(C49,C50,C55,C57,C61,C64,C67,C68,C69,C70,C71,C72)=0,"",SUM(C49,C50,C55,C57,C61,C64,C67,C68,C69,C70,C71,C72)) | D73: =IF(COUNT(D49,D50,D55,D57,D61,D64,D67,D68,D69,D70,D71,D72)=0,"",SUM(D49,D50,D55,D57,D61,D64,D67,D68,D69,D70,D71,D72))
A74: Variation de la dette courante | B74: =IF(ROUND('Saisie passif'!H26 - 'Saisie passif'!G26,3)=0,"",ROUND('Saisie passif'!H26 - 'Saisie passif'!G26,3)/1000) | C74: =IF(ROUND('Saisie passif'!G26 - 'Saisie passif'!F26,3)=0,"",ROUND('Saisie passif'!G26 - 'Saisie passif'!F26,3)/1000) | D74: =IF(ROUND('Saisie passif'!F26 - 'Saisie passif'!E26,3)=0,"",ROUND('Saisie passif'!F26 - 'Saisie passif'!E26,3)/1000)
A75: Variation de trésorerie | B75: =IF(COUNT(B48,B73,B74)=0,"",SUM(B48,B73,B74)) | C75: =IF(COUNT(C48,C73,C74)=0,"",SUM(C48,C73,C74)) | D75: =IF(COUNT(D48,D73,D74)=0,"",SUM(D48,D73,D74))
A76: Flux de trésorerie disp. av. service dette | B76: =IF(COUNT(B48,B18)=0,"",B48-SUM(B18)) | C76: =IF(COUNT(C48,C18)=0,"",C48-SUM(C18)) | D76: =IF(COUNT(D48,D18)=0,"",D48-SUM(D18))
A77: Concours Bancaires
A78: Réconciliation avec la variation de cash au bilan | B78: =IF(COUNT(B75,'Bilan - Actifs'!B81,'Bilan - Actifs'!C81)<3,"NA",IF(ABS(B75-('Bilan - Actifs'!B81-'Bilan - Actifs'!C81))<=0.011,"OK","Gap")) | C78: =IF(COUNT(C75,'Bilan - Actifs'!C81,'Bilan - Actifs'!D81)<3,"NA",IF(ABS(C75-('Bilan - Actifs'!C81-'Bilan - Actifs'!D81))<=0.011,"OK","Gap")) | D78: NA

Sheet Ratios & Aggregates
A1: WORKSHEET: Corporate - Standard | E1: Créé le | G1: Analyste : | H1: =IF('Bilan - Actifs'!E1="","",'Bilan - Actifs'!E1) | I1: Site : | J1: ALGERIE
A3: Source de données | E3: OWN | F3: OWN | G3: OWN
A4: Type | E4: Annuel | F4: Annuel | G4: Annuel
A5: Date de clôture
A6: Date de début
A7: Durée
A8: Durée | E8: 12 mois | F8: 12 mois | G8: 12 mois
A9: Statut de la consolidation | E9: Social | F9: Social | G9: Social
A10: Norme comptable | E10: Local Gaap | F10: Local Gaap | G10: Local Gaap
A11: Unité/ Devise affichée | E11: Million DZD | F11: Million DZD | G11: Million DZD
A12: Opinion | E12: Comptes non audités | F12: Comptes non audités | G12: Comptes non audités
A13: Date de Publication
E14: Valeur | F14: Valeur | G14: Valeur
A16: Working Capital Requirement | E16: =IF(COUNT('Bilan - Actifs'!B55,'Bilan - Actifs'!B68,'Bilan - Actifs'!B75,'Bilan - Passifs'!B67,'Bilan - Passifs'!B68,'Bilan - Passifs'!B75)=0,"",IFERROR(ROUND(SUM('Bilan - Actifs'!B55,'Bilan - Actifs'!B68,'Bilan - Actifs'!B75)-SUM('Bilan - Passifs'!B67,'Bilan - Passifs'!B68,'Bilan - Passifs'!B75),1),"")) | F16: =IF(COUNT('Bilan - Actifs'!C55,'Bilan - Actifs'!C68,'Bilan - Actifs'!C75,'Bilan - Passifs'!C67,'Bilan - Passifs'!C68,'Bilan - Passifs'!C75)=0,"",IFERROR(ROUND(SUM('Bilan - Actifs'!C55,'Bilan - Actifs'!C68,'Bilan - Actifs'!C75)-SUM('Bilan - Passifs'!C67,'Bilan - Passifs'!C68,'Bilan - Passifs'!C75),1),"")) | G16: =IF(COUNT('Bilan - Actifs'!D55,'Bilan - Actifs'!D68,'Bilan - Actifs'!D75,'Bilan - Passifs'!D67,'Bilan - Passifs'!D68,'Bilan - Passifs'!D75)=0,"",IFERROR(ROUND(SUM('Bilan - Actifs'!D55,'Bilan - Actifs'!D68,'Bilan - Actifs'!D75)-SUM('Bilan - Passifs'!D67,'Bilan - Passifs'!D68,'Bilan - Passifs'!D75),1),""))
A17: Dette totale | E17: =IF(COUNT('Bilan - Passifs'!B43,'Bilan - Passifs'!B53)=0,"",IFERROR(ROUND(('Bilan - Passifs'!B43+'Bilan - Passifs'!B53),1),"")) | F17: =IF(COUNT('Bilan - Passifs'!C43,'Bilan - Passifs'!C53)=0,"",IFERROR(ROUND(('Bilan - Passifs'!C43+'Bilan - Passifs'!C53),1),"")) | G17: =IF(COUNT('Bilan - Passifs'!D43,'Bilan - Passifs'!D53)=0,"",IFERROR(ROUND(('Bilan - Passifs'!D43+'Bilan - Passifs'!D53),1),""))
A18: Dette totale ajustée
A19: Dette nette | E19: =IF(COUNT('Bilan - Passifs'!B43,'Bilan - Passifs'!B53,'Bilan - Actifs'!B81)=0,"",IFERROR(ROUND(('Bilan - Passifs'!B43+'Bilan - Passifs'!B53)-'Bilan - Actifs'!B81,1),"")) | F19: =IF(COUNT('Bilan - Passifs'!C43,'Bilan - Passifs'!C53,'Bilan - Actifs'!C81)=0,"",IFERROR(ROUND(('Bilan - Passifs'!C43+'Bilan - Passifs'!C53)-'Bilan - Actifs'!C81,1),"")) | G19: =IF(COUNT('Bilan - Passifs'!D43,'Bilan - Passifs'!D53,'Bilan - Actifs'!D81)=0,"",IFERROR(ROUND(('Bilan - Passifs'!D43+'Bilan - Passifs'!D53)-'Bilan - Actifs'!D81,1),""))
A20: Dette nette ajustée
A21: Dette "Secured"
A22: Dette Senior
A23: Variation de la Dette nette | E23: =IF(COUNT('Bilan - Passifs'!B43,'Bilan - Passifs'!B53,'Bilan - Actifs'!B81,'Bilan - Passifs'!C43,'Bilan - Passifs'!C53,'Bilan - Actifs'!C81)=0,"",IFERROR(ROUND((('Bilan - Passifs'!B43+'Bilan - Passifs'!B53)-'Bilan - Actifs'!B81)-(('Bilan - Passifs'!C43+'Bilan - Passifs'!C53)-'Bilan - Actifs'!C81),1),"")) | F23: =IF(COUNT('Bilan - Passifs'!C43,'Bilan - Passifs'!C53,'Bilan - Actifs'!C81,'Bilan - Passifs'!D43,'Bilan - Passifs'!D53,'Bilan - Actifs'!D81)=0,"",IFERROR(ROUND((('Bilan - Passifs'!C43+'Bilan - Passifs'!C53)-'Bilan - Actifs'!C81)-(('Bilan - Passifs'!D43+'Bilan - Passifs'!D53)-'Bilan - Actifs'!D81),1),""))
A24: Situation Nette | E24: =IF(COUNT('Bilan - Passifs'!B35,'Bilan - Actifs'!B16,'Bilan - Actifs'!B17)=0,"",IFERROR(ROUND('Bilan - Passifs'!B35-SUM('Bilan - Actifs'!B16,'Bilan - Actifs'!B17),1),"")) | F24: =IF(COUNT('Bilan - Passifs'!C35,'Bilan - Actifs'!C16,'Bilan - Actifs'!C17)=0,"",IFERROR(ROUND('Bilan - Passifs'!C35-SUM('Bilan - Actifs'!C16,'Bilan - Actifs'!C17),1),"")) | G24: =IF(COUNT('Bilan - Passifs'!D35,'Bilan - Actifs'!D16,'Bilan - Actifs'!D17)=0,"",IFERROR(ROUND('Bilan - Passifs'!D35-SUM('Bilan - Actifs'!D16,'Bilan - Actifs'!D17),1),""))
A25: Couverture
A26: Résultat opérationnel/ Dépense d'intérêt | E26: =IF(COUNT('Compte de résultat'!B36,'Compte de résultat'!B47)=0,"",IFERROR(ROUND('Compte de résultat'!B36/ABS('Compte de résultat'!B47),1),"")) | F26: =IF(COUNT('Compte de résultat'!C36,'Compte de résultat'!C47)=0,"",IFERROR(ROUND('Compte de résultat'!C36/ABS('Compte de résultat'!C47),1),"")) | G26: =IF(COUNT('Compte de résultat'!D36,'Compte de résultat'!D47)=0,"",IFERROR(ROUND('Compte de résultat'!D36/ABS('Compte de résultat'!D47),1),""))
A27: EBITDA/ Charge d'intérêt | E27: =IF(COUNT('Compte de résultat'!B32,'Compte de résultat'!B47)=0,"",IFERROR(ROUND('Compte de résultat'!B32/ABS('Compte de résultat'!B47),1),"")) | F27: =IF(COUNT('Compte de résultat'!C32,'Compte de résultat'!C47)=0,"",IFERROR(ROUND('Compte de résultat'!C32/ABS('Compte de résultat'!C47),1),"")) | G27: =IF(COUNT('Compte de résultat'!D32,'Compte de résultat'!D47)=0,"",IFERROR(ROUND('Compte de résultat'!D32/ABS('Compte de résultat'!D47),1),""))
A28: EBITDA/ service de la dette | E28: =IF(COUNT('Compte de résultat'!B32,'Tableau de Flux de Trésorerie'!B18)=0,"",IFERROR(ROUND(-'Compte de résultat'!B32/'Tableau de Flux de Trésorerie'!B18,1),"")) | F28: =IF(COUNT('Compte de résultat'!C32,'Tableau de Flux de Trésorerie'!C18)=0,"",IFERROR(ROUND(-'Compte de résultat'!C32/'Tableau de Flux de Trésorerie'!C18,1),"")) | G28: =IF(COUNT('Compte de résultat'!D32,'Tableau de Flux de Trésorerie'!D18)=0,"",IFERROR(ROUND(-'Compte de résultat'!D32/'Tableau de Flux de Trésorerie'!D18,1),""))
A29: Charge d'intérêt / Moyenne pondérée de la dette sur deux ans | E29: =IF(COUNT('Compte de résultat'!B47,'Bilan - Passifs'!B43,'Bilan - Passifs'!B53,'Bilan - Passifs'!C43,'Bilan - Passifs'!C53)=0,"",IFERROR(ROUND(ABS('Compte de résultat'!B47)/AVERAGE(('Bilan - Passifs'!B43+'Bilan - Passifs'!B53),('Bilan - Passifs'!C43+'Bilan - Passifs'!C53)),1),"")) | F29: =IF(COUNT('Compte de résultat'!C47,'Bilan - Passifs'!C43,'Bilan - Passifs'!C53,'Bilan - Passifs'!D43,'Bilan - Passifs'!D53)=0,"",IFERROR(ROUND(ABS('Compte de résultat'!C47)/AVERAGE(('Bilan - Passifs'!C43+'Bilan - Passifs'!C53),('Bilan - Passifs'!D43+'Bilan - Passifs'!D53)),1),""))
A30: Couverture des charges fixes | E30: =IF(ISNUMBER(E28),E28,"") | F30: =IF(ISNUMBER(F28),F28,"") | G30: =IF(ISNUMBER(G28),G28,"")
A31: CFO net/ Service dette | E31: =IF(COUNT('Tableau de Flux de Trésorerie'!B39,'Tableau de Flux de Trésorerie'!B18)=0,"",IFERROR(ROUND(-'Tableau de Flux de Trésorerie'!B39/'Tableau de Flux de Trésorerie'!B18,1),"")) | F31: =IF(COUNT('Tableau de Flux de Trésorerie'!C39,'Tableau de Flux de Trésorerie'!C18)=0,"",IFERROR(ROUND(-'Tableau de Flux de Trésorerie'!C39/'Tableau de Flux de Trésorerie'!C18,1),"")) | G31: =IF(COUNT('Tableau de Flux de Trésorerie'!D39,'Tableau de Flux de Trésorerie'!D18)=0,"",IFERROR(ROUND(-'Tableau de Flux de Trésorerie'!D39/'Tableau de Flux de Trésorerie'!D18,1),""))
A32: Dette
A33: Fonds propres / Total Bilan | E33: =IF(COUNT('Bilan - Passifs'!B35,'Bilan - Passifs'!B84)=0,"",IFERROR(ROUND('Bilan - Passifs'!B35/'Bilan - Passifs'!B84,1),"")) | F33: =IF(COUNT('Bilan - Passifs'!C35,'Bilan - Passifs'!C84)=0,"",IFERROR(ROUND('Bilan - Passifs'!C35/'Bilan - Passifs'!C84,1),"")) | G33: =IF(COUNT('Bilan - Passifs'!D35,'Bilan - Passifs'!D84)=0,"",IFERROR(ROUND('Bilan - Passifs'!D35/'Bilan - Passifs'!D84,1),""))
A34: Total Engagements / Total Fonds Propres | E34: =IF(COUNT('Bilan - Passifs'!B35,'Bilan - Passifs'!B84)=0,"",IFERROR(ROUND('Bilan - Passifs'!B83/'Bilan - Passifs'!B35,1),"")) | F34: =IF(COUNT('Bilan - Passifs'!C35,'Bilan - Passifs'!C84)=0,"",IFERROR(ROUND('Bilan - Passifs'!C83/'Bilan - Passifs'!C35,1),"")) | G34: =IF(COUNT('Bilan - Passifs'!D35,'Bilan - Passifs'!D84)=0,"",IFERROR(ROUND('Bilan - Passifs'!D83/'Bilan - Passifs'!D35,1),""))
A35: Total Engagements+equiv dette OBS / Situation Nette
A36: Dette Brute / Fonds propres (Endettement Brut) | E36: =IF(COUNT('Bilan - Passifs'!B35,'Bilan - Passifs'!B84)=0,"",IFERROR(ROUND(E17/'Bilan - Passifs'!B35,1),"")) | F36: =IF(COUNT('Bilan - Passifs'!C35,'Bilan - Passifs'!C84)=0,"",IFERROR(ROUND(F17/'Bilan - Passifs'!C35,1),"")) | G36: =IF(COUNT('Bilan - Passifs'!D35,'Bilan - Passifs'!D84)=0,"",IFERROR(ROUND(G17/'Bilan - Passifs'!D35,1),""))
A37: Dette totale / Situation nette | E37: =IF(COUNT('Bilan - Passifs'!B35,'Bilan - Passifs'!B84)=0,"",IFERROR(ROUND(E17/E24,1),"")) | F37: =IF(COUNT('Bilan - Passifs'!C35,'Bilan - Passifs'!C84)=0,"",IFERROR(ROUND(F17/F24,1),"")) | G37: =IF(COUNT('Bilan - Passifs'!D35,'Bilan - Passifs'!D84)=0,"",IFERROR(ROUND(G17/G24,1),""))
A38: Dette Nette / Fonds Propres (Endettement Net) | E38: =IF(COUNT(E19,'Bilan - Passifs'!B35)=0,"",IFERROR(ROUND(E19/'Bilan - Passifs'!B35,2),"")) | F38: =IF(COUNT(F19,'Bilan - Passifs'!C35)=0,"",IFERROR(ROUND(F19/'Bilan - Passifs'!C35,2),"")) | G38: =IF(COUNT(G19,'Bilan - Passifs'!D35)=0,"",IFERROR(ROUND(G19/'Bilan - Passifs'!D35,2),""))
A39: Dette nette / Situation Nette | E39: =IF(COUNT(E19,E24)=0,"",IFERROR(ROUND(E19/E24,2),"")) | F39: =IF(COUNT(F19,F24)=0,"",IFERROR(ROUND(F19/F24,2),"")) | G39: =IF(COUNT(G19,G24)=0,"",IFERROR(ROUND(G19/G24,2),""))
A40: Dette Nette / Cash Flow Opér. Net | E40: =IF(COUNT(E19,'Tableau de Flux de Trésorerie'!B39)=0,"",IFERROR(ROUND(E19/'Tableau de Flux de Trésorerie'!B39,2),"")) | F40: =IF(COUNT(F19,'Tableau de Flux de Trésorerie'!C39)=0,"",IFERROR(ROUND(F19/'Tableau de Flux de Trésorerie'!C39,2),"")) | G40: =IF(COUNT(G19,'Tableau de Flux de Trésorerie'!D39)=0,"",IFERROR(ROUND(G19/'Tableau de Flux de Trésorerie'!D39,2),""))
A41: Dette Nette / EBITDA (Levier Net) | E41: =IF(COUNT(E19,'Compte de résultat'!B32)=0,"",IFERROR(ROUND(E19/'Compte de résultat'!B32,2),"")) | F41: =IF(COUNT(F19,'Compte de résultat'!C32)=0,"",IFERROR(ROUND(F19/'Compte de résultat'!C32,2),"")) | G41: =IF(COUNT(G19,'Compte de résultat'!D32)=0,"",IFERROR(ROUND(G19/'Compte de résultat'!D32,2),""))
A42: Dette nette ajustée / EBITDAF
A43: Ratio Actuel | E43: =IF(COUNT('Bilan - Actifs'!B68,'Bilan - Actifs'!B81,'Bilan - Passifs'!B81)=0,"",IFERROR(('Bilan - Actifs'!B68+'Bilan - Actifs'!B81)/'Bilan - Passifs'!B81,"")) | F43: =IF(COUNT('Bilan - Actifs'!C68,'Bilan - Actifs'!C81,'Bilan - Passifs'!C81)=0,"",IFERROR(('Bilan - Actifs'!C68+'Bilan - Actifs'!C81)/'Bilan - Passifs'!C81,"")) | G43: =IF(COUNT('Bilan - Actifs'!D68,'Bilan - Actifs'!D81,'Bilan - Passifs'!D81)=0,"",IFERROR(('Bilan - Actifs'!D68+'Bilan - Actifs'!D81)/'Bilan - Passifs'!D81,""))
A44: Cash Ratio | E44: =IF(COUNT('Bilan - Actifs'!B81,'Bilan - Passifs'!B81)=0,"",IFERROR('Bilan - Actifs'!B81/'Bilan - Passifs'!B81,"")) | F44: =IF(COUNT('Bilan - Actifs'!C81,'Bilan - Passifs'!C81)=0,"",IFERROR('Bilan - Actifs'!C81/'Bilan - Passifs'!C81,"")) | G44: =IF(COUNT('Bilan - Actifs'!D81,'Bilan - Passifs'!D81)=0,"",IFERROR('Bilan - Actifs'!D81/'Bilan - Passifs'!D81,""))

Sheet Leveraged Analysis & ECB
A1: WORKSHEET: Corporate - Standard | E1: Créé le | G1: Analyste : | H1: =IF('Bilan - Actifs'!E1="","",'Bilan - Actifs'!E1) | I1: Site : | J1: ALGERIE
A3: Is the cumulative ultimate equity detention by Financial Sponsors above 40% ?
A4: L'emprunteur répond-il à l'un des critères d'exclusion ci-après?
A5: - PME (groupe avec un chiffre d'affaires consolidé < 50M€)
A6: - Souverain ou Entité du Secteur Public
A7: - Entités du secteur financier
A8: - Emprunteur Investment Grade
A9: Statut de la contrepartie : Société mère ultime ou filiale ?
A10: Is there a supporting entity (mother company or another legal entity) as per the Support Entity definition provided in the applicable rating policies ?
A11: Niveau de calcul du levier BCE:
A12: L'opération répond-elle à l'un des critères d'exclusion ci-après ?
A13: En cas de revue annuelle d'une contrepartie déjà "leveragée" BCE, répondre « non » à toutes les questions ci-dessous relatives à l exclusion des transactions.
A14: - Trade Finance
... A26: Précisez l'Evènement:

Sheet Rolling Cash Flow & DettNet
A1: WORKSHEET: Corporate - Standard | E1: Créé le | G1: Analyste : | H1: =IF('Bilan - Actifs'!E1="","",'Bilan - Actifs'!E1) | I1: Site : | J1: ALGERIE
A3: Source de données | E3: OWN | F3: OWN | G3: OWN
A4: Type | E4: Annuel | F4: Annuel | G4: Annuel
A5: Date de clôture
A6: Date de début
A7: Durée
A8: Durée | E8: 12 mois | F8: 12 mois | G8: 12 mois
A9: Statut de la consolidation | E9: Social | F9: Social | G9: Social
A10: Norme comptable | E10: Local Gaap | F10: Local Gaap | G10: Local Gaap
A11: Unité/ Devise affichée | E11: Million DZD | F11: Million DZD | G11: Million DZD
A12: Opinion | E12: Comptes non audités | F12: Comptes non audités | G12: Comptes non audités
A13: Date de Publication
E14: Valeur | F14: Valeur | G14: Valeur
A16: Rolling Operating Cash Flow
A17: Chiffre D'Affaires | E17: =IF(ISNUMBER('Compte de résultat'!B16),'Compte de résultat'!B16,"") | F17: =IF(ISNUMBER('Compte de résultat'!C16),'Compte de résultat'!C16,"") | G17: =IF(ISNUMBER('Compte de résultat'!D16),'Compte de résultat'!D16,"")
A18: Cash Ebilda | E18: =IF(ISNUMBER('Compte de résultat'!B32),'Compte de résultat'!B32,"") | F18: =IF(ISNUMBER('Compte de résultat'!C32),'Compte de résultat'!C32,"") | G18: =IF(ISNUMBER('Compte de résultat'!D32),'Compte de résultat'!D32,"")
A19: Dépenses d'investissement | E19: =IF(ISNUMBER('Tableau de Flux de Trésorerie'!B40),'Tableau de Flux de Trésorerie'!B40,"") | F19: =IF(ISNUMBER('Tableau de Flux de Trésorerie'!C40),'Tableau de Flux de Trésorerie'!C40,"") | G19: =IF(ISNUMBER('Tableau de Flux de Trésorerie'!D40),'Tableau de Flux de Trésorerie'!D40,"")
A20: Acquisitions | E20: =IF(ISNUMBER('Tableau de Flux de Trésorerie'!B49),'Tableau de Flux de Trésorerie'!B49,"") | F20: =IF(ISNUMBER('Tableau de Flux de Trésorerie'!C49),'Tableau de Flux de Trésorerie'!C49,"") | G20: =IF(ISNUMBER('Tableau de Flux de Trésorerie'!D49),'Tableau de Flux de Trésorerie'!D49,"")
A21: Les charges financières payées | E21: =IF(ISNUMBER('Tableau de Flux de Trésorerie'!B18),'Tableau de Flux de Trésorerie'!B18,"") | F21: =IF(ISNUMBER('Tableau de Flux de Trésorerie'!C18),'Tableau de Flux de Trésorerie'!C18,"") | G21: =IF(ISNUMBER('Tableau de Flux de Trésorerie'!D18),'Tableau de Flux de Trésorerie'!D18,"")
A22: Impôts payés | E22: =IF(ISNUMBER('Tableau de Flux de Trésorerie'!B19),'Tableau de Flux de Trésorerie'!B19,"") | F22: =IF(ISNUMBER('Tableau de Flux de Trésorerie'!C19),'Tableau de Flux de Trésorerie'!C19,"") | G22: =IF(ISNUMBER('Tableau de Flux de Trésorerie'!D19),'Tableau de Flux de Trésorerie'!D19,"")
A23: Flux de trésorerie | E23: =IF(COUNT(E18,E19,E20,E21,E22)=0,"",SUM(E18,E19,E20,E21,E22)) | F23: =IF(COUNT(F18,F19,F20,F21,F22)=0,"",SUM(F18,F19,F20,F21,F22)) | G23: =IF(COUNT(G18,G19,G20,G21,G22)=0,"",SUM(G18,G19,G20,G21,G22))
A24: Flux de trésorerie/Chiffre d'affaires | E24: =IF(COUNT(E17,E23)=0,"",IFERROR(E23/E17,"")) | F24: =IF(COUNT(F17,F23)=0,"",IFERROR(F23/F17,"")) | G24: =IF(COUNT(G17,G23)=0,"",IFERROR(G23/G17,""))
A25: Dépréciation & Amortissement | E25: =IF(ISNUMBER('Compte de résultat'!B33),'Compte de résultat'!B33,"") | F25: =IF(ISNUMBER('Compte de résultat'!C33),'Compte de résultat'!C33,"") | G25: =IF(ISNUMBER('Compte de résultat'!D33),'Compte de résultat'!D33,"")
A26: Dépenses d'investissement/Dépréciation & Amortissement | E26: =IF(COUNT(E19,E25)=0,"",IFERROR(E19/E25,"")) | F26: =IF(COUNT(F19,F25)=0,"",IFERROR(F19/F25,"")) | G26: =IF(COUNT(G19,G25)=0,"",IFERROR(G19/G25,""))
