Workbook

Sheet Saisie actif
C1: Raison sociale
C2: NIF
C3: Source
C4: ACTIF | D4: Nature bilan | G4: Nature bilan | J4: Nature bilan | M4: Nature bilan | P4: Nature bilan
D5: Fiscal | G5: Fiscal | J5: Fiscal | M5: Fiscal | P5: Fiscal
D6: Date d'arrêté (N-4) | G6: Date d'arrêté (N-3) | J6: Date d'arrêté (N-2) | M6: Date d'arrêté (N-1) | P6: Date d'arrêté (N)
D8: Montants Bruts (KDZD) | E8: Amortissements, provisions et pertes de valeurs (KDZD) | F8: Net (KDZD) | G8: Montants Bruts (KDZD) | H8: Amortissements, provisions et pertes de valeurs (KDZD) | I8: Net (KDZD) | J8: Montants Bruts (KDZD) | K8: Amortissements, provisions et pertes de valeurs (KDZD) | L8: Net (KDZD) | M8: Montants Bruts (KDZD) | N8: Amortissements, provisions et pertes de valeurs (KDZD) | O8: Net (KDZD) | P8: Montants Bruts (KDZD) | Q8: Amortissements, provisions et pertes de valeurs (KDZD) | R8: Net (KDZD)
C9: ACTIFS NON COURANTS | D9: =+D11+D12+D17+D18+D10 -> 98524.757 | E9: =+E11+E12+E17+E18+E10 -> 38132.173 | F9: =+F11+F12+F17+F18+F10 -> 60392.584 | G9: =+G11+G12+G17+G18+G10 -> 98524.757 | H9: =+H11+H12+H17+H18+H10 -> 38132.173 | I9: =+I11+I12+I17+I18+I10 -> 60392.584 | J9: =+J11+J12+J17+J18+J10 -> 98524.757 | K9: =+K11+K12+K17+K18+K10 -> 38132.173 | ... R9: =+R11+R12+R17+R18+R10 -> 49709.866
C10: Ecart d’acquisition – goodwill positif ou négatif | F10: =+D10-E10 -> 0 | I10: =+G10-H10 -> 0 | L10: =+J10-K10 -> 0 | O10: =+M10-N10 -> 0 | R10: =+P10-Q10 -> 0
C11: Immobilisations incorporelles | D11: 1670 | E11: 775.501 | F11: =+D11-E11 -> 894.499 | G11: 1670 | H11: 775.501 | I11: =+G11-H11 -> 894.499 | J11: 1670 | K11: 775.501 | L11: =+J11-K11 -> 894.499 | M11: 1520 | N11: 459 | O11: =+M11-N11 -> 1061 | P11: 1520 | Q11: 459 | R11: =+P11-Q11 -> 1061
C12: Immobilisations corporelles | D12: =SUM(D13:D16) -> 96854.757 | E12: =SUM(E13:E16) -> 37356.672 | F12: =SUM(F13:F16) -> 59498.085 | G12: =SUM(G13:G16) -> 96854.757 | H12: =SUM(H13:H16) -> 37356.672 | I12: =SUM(I13:I16) -> 59498.085 | J12: =SUM(J13:J16) -> 96854.757 | K12: =SUM(K13:K16) -> 37356.672 | ... R12: =SUM(R13:R16) -> 48648.866
C13: Terrains | F13: =+D13-E13 -> 0 | I13: =+G13-H13 -> 0 | L13: =+J13-K13 -> 0 | O13: =+M13-N13 -> 0 | R13: =+P13-Q13 -> 0
C14: Bâtiments | D14: 6000 | E14: 925 | F14: =+D14-E14 -> 5075 | G14: 6000 | H14: 925 | I14: =+G14-H14 -> 5075 | J14: 6000 | K14: 925 | L14: =+J14-K14 -> 5075 | M14: 6000 | N14: 775 | O14: =+M14-N14 -> 5225 | P14: 6000 | Q14: 775 | R14: =+P14-Q14 -> 5225
C15: Autres immobilisations corporelles | D15: 90854.757 | E15: 36431.672 | F15: =+D15-E15 -> 54423.085 | G15: 90854.757 | H15: 36431.672 | I15: =+G15-H15 -> 54423.085 | J15: 90854.757 | K15: 36431.672 | L15: =+J15-K15 -> 54423.085 | M15: 71268.03 | N15: 27844.164 | O15: =+M15-N15 -> 43423.866 | P15: 71268.03 | Q15: 27844.164 | R15: =+P15-Q15 -> 43423.866
C16: Immobilisations en concession | F16: =+D16-E16 -> 0 | I16: =+G16-H16 -> 0 | L16: =+J16-K16 -> 0 | O16: =+M16-N16 -> 0 | R16: =+P16-Q16 -> 0
C17: Immobilisations en cours | F17: =+D17-E17 -> 0 | I17: =+G17-H17 -> 0 | L17: =+J17-K17 -> 0 | O17: =+M17-N17 -> 0 | R17: =+P17-Q17 -> 0
C18: Immobilisations financières | D18: =SUM(D19:D23) -> 0 | E18: =SUM(E19:E23) -> 0 | F18: =SUM(F19:F23) -> 0 | G18: =SUM(G19:G23) -> 0 | H18: =SUM(H19:H23) -> 0 | I18: =SUM(I19:I23) -> 0 | J18: =SUM(J19:J23) -> 0 | K18: =SUM(K19:K23) -> 0 | ... R18: =SUM(R19:R23) -> 0
C19: Titres mis en équivalence | F19: =+D19-E19 -> 0 | I19: =+G19-H19 -> 0 | L19: =+J19-K19 -> 0 | O19: =+M19-N19 -> 0 | R19: =+P19-Q19 -> 0
C20: Autres participations et créances rattachées | F20: =+D20-E20 -> 0 | I20: =+G20-H20 -> 0 | L20: =+J20-K20 -> 0 | O20: =+M20-N20 -> 0 | R20: =+P20-Q20 -> 0
C21: Autres titres immobilisés | F21: =+D21-E21 -> 0 | I21: =+G21-H21 -> 0 | L21: =+J21-K21 -> 0 | O21: =+M21-N21 -> 0 | R21: =+P21-Q21 -> 0
C22: Prêts et autres actifs financiers non courants | F22: =+D22-E22 -> 0 | I22: =+G22-H22 -> 0 | L22: =+J22-K22 -> 0 | O22: =+M22-N22 -> 0 | R22: =+P22-Q22 -> 0
C23: Impôts différés actif | F23: =+D23-E23 -> 0 | I23: =+G23-H23 -> 0 | L23: =+J23-K23 -> 0 | O23: =+M23-N23 -> 0 | R23: =+P23-Q23 -> 0
C24: TOTAL ACTIF NON COURANT | D24: =+D9 -> 98524.757 | E24: =+E9 -> 38132.173 | F24: =+F9 -> 60392.584 | G24: =+G9 -> 98524.757 | H24: =+H9 -> 38132.173 | I24: =+I9 -> 60392.584 | J24: =+J9 -> 98524.757 | K24: =+K9 -> 38132.173 | ... R24: =+R9 -> 49709.866
C25: ACTIFS COURANTS | D25: =+D26+D27+D32 -> 78787.274 | E25: =+E26+E27+E32 -> 0 | F25: =+F26+F27+F32 -> 78787.274 | G25: =+G26+G27+G32 -> 78787.274 | H25: =+H26+H27+H32 -> 0 | I25: =+I26+I27+I32 -> 78787.274 | J25: =+J26+J27+J32 -> 78787.274 | K25: =+K26+K27+K32 -> 0 | ... R25: =+R26+R27+R32 -> 37290.267
C26: Stocks et encours | D26: 54424.256 | F26: =+D26-E26 -> 54424.256 | G26: 54424.256 | I26: =+G26-H26 -> 54424.256 | J26: 54424.256 | L26: =+J26-K26 -> 54424.256 | M26: 19958.44 | O26: =+M26-N26 -> 19958.44 | P26: 19958.44 | R26: =+P26-Q26 -> 19958.44
C27: Créances et emplois assimilés | D27: =+D28+D29+D30+D31 -> 24068.253 | E27: =+E28+E29+E30+E31 -> 0 | F27: =+F28+F29+F30+F31 -> 24068.253 | G27: =+G28+G29+G30+G31 -> 24068.253 | H27: =+H28+H29+H30+H31 -> 0 | I27: =+I28+I29+I30+I31 -> 24068.253 | J27: =+J28+J29+J30+J31 -> 24068.253 | K27: =+K28+K29+K30+K31 -> 0 | ... R27: =+R28+R29+R30+R31 -> 15195.673
C28: Clients | D28: 4802.292 | F28: =+D28-E28 -> 4802.292 | G28: 4802.292 | I28: =+G28-H28 -> 4802.292 | J28: 4802.292 | L28: =+J28-K28 -> 4802.292 | M28: 3495.623 | O28: =+M28-N28 -> 3495.623 | P28: 3495.623 | R28: =+P28-Q28 -> 3495.623
C29: Autres débiteurs | D29: 3943.005 | F29: =+D29-E29 -> 3943.005 | G29: 3943.005 | I29: =+G29-H29 -> 3943.005 | J29: 3943.005 | L29: =+J29-K29 -> 3943.005 | M29: 323.699 | O29: =+M29-N29 -> 323.699 | P29: 323.699 | R29: =+P29-Q29 -> 323.699
C30: Impôts et assimilés | D30: 15322.956 | F30: =+D30-E30 -> 15322.956 | G30: 15322.956 | I30: =+G30-H30 -> 15322.956 | J30: 15322.956 | L30: =+J30-K30 -> 15322.956 | M30: 11376.351 | O30: =+M30-N30 -> 11376.351 | P30: 11376.351 | R30: =+P30-Q30 -> 11376.351
C31: Autres créances et emplois assimilés | F31: =+D31-E31 -> 0 | I31: =+G31-H31 -> 0 | L31: =+J31-K31 -> 0 | O31: =+M31-N31 -> 0 | R31: =+P31-Q31 -> 0
C32: Disponibilités et assimilés | D32: =+D33+D34 -> 294.765 | E32: =+E33+E34 -> 0 | F32: =+F33+F34 -> 294.765 | G32: =+G33+G34 -> 294.765 | H32: =+H33+H34 -> 0 | I32: =+I33+I34 -> 294.765 | J32: =+J33+J34 -> 294.765 | K32: =+K33+K34 -> 0 | ... R32: =+R33+R34 -> 2136.154
C33: Placements et autres actifs financiers courants | F33: =+D33-E33 -> 0 | I33: =+G33-H33 -> 0 | L33: =+J33-K33 -> 0 | O33: =+M33-N33 -> 0 | R33: =+P33-Q33 -> 0
C34: Trésorerie | D34: 294.765 | F34: =+D34-E34 -> 294.765 | G34: 294.765 | I34: =+G34-H34 -> 294.765 | J34: 294.765 | L34: =+J34-K34 -> 294.765 | M34: 2136.154 | O34: =+M34-N34 -> 2136.154 | P34: 2136.154 | R34: =+P34-Q34 -> 2136.154
C35: TOTAL ACTIF COURANT | D35: =+D25 -> 78787.274 | E35: =+E25 -> 0 | F35: =+F25 -> 78787.274 | G35: =+G25 -> 78787.274 | H35: =+H25 -> 0 | I35: =+I25 -> 78787.274 | J35: =+J25 -> 78787.274 | K35: =+K25 -> 0 | ... R35: =+R25 -> 37290.267
C36: TOTAL GENERAL ACTIF | D36: =+D35+D24 -> 177312.03 | E36: =+E35+E24 -> 38132.173 | F36: =+F35+F24 -> 139179.86 | G36: =+G35+G24 -> 177312.03 | H36: =+H35+H24 -> 38132.173 | I36: =+I35+I24 -> 139179.86 | J36: =+J35+J24 -> 177312.03 | K36: =+K35+K24 -> 38132.173 | ... R36: =+R35+R24 -> 87000.133

Sheet Saisie passif
C1: Raison sociale
C2: NIF
C3: Source
C4: PASSIF | D4: N-4 | E4: N-3 | F4: N-2 | G4: N-1 | H4: N
C5: CAPITAUX PROPRES : | D5: =D6-D7+SUM(D8:D12) -> 77953.808 | E5: =E6-E7+SUM(E8:E12) -> 77953.808 | F5: =F6-F7+SUM(F8:F12) -> 0 | G5: =G6-G7+SUM(G8:G12) -> 77953.808 | H5: =H6-H7+SUM(H8:H12) -> 64767.33
C6: Capital émis | D6: 62541.411 | E6: 62541.411 | G6: 62541.411 | H6: 50465
C7: Capital non appelé
C8: Primes et réserves- Réserves consolidées(1)
C9: Ecarts de réévaluation
C10: Ecart d’équivalence (1)
C11: Résultat net - Résultat net part du groupe (1) | D11: 15412.397 | E11: 15412.397 | G11: 15412.397 | H11: 14302.33
C12: Autres capitaux propres – Report à nouveau
C13: Part de la société consolidante (1)
C14: Part des minoritaires (1)
C15: TOTAL I (KDZD) | D15: =+D5 -> 77953.808 | E15: =+E5 -> 77953.808 | F15: =+F5 -> 0 | G15: =+G5 -> 77953.808 | H15: =+H5 -> 64767.33
C16: PASSIFS NON-COURANTS : | D16: =SUM(D17:D20) -> 962.647 | E16: =SUM(E17:E20) -> 962.647 | F16: =SUM(F17:F20) -> 0 | G16: =SUM(G17:G20) -> 962.647 | H16: =SUM(H17:H20) -> 4689.417
C17: Emprunts et dettes financières
C18: Impôts (différés et provisionnés) | D18: 962.647 | E18: 962.647 | G18: 962.647 | H18: 4689.417
C19: Autres dettes non courantes
C20: Provisions et produits constatés d’avance
C21: TOTAL II (KDZD) | D21: =+D16 -> 962.647 | E21: =+E16 -> 962.647 | F21: =+F16 -> 0 | G21: =+G16 -> 962.647 | H21: =+H16 -> 4689.417
C22: PASSIFS COURANTS : | D22: =SUM(D23:D26) -> 60263.306 | E22: =SUM(E23:E26) -> 60263.306 | F22: =SUM(F23:F26) -> 0 | G22: =SUM(G23:G26) -> 60263.306 | H22: =SUM(H23:H26) -> 17543.426
C23: Fournisseurs et comptes rattachés | D23: 36959.869 | E23: 36959.869 | G23: 36959.869 | H23: 9867.194
C24: Impôts | D24: 4353.557 | E24: 4353.557 | G24: 4353.557 | H24: 2930.995
C25: Autres dettes | D25: =11597.945 -> 11597.945 | E25: =11597.945 -> 11597.945 | G25: =11597.945 -> 11597.945 | H25: =646.477+0.2 -> 646.677
C26: Trésorerie Passif | D26: 7351.935 | E26: 7351.935 | G26: 7351.935 | H26: 4098.56
C27: TOTAL III (KDZD) | D27: =+D22 -> 60263.306 | E27: =+E22 -> 60263.306 | F27: =+F22 -> 0 | G27: =+G22 -> 60263.306 | H27: =+H22 -> 17543.426
C28: TOTAL PASSIF (I+II+III) (KDZD) | D28: =+D27+D21+D15 -> 139179.76 | E28: =+E27+E21+E15 -> 139179.76 | F28: =+F27+F21+F15 -> 0 | G28: =+G27+G21+G15 -> 139179.76 | H28: =+H27+H21+H15 -> 87000.173
D29: =IF(OR(D28-'[1]Saisie actif'!F34<=-0.1,D28-'[1]Saisie actif'!F34>=0.1),"ERREUR (Actif ≠ Passif)","OK (Actif = Passif)") -> OK (Actif = Passif) | E29: =IF(OR(E28-'[1]Saisie actif'!P34<=-0.1,E28-'[1]Saisie actif'!P34>=0.1),"ERREUR (Actif ≠ Passif)","OK (Actif = Passif)") -> ERREUR (Actif ≠ Passif) | G29: =IF(OR(G28-'[1]Saisie actif'!R34<=-0.1,G28-'[1]Saisie actif'!R34>=0.1),"ERREUR (Actif ≠ Passif)","OK (Actif = Passif)") -> ERREUR (Actif ≠ Passif) | H29: =IF(OR(H28-'[1]Saisie actif'!U34<=-0.1,H28-'[1]Saisie actif'!U34>=0.1),"ERREUR (Actif ≠ Passif)","OK (Actif = Passif)") -> ERREUR (Actif ≠ Passif)
D30: =IF(D29="ERREUR (Actif ≠ Passif)",-D28+'[1]Saisie actif'!F34,"") | E30: =IF(E29="ERREUR (Actif ≠ Passif)",-E28+'[1]Saisie actif'!P34,"") -> -23101.464 | G30: =IF(G29="ERREUR (Actif ≠ Passif)",-G28+'[1]Saisie actif'!R34,"") -> -52179.628 | H30: =IF(H29="ERREUR (Actif ≠ Passif)",-H28+'[1]Saisie actif'!U34,"") -> -87000.173
C31: (1) à utiliser uniquement pour la présentation d’états financiers consolidés

Sheet Saisie TCR
C1: Raison sociale
C2: NIF
C3: Source
C4: Rubriques | E4: N-4 | G4: N-3 | I4: N-2 | K4: N-1 | M4: N
E5: DEBIT (en Dinars) | F5: CREDIT (en Dinars) | G5: DEBIT (en Dinars) | H5: CREDIT (en Dinars) | I5: DEBIT (en Dinars) | J5: CREDIT (en Dinars) | K5: DEBIT (KDZD) | L5: CREDIT (KDZD) | M5: DEBIT (KDZD) | N5: CREDIT (KDZD)
C6: Ventes de marchandises | L6: 246152.99 | N6: 223276.08
C7: Production vendue | D7: Produits fabriqués
D8: Prestations de services
D9: Vente de travaux
C10: Produits annexes
C11: Rabais, remises, ristournes accordés
C12: Chiffre d’affaires net des Rabais, remises, ristournes | E12: =(IF((SUM(E6:E11))>(SUM(F6:F11)),(+F6+F7+F8+F9+F10+F11-E6-E7-E8-E9-E10-E11),0))*(-1) -> 0 | F12: =IF((SUM(F6:F11))>(SUM(E6:E11)),(+F6+F7+F8+F9+F10+F11-E6-E7-E8-E9-E10-E11),0) -> 0 | G12: =(IF((SUM(G6:G11))>(SUM(H6:H11)),(+H6+H7+H8+H9+H10+H11-G6-G7-G8-G9-G10-G11),0))*(-1) -> 0 | H12: =IF((SUM(H6:H11))>(SUM(G6:G11)),(+H6+H7+H8+H9+H10+H11-G6-G7-G8-G9-G10-G11),0) -> 0 | I12: =(IF((SUM(I6:I11))>(SUM(J6:J11)),(+J6+J7+J8+J9+J10+J11-I6-I7-I8-I9-I10-I11),0))*(-1) -> 0 | J12: =IF((SUM(J6:J11))>(SUM(I6:I11)),(+J6+J7+J8+J9+J10+J11-I6-I7-I8-I9-I10-I11),0) -> 0 | K12: =(IF((SUM(K6:K11))>(SUM(L6:L11)),(+L6+L7+L8+L9+L10+L11-K6-K7-K8-K9-K10-K11),0))*(-1) -> 0 | L12: =IF((SUM(L6:L11))>(SUM(K6:K11)),(+L6+L7+L8+L9+L10+L11-K6-K7-K8-K9-K10-K11),0) -> 246152.99 | M12: =(IF((SUM(M6:M11))>(SUM(N6:N11)),(+N6+N7+N8+N9+N10+N11-M6-M7-M8-M9-M10-M11),0))*(-1) -> 0 | N12: =IF((SUM(N6:N11))>(SUM(M6:M11)),(+N6+N7+N8+N9+N10+N11-M6-M7-M8-M9-M10-M11),0) -> 223276.08
C13: Production stockée ou déstockée
C14: Production immobilisée
C15: Subventions d’exploitation
C16: I-Production de l’exercice | E16: =(IF((SUM(E12:E15))>(SUM(F12:F15)),(+F12+F13+F14+F15-E12-E13-E14-E15),0))*(-1) -> 0 | F16: =IF((SUM(F12:F15))>(SUM(E12:E15)),(+F12+F13+F14+F15-E12-E13-E14-E15),0) -> 0 | G16: =(IF((SUM(G12:G15))>(SUM(H12:H15)),(+H12+H13+H14+H15-G12-G13-G14-G15),0))*(-1) -> 0 | H16: =IF((SUM(H12:H15))>(SUM(G12:G15)),(+H12+H13+H14+H15-G12-G13-G14-G15),0) -> 0 | I16: =(IF((SUM(I12:I15))>(SUM(J12:J15)),(+J12+J13+J14+J15-I12-I13-I14-I15),0))*(-1) -> 0 | J16: =IF((SUM(J12:J15))>(SUM(I12:I15)),(+J12+J13+J14+J15-I12-I13-I14-I15),0) -> 0 | K16: =(IF((SUM(K12:K15))>(SUM(L12:L15)),(+L12+L13+L14+L15-K12-K13-K14-K15),0))*(-1) -> 0 | L16: =IF((SUM(L12:L15))>(SUM(K12:K15)),(+L12+L13+L14+L15-K12-K13-K14-K15),0) -> 246152.99 | M16: =(IF((SUM(M12:M15))>(SUM(N12:N15)),(+N12+N13+N14+N15-M12-M13-M14-M15),0))*(-1) -> 0 | N16: =IF((SUM(N12:N15))>(SUM(M12:M15)),(+N12+N13+N14+N15-M12-M13-M14-M15),0) -> 223276.08
C17: Achats de marchandises vendues
C18: Matières premières | K18: 165273.99 | M18: 150424.33
C19: Autres approvisionnements
C20: Variations des stocks
C21: Achats d’études et de prestations de services
C22: Autres consommations | M22: 2683.194
C23: Rabais, remises, ristournes obtenus sur achats
C24: Services extérieurs | D24: Sous-traitance générale | M24: 3155.879
D25: Locations | M25: 1002
D26: Entretien, réparations et maintenance | M26: 396.062
D27: Primes d'assurances | M27: 271.079
D28: Personnel extérieur à l’entreprise
D29: Rémunération d’intermédiaires et honoraires | M29: 2548.207
D30: Publicité | M30: 103.47
D31: Déplacements, missions et réceptions
C32: Autres services | K32: 18155.68 | M32: 6958.35
C33: Rabais, remises, ristournes obtenus sur services extérieurs
C34: II-Consommations de l’exercice | E34: =(IF((SUM(E17:E33))>(SUM(F17:F33)),(+(SUM(F17:F33))-(SUM(E17:E33))),0))*(-1) -> 0 | F34: =IF((SUM(F17:F33))>(SUM(E17:E33)),(+(SUM(F17:F33))-(SUM(E17:E33))),0) -> 0 | G34: =(IF((SUM(G17:G33))>(SUM(H17:H33)),(+(SUM(H17:H33))-(SUM(G17:G33))),0))*(-1) -> 0 | H34: =IF((SUM(H17:H33))>(SUM(G17:G33)),(+(SUM(H17:H33))-(SUM(G17:G33))),0) -> 0 | I34: =(IF((SUM(I17:I33))>(SUM(J17:J33)),(+(SUM(J17:J33))-(SUM(I17:I33))),0))*(-1) -> 0 | J34: =IF((SUM(J17:J33))>(SUM(I17:I33)),(+(SUM(J17:J33))-(SUM(I17:I33))),0) -> 0 | K34: =(IF((SUM(K17:K33))>(SUM(L17:L33)),(+(SUM(L17:L33))-(SUM(K17:K33))),0))*(-1) -> 183429.67 | L34: =IF((SUM(L17:L33))>(SUM(K17:K33)),(+(SUM(L17:L33))-(SUM(K17:K33))),0) -> 0 | M34: =(IF((SUM(M17:M33))>(SUM(N17:N33)),(+(SUM(N17:N33))-(SUM(M17:M33))),0))*(-1) -> 167542.57 | N34: =IF((SUM(N17:N33))>(SUM(M17:M33)),(+(SUM(N17:N33))-(SUM(M17:M33))),0) -> 0
C35: III-Valeur ajoutée d’exploitation (I–II) | E35: =(IF(((+E34+E16)>(+F34+F16)),(+F34+F16-E34-E16),0))*(-1) -> 0 | F35: =+IF(((+F34+F16)>(+E34+E16)),(-E34-E16+F34+F16),0) -> 0 | G35: =(IF(((+G34+G16)>(+H34+H16)),(+H34+H16-G34-G16),0))*(-1) -> 0 | H35: =+IF(((+H34+H16)>(+G34+G16)),(-G34-G16+H34+H16),0) -> 0 | I35: =(IF(((+I34+I16)>(+J34+J16)),(+J34+J16-I34-I16),0))*(-1) -> 0 | J35: =+IF(((+J34+J16)>(+I34+I16)),(-I34-I16+J34+J16),0) -> 0 | K35: =(IF(((+K34+K16)>(+L34+L16)),(+L34+L16-K34-K16),0))*(-1) -> 0 | L35: =+IF(((+L34+L16)>(+K34+K16)),(-K34-K16+L34+L16),0) -> 62723.317 | M35: =(IF(((+M34+M16)>(+N34+N16)),(+N34+N16-M34-M16),0))*(-1) -> 0 | N35: =+IF(((+N34+N16)>(+M34+M16)),(-M34-M16+N34+N16),0) -> 55733.518
D36: Charges de personnel | K36: 29033.924 | M36: 21966.003
D37: Impôts et taxes et versements assimilés | K37: 4958.721 | M37: 4518.579
C38: IV-Excédent brut d’exploitation | E38: =(IF((SUM(E35:E37))>(SUM(F35:F37)),(+(SUM(F35:F37))-(SUM(E35:E37))),0))*(-1) -> 0 | F38: =IF((SUM(F35:F37))>(SUM(E35:E37)),(+(SUM(F35:F37))-(SUM(E35:E37))),0) -> 0 | G38: =(IF((SUM(G35:G37))>(SUM(H35:H37)),(+(SUM(H35:H37))-(SUM(G35:G37))),0))*(-1) -> 0 | H38: =IF((SUM(H35:H37))>(SUM(G35:G37)),(+(SUM(H35:H37))-(SUM(G35:G37))),0) -> 0 | I38: =(IF((SUM(I35:I37))>(SUM(J35:J37)),(+(SUM(J35:J37))-(SUM(I35:I37))),0))*(-1) -> 0 | J38: =IF((SUM(J35:J37))>(SUM(I35:I37)),(+(SUM(J35:J37))-(SUM(I35:I37))),0) -> 0 | K38: =(IF((SUM(K35:K37))>(SUM(L35:L37)),(+(SUM(L35:L37))-(SUM(K35:K37))),0))*(-1) -> 0 | L38: =IF((SUM(L35:L37))>(SUM(K35:K37)),(+(SUM(L35:L37))-(SUM(K35:K37))),0) -> 28730.672 | M38: =(IF((SUM(M35:M37))>(SUM(N35:N37)),(+(SUM(N35:N37))-(SUM(M35:M37))),0))*(-1) -> 0 | N38: =IF((SUM(N35:N37))>(SUM(M35:M37)),(+(SUM(N35:N37))-(SUM(M35:M37))),0) -> 29248.936
C39: Autres produits opérationnels | N39: 108.803
C40: Autres charges opérationnelles | K40: 5 | M40: 3875.82
C41: Dotations aux amortissements | K41: 9054.008 | M41: 6668.263
C42: Provision
C43: Pertes de valeur
C44: Reprise sur pertes de valeur et provisions
C45: V-Résultat opérationnel | E45: =(IF((SUM(E38:E44))>(SUM(F38:F44)),(+(SUM(F38:F44))-(SUM(E38:E44))),0))*(-1) -> 0 | F45: =IF((SUM(F38:F44))>(SUM(E38:E44)),(+(SUM(F38:F44))-(SUM(E38:E44))),0) -> 0 | G45: =(IF((SUM(G38:G44))>(SUM(H38:H44)),(+(SUM(H38:H44))-(SUM(G38:G44))),0))*(-1) -> 0 | H45: =IF((SUM(H38:H44))>(SUM(G38:G44)),(+(SUM(H38:H44))-(SUM(G38:G44))),0) -> 0 | I45: =(IF((SUM(I38:I44))>(SUM(J38:J44)),(+(SUM(J38:J44))-(SUM(I38:I44))),0))*(-1) -> 0 | J45: =IF((SUM(J38:J44))>(SUM(I38:I44)),(+(SUM(J38:J44))-(SUM(I38:I44))),0) -> 0 | K45: =(IF((SUM(K38:K44))>(SUM(L38:L44)),(+(SUM(L38:L44))-(SUM(K38:K44))),0))*(-1) -> 0 | L45: =IF((SUM(L38:L44))>(SUM(K38:K44)),(+(SUM(L38:L44))-(SUM(K38:K44))),0) -> 19671.664 | M45: =(IF((SUM(M38:M44))>(SUM(N38:N44)),(+(SUM(N38:N44))-(SUM(M38:M44))),0))*(-1) -> 0 | N45: =IF((SUM(N38:N44))>(SUM(M38:M44)),(+(SUM(N38:N44))-(SUM(M38:M44))),0) -> 18813.656
C46: Produits financiers
C47: Charges financières | K47: 406.263 | M47: 930.338
C48: VI-Résultat financier | E48: =(IF((SUM(E46:E47))>(SUM(F46:F47)),(+(SUM(F46:F47))-(SUM(E46:E47))),0))*(-1) -> 0 | F48: =IF((SUM(F46:F47))>(SUM(E46:E47)),(+(SUM(F46:F47))-(SUM(E46:E47))),0) -> 0 | G48: =(IF((SUM(G46:G47))>(SUM(H46:H47)),(+(SUM(H46:H47))-(SUM(G46:G47))),0))*(-1) -> 0 | H48: =IF((SUM(H46:H47))>(SUM(G46:G47)),(+(SUM(H46:H47))-(SUM(G46:G47))),0) -> 0 | I48: =(IF((SUM(I46:I47))>(SUM(J46:J47)),(+(SUM(J46:J47))-(SUM(I46:I47))),0))*(-1) -> 0 | J48: =IF((SUM(J46:J47))>(SUM(I46:I47)),(+(SUM(J46:J47))-(SUM(I46:I47))),0) -> 0 | K48: =(IF((SUM(K46:K47))>(SUM(L46:L47)),(+(SUM(L46:L47))-(SUM(K46:K47))),0))*(-1) -> 406.263 | L48: =IF((SUM(L46:L47))>(SUM(K46:K47)),(+(SUM(L46:L47))-(SUM(K46:K47))),0) -> 0 | M48: =(IF((SUM(M46:M47))>(SUM(N46:N47)),(+(SUM(N46:N47))-(SUM(M46:M47))),0))*(-1) -> 930.338 | N48: =IF((SUM(N46:N47))>(SUM(M46:M47)),(+(SUM(N46:N47))-(SUM(M46:M47))),0) -> 0
C49: VII-Résultat ordinaire (V+VI) | E49: =(IF(((+E48+E45)>(+F48+F45)),(+F48+F45-E48-E45),0))*(-1) -> 0 | F49: =+IF(((+F48+F45)>(+E48+E45)),(-E48-E45+F48+F45),0) -> 0 | G49: =(IF(((+G48+G45)>(+H48+H45)),(+H48+H45-G48-G45),0))*(-1) -> 0 | H49: =+IF(((+H48+H45)>(+G48+G45)),(-G48-G45+H48+H45),0) -> 0 | I49: =(IF(((+I48+I45)>(+J48+J45)),(+J48+J45-I48-I45),0))*(-1) -> 0 | J49: =+IF(((+J48+J45)>(+I48+I45)),(-I48-I45+J48+J45),0) -> 0 | K49: =(IF(((+K48+K45)>(+L48+L45)),(+L48+L45-K48-K45),0))*(-1) -> 0 | L49: =+IF(((+L48+L45)>(+K48+K45)),(-K48-K45+L48+L45),0) -> 19265.401 | M49: =(IF(((+M48+M45)>(+N48+N45)),(+N48+N45-M48-M45),0))*(-1) -> 0 | N49: =+IF(((+N48+N45)>(+M48+M45)),(-M48-M45+N48+N45),0) -> 17883.318
C50: Eléments extraordinaires (produits) (*)
C51: Eléments extraordinaires (Charges) (*)
C52: VIII-Résultat extraordinaire | E52: =(IF((SUM(E50:E51))>(SUM(F50:F51)),(+(SUM(F50:F51))-(SUM(E50:E51))),0))*(-1) -> 0 | F52: =IF((SUM(F50:F51))>(SUM(E50:E51)),(+(SUM(F50:F51))-(SUM(E50:E51))),0) -> 0 | G52: =(IF((SUM(G50:G51))>(SUM(H50:H51)),(+(SUM(H50:H51))-(SUM(G50:G51))),0))*(-1) -> 0 | H52: =IF((SUM(H50:H51))>(SUM(G50:G51)),(+(SUM(H50:H51))-(SUM(G50:G51))),0) -> 0 | I52: =(IF((SUM(I50:I51))>(SUM(J50:J51)),(+(SUM(J50:J51))-(SUM(I50:I51))),0))*(-1) -> 0 | J52: =IF((SUM(J50:J51))>(SUM(I50:I51)),(+(SUM(J50:J51))-(SUM(I50:I51))),0) -> 0 | K52: =(IF((SUM(K50:K51))>(SUM(L50:L51)),(+(SUM(L50:L51))-(SUM(K50:K51))),0))*(-1) -> 0 | L52: =IF((SUM(L50:L51))>(SUM(K50:K51)),(+(SUM(L50:L51))-(SUM(K50:K51))),0) -> 0 | M52: =(IF((SUM(M50:M51))>(SUM(N50:N51)),(+(SUM(N50:N51))-(SUM(M50:M51))),0))*(-1) -> 0 | N52: =IF((SUM(N50:N51))>(SUM(M50:M51)),(+(SUM(N50:N51))-(SUM(M50:M51))),0) -> 0
C53: Impôts exigibles sur résultats | K53: 3853 | M53: 3580.982
C54: Impôts différés (variations) sur résultats
C55: IX - RESULTAT NET DE L’EXERCICE | E55: =(IF((+E54+E53+E52+E49)>(+F54+F53+F52+F49),(+F54+F53+F52+F49-E54-E53-E52-E49),0))*(-1) -> 0 | F55: =(IF((+F54+F53+F52+F49)>(+E54+E53+E52+E49),(+E54+E53+E52+E49-F54-F53-F52-F49),0))*(-1) -> 0 | G55: =(IF((+G54+G53+G52+G49)>(+H54+H53+H52+H49),(+H54+H53+H52+H49-G54-G53-G52-G49),0))*(-1) -> 0 | H55: =(IF((+H54+H53+H52+H49)>(+G54+G53+G52+G49),(+G54+G53+G52+G49-H54-H53-H52-H49),0))*(-1) -> 0 | I55: =(IF((+I54+I53+I52+I49)>(+J54+J53+J52+J49),(+J54+J53+J52+J49-I54-I53-I52-I49),0))*(-1) -> 0 | J55: =(IF((+J54+J53+J52+J49)>(+I54+I53+I52+I49),(+I54+I53+I52+I49-J54-J53-J52-J49),0))*(-1) -> 0 | K55: =(IF((+K54+K53+K52+K49)>(+L54+L53+L52+L49),(+L54+L53+L52+L49-K54-K53-K52-K49),0))*(-1) -> 0 | L55: =(IF((+L54+L53+L52+L49)>(+K54+K53+K52+K49),(+K54+K53+K52+K49-L54-L53-L52-L49),0))*(-1) -> 15412.401 | M55: =(IF((+M54+M53+M52+M49)>(+N54+N53+N52+N49),(+N54+N53+N52+N49-M54-M53-M52-M49),0))*(-1) -> 0 | N55: =(IF((+N54+N53+N52+N49)>(+M54+M53+M52+M49),(+M54+M53+M52+M49-N54-N53-N52-N49),0))*(-1) -> 14302.336

Sheet Saisie
C1: Unité de compte (M.EUR, M.USD, ...) : | D1: 000' DZD | I1: =TODAY() -> 46304 | N1: =TODAY() -> 46304
B2: Société: | C2: MERIPLAST | E2: Feuille de Saisie
A3: Référence Liasse Fiscale | B3: Groupe: | C3: SARL | D3: 38322 | E3: 39417 | F3: 39783 | G3: 40178 | H3: 40543 | I3: 46022 | N3: =IF('Saisie actif'!U7="","",'Saisie actif'!U7)
B4: Immo. d'exploitation brutes (incorporelles) | D4: =D5+D6+D7+D8-D9 -> 0 | E4: =E5+E6+E7+E8-E9 -> 0 | F4: =F5+F6+F7+F8-F9 -> 41.25 | G4: =G5+G6+G7+G8-G9 -> 16 | H4: =H5+H6+H7+H8-H9 -> 565.545 | I4: =I5+I6+I7+I8-I9 -> 1520 | N4: =N5+N6+N7+N8-N9 -> 0
A5: AB | C5: Frais d'établissement bruts | F5: 41.25
A6: CM | C6: + Prime de remb. sur emprunt oblig.
C7: (+ charges à répartir sur plusieurs exercices, uniquement pour la part relative aux immo. industrielles)
A8: AD+AF+AH+AJ+AL | C8: + Autres immo. incorporelles brutes | G8: 16 | H8: 565.545 | I8: =+'Saisie actif'!P11 -> 1520 | N8: =+'Saisie actif'!U11 -> 0
C9: - Survaleur / goodwill bruts (si inclus)
B10: Amortissemts (& prov.) immo. incorporelles | D10: =D11-D12 -> 0 | E10: =E11-E12 -> 0 | F10: =F11-F12 -> 0 | G10: =G11-G12 -> 1.466 | H10: =H11-H12 -> 146.378 | I10: =I11-I12 -> 459 | N10: =N11-N12 -> 0
A11: AC+AE+AG+AI+AK+AM | C11: Amts sur immo. incorporelles. | G11: 1.466 | H11: 146.378 | I11: =+'Saisie actif'!Q11 -> 459 | N11: =+'Saisie actif'!V11 -> 0
C12: - Amts de la survaleur (si inclus)
B13: Immo. d'exploitation brutes (corporelles) | D13: =D14 -> 0 | E13: =E14 -> 88086.06 | F13: =F14 -> 149479.02 | G13: =G14 -> 161659.93 | H13: =H14 -> 186870.25 | I13: =I14 -> 77268.03 | N13: =N14 -> 0
A14: AN+AP+AR+AT+AV+AX | C14: Immo. corporelles brutes | E14: =9696+272.509+62035.547+4500+11543.704+38.3 -> 88086.06 | F14: =9696+139709.67525+73.34273 -> 149479.02 | G14: =9696+272.509+125326.285+4500+21791.794+73.342 -> 161659.93 | H14: 186870.25 | I14: =+'Saisie actif'!P12+'Saisie actif'!P17 -> 77268.03 | N14: =+'Saisie actif'!U12+'Saisie actif'!U17 -> 0
B15: Amortissemts (& prov.) immo. corporelles | D15: =+D16 -> 0 | E15: =+E16 -> 23976.664 | F15: =+F16 -> 43340.142 | G15: =+G16 -> 64226.37 | H15: =+H16 -> 91639.346 | I15: =+I16 -> 28619.164 | N15: =+N16 -> 0
A16: AO+AQ+AS+AU+AW+AY | C16: Amts sur immo. corporelles. | E16: =271.374+14103.339+4440+5142.255+19.696 -> 23976.664 | F16: =43312.07271+28.06925 -> 43340.142 | G16: =272.509+50210.372+4500+9204.419+39.07 -> 64226.37 | H16: 91639.346 | I16: =+'Saisie actif'!Q12+'Saisie actif'!Q17 -> 28619.164 | J16: ='Saisie actif'!$E$14 -> 925 | N16: =+'Saisie actif'!V12+'Saisie actif'!V17 -> 0
B17: Survaleur/ goodwill/ écart d'acquisit. nets | D17: =D18-D19 -> 0 | E17: =E18-E19 -> 0 | F17: =F18-F19 -> 0 | G17: =G18-G19 -> 0 | H17: 0 | I17: =I18-I19 -> 0 | N17: =N18-N19 -> 0
C18: Survaleur / goodwill brut(s) | I18: =+'Saisie actif'!P10 -> 0 | N18: =+'Saisie actif'!U10 -> 0
C19: - Amt de la survaleur / goodwill | I19: =+'Saisie actif'!Q10 -> 0 | N19: =+'Saisie actif'!V10 -> 0
B20: Immo. financières nettes | D20: =D21+D22+D23+D24+D25+D26-D27-D28-D29-D30-D31-D32 -> 0 | E20: =E21+E22+E23+E24+E25+E26-E27-E28-E29-E30-E31-E32 -> 51512.928 | F20: =F21+F22+F23+F24+F25+F26-F27-F28-F29-F30-F31-F32 -> 51512.928 | G20: =G21+G22+G23+G24+G25+G26-G27-G28-G29-G30-G31-G32 -> 3813.992 | H20: =H21+H22+H23+H24+H25+H26-H27-H28-H29-H30-H31-H32 -> 1847 | I20: =I21+I22+I23+I24+I25+I26-I27-I28-I29-I30-I31-I32 -> 0 | N20: =N21-N22 -> 0
A21: CS+CU | B21: Brut : | C21: Participations
C22: + Titres des stés mises en équival. | I22: =+'Saisie actif'!P19 -> 0 | N22: =+'Saisie actif'!U19 -> 0
C23: + VMP nanties ou bloquées
A24: BD | C24: + Autres titres immobilisés | I24: =+'Saisie actif'!P21 -> 0 | N24: =+'Saisie actif'!U21 -> 0
A25: BF | C25: + Prêts | H25: 1847 | I25: =+'Saisie actif'!P22 -> 0 | N25: =+'Saisie actif'!U22 -> 0
A26: BH | C26: + Autres immo. financières | E26: 51512.928 | F26: 51512.928 | G26: =3813.992 -> 3813.992 | I26: =+'Saisie actif'!P20+'Saisie actif'!P23 -> 0 | N26: =+'Saisie actif'!U20+'Saisie actif'!U23 -> 0
A27: CT+CV | B27: - Prov.: | C27: pour participations
C28: pour titres stés mises en équival. | I28: =+'Saisie actif'!Q19 -> 0 | N28: =+'Saisie actif'!V19 -> 0
C29: pour VMP nanties ou bloquées
A30: BE | C30: pour autres titres immobilisés | I30: =+'Saisie actif'!Q21 -> 0 | N30: =+'Saisie actif'!V21 -> 0
A31: BG | C31: pour prêts | I31: =+'Saisie actif'!Q22 -> 0 | N31: =+'Saisie actif'!V22 -> 0
A32: BI | C32: pour autres immo. financières | I32: =+'Saisie actif'!Q20+'Saisie actif'!Q23 -> 0 | N32: =+'Saisie actif'!V20+'Saisie actif'!V23 -> 0
B33: Sociétés apparentées (actif) nettes | D33: =D34+D35-D36 -> 0 | E33: =E34+E35-E36 -> 0 | F33: =F34+F35-F36 -> 0 | G33: =G34+G35-G36 -> 421.393 | H33: 0 | I33: =I34+I35-I36 -> 0 | N33: =N34+N35-N36 -> 0
A34: BB | B34: Brut : | C34: Créances rattach. à des partic.
A35: VC Annexe 8 | C35: + Créances Groupe & associés | G35: 421.393 | J35: ce poste est généralement compris dans les autres créances de l'actif circulant: on en trouve le détail dans les annexes des états financiers (sinon info à demander aux entreprises)
A36: BC | B36: - Prov.: | C36: - Provis. pour créances rattachées à des participations
B37: Stocks nets | D37: =D38+D39+D40+D41-D42-D43-D44-D45 -> 0 | E37: =E38+E39+E40+E41-E42-E43-E44-E45 -> 108697.29 | F37: =F38+F39+F40+F41-F42-F43-F44-F45 -> 262709.32 | G37: =G38+G39+G40+G41-G42-G43-G44-G45 -> 475743.81 | H37: =H38+H39+H40+H41-H42-H43-H44-H45 -> 444621.94 | I37: =I38+I39+I40+I41-I42-I43-I44-I45 -> 19958.44 | N37: =N38+N39+N40+N41-N42-N43-N44-N45 -> 0
A38: BL | B38: Brut : | C38: Matières premières & approv. | E38: 108697.29 | F38: 256279 | G38: 475743.81
A39: BT | C39: + Marchandises | F39: =3416.52753+3013.79138 -> 6430.3189 | H39: 444621.94 | I39: =+'Saisie actif'!P26 -> 19958.44 | N39: =+'Saisie actif'!U26 -> 0
A40: BN+BP | C40: + Encours prod. biens & services
A41: BR | C41: + Produits finis
A42: BM | B42: - Prov.: | C42: pour mat. prem. & approv.
A43: BU | C43: pour marchandises | I43: =+'Saisie actif'!Q26 -> 0 | N43: =+'Saisie actif'!V26 -> 0
A44: BO+BQ | C44: pour enc. prod. biens & services
A45: BS | C45: pour produits finis
B46: Clients nets | D46: =D47-D48 -> 0 | E46: =E47-E48 -> 107718.96 | F46: =F47-F48 -> 57395.55 | G46: =G47-G48 -> 117587.54 | H46: =H47-H48 -> 383709.16 | I46: =I47-I48 -> 1296.442 | N46: =N47-N48 -> 0
A47: BX | C47: Clients & cptes rattachés (bruts) | E47: 109918.14 | F47: 59594.731 | G47: 119786.72 | H47: 385908.34 | I47: =+'Saisie actif'!P28 -> 3495.623 | N47: =+'Saisie actif'!U28 -> 0
A48: BY | C48: - Prov. sur clients & cptes rattachés | E48: 2199.182 | F48: 2199.1816 | G48: 2199.181 | H48: 2199.181 | I48: 2199.181
B49: Autres créances nettes | D49: =D50+D51-D52-D53+D54+D55+D56+D57 -> 0 | E49: =E50+E51-E52-E53+E54+E55+E56+E57 -> 15533.525 | F49: =F50+F51-F52-F53+F54+F55+F56+F57 -> 41872.384 | G49: =G50+G51-G52-G53+G54+G55+G56+G57 -> 60028.927 | H49: =H50+H51-H52-H53+H54+H55+H56+H57 -> 78139.476 | I49: =I50+I51-I52-I53+I54+I55+I56+I57 -> 11966.525 | N49: =N50+N51-N52-N53+N54+N55+N56+N57 -> 0
A50: BV-BW | C50: Av./acptes sur commandes | F50: 37543.773 | G50: =1304.036+57920.086 -> 59224.122
A51: BZ | C51: + Autres créances & cré. diverses | E51: 15533.525 | F51: 4328.6116 | H51: 77873.001 | I51: =+SUM('Saisie actif'!P29:P31) -> 11700.05 | N51: =+SUM('Saisie actif'!U29:U31) -> 0
A52: CA | C52: - Prov. autres créances et cré. div. | I52: =+SUM('Saisie actif'!Q29:Q31) -> 0 | N52: =+SUM('Saisie actif'!V29:V31) -> 0
A53: VC | C53: - Groupe & associés (si inclus) | J53: à vérifier dans les annexes des états financiers ou à demander aux entreprises
A54: CH | C54: + Charges constatées d'avance
A55: CL | C55: + Charges à répart. sur plus. exerc.
C56: + Impôts diff. actif (cptes conso.) | H56: 266.475 | I56: 266.475
A57: CN | C57: + Ecart de conversion actif | G57: 804.805
B58: Valeurs mobilières de placement nettes | D58: =D59-D60-D61 -> 0 | E58: =E59-E60-E61 -> 0 | F58: =F59-F60-F61 -> 0 | G58: =G59-G60-G61 -> 0 | H58: 0 | I58: =I59-I60-I61 -> 0 | N58: =N59-N60-N61 -> 0
A59: CD | C59: VMP brutes | I59: =+'Saisie actif'!P33 -> 0 | N59: =+'Saisie actif'!U33 -> 0
C60: - VMP nanties ou bloquées brutes
A61: CE | C61: - Prov. sur VMP ni nanties ni bloquées | I61: =+'Saisie actif'!Q33 -> 0 | N61: =+'Saisie actif'!V33 -> 0
B62: Disponible | D62: =D63-D64 -> 0 | E62: =E63-E64 -> 30403.941 | F62: =F63-F64 -> 126419.96 | G62: =G63-G64 -> 22728.054 | H62: =H63-H64 -> 104619.7 | I62: =I63-I64 -> 2136.154 | N62: =N63-N64 -> 0
A63: CF | C63: Disponibilités | E63: 30403.941 | F63: 126419.96 | G63: 22728.054 | H63: 104619.7 | I63: =+'Saisie actif'!P34 -> 2136.154 | N63: =+'Saisie actif'!U34 -> 0
C64: - VMP nettes (si incluses) | I64: =+'Saisie actif'!Q34 -> 0 | N64: =+'Saisie actif'!V34 -> 0
B65: Hors bilan actif | D65: =D66 -> 0 | E65: =E66 -> 0 | F65: =F66 -> 0 | G65: =G66 -> 0 | H65: 0 | I65: =I66 -> 0 | N65: =N66 -> 0
C66: Engagements reçus | E66: 0 | F66: 0
B67: Capital | D67: =D68-D69+D70 -> 0 | E67: =E68-E69+E70 -> 55000 | F67: =F68-F69+F70 -> 55000 | G67: =G68-G69+G70 -> 55000 | H67: =H68-H69+H70 -> 55000 | I67: =I68-I69+I70 -> 50465 | N67: =N68-N69+N70 -> 0
A68: DA | C68: Capital social | E68: 55000 | F68: 55000 | G68: 55000 | H68: 55000 | I68: =+'Saisie passif'!H6 -> 50465 | J68: ='Saisie passif'!$E$18 -> 962.647 | N68: =+'Saisie passif'!M6 -> 0
A69: AA | C69: - Capital souscrit, ni appelé ni versé | I69: =+'Saisie passif'!H7 -> 0 | N69: =+'Saisie passif'!M7 -> 0
A70: DB | C70: + Prime d'émission, fusion ou apport | I70: =+'Saisie passif'!H8 -> 0 | N70: =+'Saisie passif'!M8 -> 0
B71: Réserves | D71: =D72+D73+D74+D75+D76 -> 0 | E71: =E72+E73+E74+E75+E76 -> 21587.473 | F71: =F72+F73+F74+F75+F76 -> 32088.007 | G71: =G72+G73+G74+G75+G76 -> 50446.013 | H71: =H72+H73+H74+H75+H76 -> 74277.392 | I71: =I72+I73+I74+I75+I76 -> 33176.275 | N71: =N72+N73+N74+N75+N76 -> 0
A72: DC+DD+DE+DF+DG | C72: Réserves diverses | E72: 320 | F72: 32088.007 | G72: =5500+1426.596 -> 6926.596 | H72: 33176.275 | I72: 33176.275
C73: + Ecart de conversion (sur Fds Prop.) | I73: =+'Saisie passif'!H9 -> 0 | N73: =+'Saisie passif'!M9 -> 0
C74: + Ecart de consolidation | I74: =+'Saisie passif'!H10 -> 0 | N74: =+'Saisie passif'!M10 -> 0
C75: + Quasi-Fonds Propres | E75: 21267.473
A76: DH | C76: + Report à nouveau | G76: =17269.738+26249.679 -> 43519.417 | H76: 41101.117 | I76: =+'Saisie passif'!H12 -> 0 | N76: =+'Saisie passif'!M12 -> 0
B77: Bénéfice de l'exercice | D77: =D78 -> 0 | E77: =E78 -> 9000.4575 | F77: =F78 -> 18383.009 | G77: =G78 -> 21368.238 | H77: =H78 -> 27766.661 | I77: =I78 -> 14302.33 | J77: bénéfice après dividendes versés ou à verser au titre de ce bénéfice (pour obtenir des FP après distribution, contrairement aux comptes français qui sont généralement présentés avant distribution) | N77: =N78 -> 0
A78: DI | C78: Résultat net publié (pour consolidé: part du groupe + part des minor.) | E78: =12000.61*0.75 -> 9000.4575 | F78: =24510.6782*0.75 -> 18383.009 | G78: 21368.238 | H78: 27766.661 | I78: =+'Saisie passif'!H11 -> 14302.33 | J78: il s'agit ici du résultat net "global", groupe et minoritaire | N78: =+'Saisie passif'!M11 -> 0
A79: ZE Annexe 11 n+1 | C79: - Dividendes (votés en A.G. au titre de "n") | J79: à saisir à partir des annexes des états financiers ou à demander aux entreprises
B80: Intérêts minoritaires (cptes consolidés) | D80: =D81-D82 -> 0 | E80: =E81-E82 -> 0 | F80: =F81-F82 -> 0 | G80: =G81-G82 -> 0 | H80: 0 | I80: =I81-I82 -> 0 | N80: =N81-N82 -> 0
C81: Intérêts minoritaires (passif)
C82: - Intérêts minor. (cpte de résultat) | J82: à saisir si le poste "intérêts mino." de la ligne 93 comprend la part des mino. du résultat net déjà inclu dans la ligne 90 "résultat net publié"
B83: Provisions pour risques et charges (stables) | D83: =D84+D85 -> 0 | E83: =E84+E85 -> 0 | F83: =F84+F85 -> 0 | G83: =G84+G85 -> 0 | H83: 0 | I83: =I84+I85 -> 0 | N83: =N84+N85 -> 0
A84: DJ+DK | C84: (1-i) Subv. d'investiss. + prov. réglem. | J84: remplir si l'information est disponible
A85: dans DR : part stable | C85: Provis. Pour risques et charges stables | J85: remplir si l'information est disponible
B86: Dettes financières à long / moyen terme | D86: =D87+D88+D89-D90-D91+D92+D93+D94+D95 -> 0 | E86: =E87+E88+E89-E90-E91+E92+E93+E94+E95 -> 45584 | F86: =F87+F88+F89-F90-F91+F92+F93+F94+F95 -> 50953.402 | G86: =G87+G88+G89-G90-G91+G92+G93+G94+G95 -> 50000 | H86: =H87+H88+H89-H90-H91+H92+H93+H94+H95 -> 51043.006 | I86: =I87+I88+I89-I90-I91+I92+I93+I94+I95 -> 0 | N86: =N87+N88+N89-N90-N91+N92+N93+N94+N95 -> 0
A87: DT | C87: Emprunts obligataires
A88: DU | C88: + Emprunts auprès des éts de cdt | E88: 39780.8
A89: DV | C89: + Emprunts et dettes financières | E89: 5803.2 | F89: 50953.402 | G89: 50000 | H89: 51043.006 | I89: =+'Saisie passif'!H17 -> 0 | N89: =+'Saisie passif'!M17 -> 0
A90: EH | C90: - Concours banc. courants (si inclus) | J90: à saisir à partir des annexes des états financiers ou à demander aux entreprises
A91: VI Annexe 8 | C91: - Groupe et associés (si inclus dans les lignes 99 à 107 => pour reclassement ligne 109) | J91: à saisir à partir des annexes des états financiers ou à demander aux entreprises
A92: DN | C92: + Avances conditionnées | J92: on peut aussi saisir ces "avances" en quasi fonds propres ligne 87 si l'on a la certitude que ces avances d'actionnaires seront apportées (ou ont été apportées) à une augmentation de capital (si incertitude, à laisser en dettes financière)
A93: DM | C93: + Titres participatifs | J93: à saisir ici lorsqu'ils ont plus un caractère de dettes que de fonds propres => sinon à classer plutôt en quasi-fonds propres, ligne 87 (quasi-FP si disponibles pour le financement à LT/pérenne de la sté)
A94: DS | C94: + TSDI | J94: à saisir ici lorsqu'ils ont plus un caractère de dettes que de fonds propres => sinon à classer plutôt en quasi-fonds propres, ligne 87 (quasi-FP si disponibles pour le financement à LT/pérenne de la sté)
C95: + ORA | J95: à saisir ici par exception car en général, les ORA n'étant remboursés qu'en actions participent donc du financement pérenne de l'entreprise et doivent plutôt être saisis en quasi-FP ligne 87
B96: Sociétés apparentées (passif) | D96: =D97 -> 0 | E96: =E97 -> 53383.399 | F96: =F97 -> 78273.741 | G96: =G97 -> 72730.389 | H96: =H97 -> 72730.389 | I96: =I97 -> 0 | N96: =N97 -> 0
A97: VI Annexe 8 | C97: Groupe et associés passif | E97: 53383.399 | F97: 78273.741 | G97: 72730.389 | H97: 72730.389 | J97: ces dettes "groupe et associés" sont généralement incluses dans les dettes financières MLT ou dans les autres dettes circulantes des états financiers de l'entreprise. On les reclasse ici du fait de leur caractère financier
B98: Avances et acomptes reçus | D98: =D99 -> 0 | E98: =E99 -> 0 | F98: =F99 -> 296.0115 | G98: =G99 -> 0 | H98: 0 | I98: =I99 -> 0 | N98: =N99 -> 0
A99: DW | C99: Avances et acomptes reçus | F99: 296.0115
B100: Fournisseurs | D100: =D101 -> 0 | E100: =E101 -> 68995.586 | F100: =F101 -> 205984.72 | G100: =G101 -> 130093.2 | H100: =H101 -> 331432.5 | I100: =I101 -> 9867.194 | N100: =N101 -> 0
...

Sheet Etatsfin
A1: Unité de compte (MF, MUSD, ...): | D1: =IF(Saisie!D1="","Saisir sur Saisie ou Etatsfin",Saisie!D1) -> 000' DZD | F1: ETATS FINANCIERS | K1: Date : | L1: =TODAY() -> 46304 | O1: =IF(OR(D1="",D1="Saisir sur Saisie ou Etatsfin")," montant",D1) -> 000' DZD | P1: =IF(OR(D1="",D1="Saisir sur Saisie ou Etatsfin")," Saisir sur Saisie ou Etatsfin",D1) -> 000' DZD
A2: Société : | D2: =IF(Saisie!C2="","Saisir sur Saisie ou Etatsfin",Saisie!C2) -> MERIPLAST | I2: Commissaires aux comptes : | L2: Consolidé :
A3: Groupe : | D3: =IF(Saisie!C3="","Saisir sur Saisie ou Etatsfin",Saisie!C3) -> SARL | L3: Audité :
A4: Saisie automatisée (même partiellement) ? (o/n): | G4: si oui, les contrôles spécifiques sont-ils effectués ? (o/n): | H4: si oui, les contrôles spécifiques sont-ils effectués ? (o/n): | O4: =(Saisie!E3-Saisie!D3) -> 1095 | P4: (Détermination de la durée du 1er exercice)
A5: ACTIF | C5: =IF(Saisie!D3=0,D5-365,Saisie!D3) -> 38322 | D5: =IF(Saisie!E3=0,E5-365,Saisie!E3) -> 39417 | E5: =IF(Saisie!F3=0,F5-365,Saisie!F3) -> 39783 | F5: =IF(Saisie!G3=0,G5-365,Saisie!G3) -> 40178 | G5: =IF(Saisie!H3=0,0,Saisie!H3) -> 40543 | H5: =IF(Saisie!I3=0,0,Saisie!I3) -> 46022 | I5: PASSIF | J5: =D5 -> 39417 | K5: =E5 -> 39783 | L5: =F5 -> 40178 | M5: =G5 -> 40543 | N5: =H5 -> 46022
C6: =O4/365 -> 3 | D6: =O4/365 -> 3 | E6: =(E5-D5)/365 -> 1.0027397 | F6: =(F5-E5)/365 -> 1.0821918 | G6: =(G5-F5)/365 -> 1 | H6: =(H5-G5)/365 -> 15.010959
A7: =IF(OR(G5=0,G5=""),"Date d'arrêté à saisir ci-dessous en ''G'', ligne 23, dans la cellule blanche.","") | D7: Fiscal | E7: Fiscal | F7: Fiscal | G7: fiscal | H7: fiscal | I7: =IF(OR(O4<=0,O4=""),"Saisir durée, en jours, du 1er exercice histo., dans la cellule ''M'' ici à droite, ligne 22 :","") | J7: =J8/J31 -> 0.22643745 | K7: =K8/K31 -> 0.16324502 | L7: =L8/L31 -> 0.16304815 | M7: =M8/M31 -> 0.14166142 | N7: =N8/N31 -> 0.81499833
A8: Actifs immobilisés ( nets) | C8: =C14+C17+C18+C19 -> 0 | D8: =D14+D17+D18+D19 -> 115622.32 | E8: =E14+E17+E18+E19 -> 157693.05 | F8: =F14+F17+F18+F19 -> 101683.48 | G8: =G14+G17+G18+G19 -> 97497.075 | H8: =H14+H17+H18+H19 -> 49709.866 | I8: Fonds propres | J8: =J10+J11+J12+J13 -> 85587.931 | K8: =K10+K11+K12+K13 -> 105471.02 | L8: =L10+L11+L12+L13 -> 126814.25 | M8: =M10+M11+M12+M13 -> 157044.05 | N8: =N10+N11+N12+N13 -> 97943.605
A10: Immobilisations d'exploitation brutes | C10: =Saisie!D4+Saisie!D13 -> 0 | D10: =Saisie!E4+Saisie!E13 -> 88086.06 | E10: =Saisie!F4+Saisie!F13 -> 149520.27 | F10: =Saisie!G4+Saisie!G13 -> 161675.93 | G10: =Saisie!H4+Saisie!H13 -> 187435.8 | H10: =Saisie!I4+Saisie!I13 -> 78788.03 | I10: Capital | J10: =Saisie!E67 -> 55000 | K10: =Saisie!F67 -> 55000 | L10: =Saisie!G67 -> 55000 | M10: =Saisie!H67 -> 55000 | N10: =Saisie!I67 -> 50465
A11: - Amortissements et Provisions | C11: =Saisie!D10+Saisie!D15 -> 0 | D11: =Saisie!E10+Saisie!E15 -> 23976.664 | E11: =Saisie!F10+Saisie!F15 -> 43340.142 | F11: =Saisie!G10+Saisie!G15 -> 64227.836 | G11: =Saisie!H10+Saisie!H15 -> 91785.724 | H11: =Saisie!I10+Saisie!I15 -> 29078.164 | I11: Réserves | J11: =Saisie!E71 -> 21587.473 | K11: =Saisie!F71 -> 32088.007 | L11: =Saisie!G71 -> 50446.013 | M11: =Saisie!H71 -> 74277.392 | N11: =Saisie!I71 -> 33176.275
I12: Bénéfice | J12: =Saisie!E77 -> 9000.4575 | K12: =Saisie!F77 -> 18383.009 | L12: =Saisie!G77 -> 21368.238 | M12: =Saisie!H77 -> 27766.661 | N12: =Saisie!I77 -> 14302.33
I13: Intérêts minoritaires | J13: =Saisie!E80 -> 0 | K13: =Saisie!F80 -> 0 | L13: =Saisie!G80 -> 0 | M13: =Saisie!H80 -> 0 | N13: =Saisie!I80 -> 0
A14: = Immobilisations nettes | C14: =C10-C11 -> 0 | D14: =D10-D11 -> 64109.396 | E14: =E10-E11 -> 106180.13 | F14: =F10-F11 -> 97448.094 | G14: =G10-G11 -> 95650.075 | H14: =H10-H11 -> 49709.866
A15: <dt immo. incorporelles nettes> | C15: =Saisie!D4-Saisie!D10 -> 0 | D15: =Saisie!E4-Saisie!E10 -> 0 | E15: =Saisie!F4-Saisie!F10 -> 41.25 | F15: =Saisie!G4-Saisie!G10 -> 14.534 | G15: =Saisie!H4-Saisie!H10 -> 419.167 | H15: =Saisie!I4-Saisie!I10 -> 1061 | I15: Prov. risques et charges stables | J15: =Saisie!E83 -> 0 | K15: =Saisie!F83 -> 0 | L15: =Saisie!G83 -> 0 | M15: =Saisie!H83 -> 0 | N15: =Saisie!I83 -> 0
A17: Survaleur/ Goodwill | C17: =Saisie!D17 -> 0 | D17: =Saisie!E17 -> 0 | E17: =Saisie!F17 -> 0 | F17: =Saisie!G17 -> 0 | G17: =Saisie!H17 -> 0 | H17: =Saisie!I17 -> 0 | I17: Dettes à long / moyen terme | J17: =J19+J21 -> 98967.399 | K17: =K19+K21 -> 129227.14 | L17: =L19+L21 -> 122730.39 | M17: =M19+M21 -> 123773.39 | N17: =N19+N21 -> 0
A18: Immobilisations financières nettes | C18: =Saisie!D20 -> 0 | D18: =Saisie!E20 -> 51512.928 | E18: =Saisie!F20 -> 51512.928 | F18: =Saisie!G20 -> 3813.992 | G18: =Saisie!H20 -> 1847 | H18: =Saisie!I20 -> 0
A19: Sociétés apparentées | C19: =Saisie!D33 -> 0 | D19: =Saisie!E33 -> 0 | E19: =Saisie!F33 -> 0 | F19: =Saisie!G33 -> 421.393 | G19: =Saisie!H33 -> 0 | H19: =Saisie!I33 -> 0 | I19: Dettes financières | J19: =Saisie!E86 -> 45584 | K19: =Saisie!F86 -> 50953.402 | L19: =Saisie!G86 -> 50000 | M19: =Saisie!H86 -> 51043.006 | N19: =Saisie!I86 -> 0
I20: <y compris annuités moins d'1 an> | J20: =Saisie!E192 -> 0 | K20: =Saisie!F192 -> 0 | L20: =Saisie!G192 -> 0 | M20: =Saisie!H192 -> 0 | N20: =Saisie!I192 -> 0
A21: Actifs circulants (nets) | C21: =C23+C25+C26+C27+C28 -> 0 | D21: =D23+D25+D26+D27+D28 -> 262353.72 | E21: =E23+E25+E26+E27+E28 -> 488397.22 | F21: =F23+F25+F26+F27+F28 -> 676088.32 | G21: =G23+G25+G26+G27+G28 -> 1011090.3 | H21: =H23+H25+H26+H27+H28 -> 35357.561 | I21: Sociétés apparentées | J21: =Saisie!E96 -> 53383.399 | K21: =Saisie!F96 -> 78273.741 | L21: =Saisie!G96 -> 72730.389 | M21: =Saisie!H96 -> 72730.389 | N21: =Saisie!I96 -> 0
A23: Stocks | C23: =Saisie!D37 -> 0 | D23: =Saisie!E37 -> 108697.29 | E23: =Saisie!F37 -> 262709.32 | F23: =Saisie!G37 -> 475743.81 | G23: =Saisie!H37 -> 444621.94 | H23: =Saisie!I37 -> 19958.44 | I23: Exigibles court terme | J23: =J25+J26+J27+J29 -> 193420.71 | K23: =K25+K26+K27+K29 -> 411392.11 | L23: =L25+L26+L27+L29 -> 528227.16 | M23: =M25+M26+M27+M29 -> 827769.89 | N23: =N25+N26+N27+N29 -> 22232.843
A24: <dont travaux en cours> | C24: =Saisie!D40-Saisie!D44 -> 0 | D24: =Saisie!E40-Saisie!E44 -> 0 | E24: =Saisie!F40-Saisie!F44 -> 0 | F24: =Saisie!G40-Saisie!G44 -> 0 | G24: =Saisie!H40-Saisie!H44 -> 0 | H24: =Saisie!I40-Saisie!I44 -> 0
A25: Clients | C25: =Saisie!D46 -> 0 | D25: =Saisie!E46 -> 107718.96 | E25: =Saisie!F46 -> 57395.55 | F25: =Saisie!G46 -> 117587.54 | G25: =Saisie!H46 -> 383709.16 | H25: =Saisie!I46 -> 1296.442 | I25: Avances et Acomptes reçus | J25: =Saisie!E98 -> 0 | K25: =Saisie!F98 -> 296.0115 | L25: =Saisie!G98 -> 0 | M25: =Saisie!H98 -> 0 | N25: =Saisie!I98 -> 0
A26: Autres créances | C26: =Saisie!D49 -> 0 | D26: =Saisie!E49 -> 15533.525 | E26: =Saisie!F49 -> 41872.384 | F26: =Saisie!G49 -> 60028.927 | G26: =Saisie!H49 -> 78139.476 | H26: =Saisie!I49 -> 11966.525 | I26: Fournisseurs | J26: =Saisie!E100 -> 68995.586 | K26: =Saisie!F100 -> 205984.72 | L26: =Saisie!G100 -> 130093.2 | M26: =Saisie!H100 -> 331432.5 | N26: =Saisie!I100 -> 9867.194
A27: Valeurs mobilières de placement | C27: =Saisie!D58 -> 0 | D27: =Saisie!E58 -> 0 | E27: =Saisie!F58 -> 0 | F27: =Saisie!G58 -> 0 | G27: =Saisie!H58 -> 0 | H27: =Saisie!I58 -> 0 | I27: Autres dettes | J27: =Saisie!E102 -> 87623.951 | K27: =Saisie!F102 -> 16214.819 | L27: =Saisie!G102 -> 230249.91 | M27: =Saisie!H102 -> 44421.925 | N27: =Saisie!I102 -> 8267.089
A28: Disponible | C28: =Saisie!D62 -> 0 | D28: =Saisie!E62 -> 30403.941 | E28: =Saisie!F62 -> 126419.96 | F28: =Saisie!G62 -> 22728.054 | G28: =Saisie!H62 -> 104619.7 | H28: =Saisie!I62 -> 2136.154 | I28: <dont provisions et dividendes> | J28: =Saisie!E105+Saisie!E106+Saisie!E110+Saisie!E111 -> 0 | K28: =Saisie!F105+Saisie!F106+Saisie!F110+Saisie!F111 -> 0 | L28: =Saisie!G105+Saisie!G106+Saisie!G110+Saisie!G111 -> 0 | M28: =Saisie!H105+Saisie!H106+Saisie!H110+Saisie!H111 -> 844.248 | N28: =Saisie!I105+Saisie!I106+Saisie!I110+Saisie!I111 -> 4689.417
I29: Concours bancaires de trésorerie | J29: =Saisie!E112 -> 36801.173 | K29: =Saisie!F112 -> 188896.56 | L29: =Saisie!G112 -> 167884.05 | M29: =Saisie!H112 -> 451915.46 | N29: =Saisie!I112 -> 4098.56
A31: (*) Total Actif | C31: =C21+C8 -> 0 | D31: =D21+D8 -> 377976.04 | E31: =E21+E8 -> 646090.27 | F31: =F21+F8 -> 777771.8 | G31: =G21+G8 -> 1108587.3 | H31: =H21+H8 -> 85067.427 | I31: (*) Total Passif | J31: =J23+J17+J15+J8 -> 377976.04 | K31: =K23+K17+K15+K8 -> 646090.27 | L31: =L23+L17+L15+L8 -> 777771.8 | M31: =M23+M17+M15+M8 -> 1108587.3 | N31: =N23+N17+N15+N8 -> 120176.45
A32: =IF(AND(D32="",E32="",F32="",G32=""),""," Actif = Passif ?") | D32: =IF(AND(D31=0,J31=0),"",IF(AND((D31-J31)>=-0.1,(D31-J31)<=0.1),"","Erreur!")) | E32: =IF(AND(E31=0,K31=0),"",IF(AND((E31-K31)>=-0.1,(E31-K31)<=0.1),"","Erreur!")) | F32: =IF(AND(F31=0,L31=0),"",IF(AND((F31-L31)>=-0.1,(F31-L31)<=0.1),"","Erreur!")) | G32: =IF(AND(G31=0,M31=0),"",IF(AND((G31-M31)>=-0.1,(G31-M31)<=0.1),"","Erreur!")) | H32: =IF(AND(H31=0,N31=0),"",IF(AND((H31-N31)>=-0.1,(H31-N31)<=0.1),"","Erreur!")) -> Erreur! | I32: =IF(AND(D32="",E32="",F32="",G32=""),""," Si erreur, Actif - Passif = ?") | J32: =IF(D32="Erreur!",D31-J31,"") | K32: =IF(E32="Erreur!",E31-K31,"") | L32: =IF(F32="Erreur!",F31-L31,"") | M32: =IF(G32="Erreur!",G31-M31,"") | N32: =IF(H32="Erreur!",H31-N31,"") -> -35109.021
A33: Hors bilan | I33: Hors bilan
A34: Engagements reçus | D34: =Saisie!E65 -> 0 | E34: =Saisie!F65 -> 0 | F34: =Saisie!G65 -> 0 | G34: =Saisie!H65 -> 0 | H34: =Saisie!I65 -> 0 | I34: Effets escomptés non échus | J34: =Saisie!E115 -> 0 | K34: =Saisie!F115 -> 0 | L34: =Saisie!G115 -> 0 | M34: =Saisie!H115 -> 0 | N34: =Saisie!I115 -> 0
A35: Fonds de roulement | D35: =J8+J15+J17-J20-D8 -> 68933.005 | E35: =K8+K15+K17-K20-E8 -> 77005.105 | F35: =L8+L15+L17-L20-F8 -> 147861.16 | G35: =M8+M15+M17-M20-G8 -> 183320.37 | H35: =N8+N15+N17-N20-H8 -> 48233.739 | I35: Engagements de crédit bail | J35: =Saisie!E116 -> 0 | K35: =Saisie!F116 -> 0 | L35: =Saisie!G116 -> 16633.221 | M35: =Saisie!H116 -> 12000 | N35: =Saisie!I116 -> 12000
A36: Besoin en fonds de roulement (net) | D36: =-1*(J25+J26+J27-J28-D23-D25-D26+Saisie!E56) -> 75330.238 | E36: =-1*(K25+K26+K27-K28-E23-E25-E26+Saisie!F56) -> 139481.71 | F36: =-1*(L25+L26+L27-L28-F23-F25-F26+Saisie!G56) -> 293017.16 | G36: =-1*(M25+M26+M27-M28-G23-G25-G26+Saisie!H56) -> 531193.91 | H36: =-1*(N25+N26+N27-N28-H23-H25-H26+Saisie!I56) -> 19510.066 | I36: Autres | J36: =Saisie!E117 -> 0 | K36: =Saisie!F117 -> 0 | L36: =Saisie!G117 -> 0 | M36: =Saisie!H117 -> 0 | N36: =Saisie!I117 -> 0
A37: BFR (en Jours de C.A.) | D37: =IF(D41=0,"n/d ",(D36/D41)*360*D6) -> 195.46227 | E37: =IF(E41=0,"n/d ",(E36/E41)*360*E6) -> 70.129975 | F37: =IF(F41=0,"n/d ",(F36/F41)*360*F6) -> 125.75105 | G37: =IF(G41=0,"n/d ",(G36/G41)*360*G6) -> 118.32029 | H37: =IF(H41=0,"n/d ",(H36/H41)*360*H6) -> 472.20161
A38: Trésorerie | D38: =D35-D36 -> -6397.232 | E38: =E35-E36 -> -62476.6 | F38: =F35-F36 -> -145156 | G38: =G35-G36 -> -347873.54 | H38: =H35-H36 -> 28723.673
A39: COMPTE DE RESULTAT | D39: =D5 -> 39417 | E39: =E5 -> 39783 | F39: =F5 -> 40178 | G39: =G5 -> 40543 | H39: =H5 -> 46022 | I39: TABLEAU DE FLUX | J39: =D5 -> 39417 | K39: =E5 -> 39783 | L39: =F5 -> 40178 | M39: =G5 -> 40543 | N39: =H5 -> 46022
A41: Chiffre d'affaires H.T. | C41: =Saisie!D120 -> 0 | D41: =Saisie!E120 -> 416226.91 | E41: =Saisie!F120 -> 717966.67 | F41: =Saisie!G120 -> 907795.82 | G41: =Saisie!H120 -> 1616204.7 | H41: =Saisie!I120 -> 223276.08 | I41: Excédent Brut d'Exploitation | J41: =D56 -> 29838.884 | K41: =E56 -> 45113.275 | L41: =F56 -> 85384.745 | M41: =G56 -> 114043.95 | N41: =H56 -> 25481.919
A43: + Product° stockée et immobilisée | D43: =Saisie!E122+Saisie!E123 -> 0 | E43: =Saisie!F122+Saisie!F123 -> 0 | F43: =Saisie!G122+Saisie!G123 -> 17182.754 | G43: =Saisie!H122+Saisie!H123 -> 231.15 | H43: =Saisie!I122+Saisie!I123 -> 0 | I43: - Résultat financier retraité | J43: =D63-D65+(1/3*D64) -> 5350.758 | K43: =E63-E65+(1/3*E64) -> 7135.5244 | L43: =F63-F65+(1/3*F64) -> 23322.944 | M43: =G63-G65+(1/3*G64) -> 53131.535 | N43: =H63-H65+(1/3*H64) -> -1826.24
A44: + Autres produits | D44: =Saisie!E124 -> 0 | E44: =Saisie!F124 -> 0 | F44: =Saisie!G124 -> 2281.665 | G44: =Saisie!H124 -> 621.118 | H44: =Saisie!I124 -> 108.803 | I44: - Impôt sur les sociétés | J44: =D71 -> 3000.1525 | K44: =E71 -> 6127.6695 | L44: =F71 -> 6938.5937 | M44: =G71 -> 6990.363 | N44: =H71 -> 3580.982
A46: = Production | D46: =D41+D43+D44 -> 416226.91 | E46: =E41+E43+E44 -> 717966.67 | F46: =F41+F43+F44 -> 927260.24 | G46: =G41+G43+G44 -> 1617056.9 | H46: =H41+H43+H44 -> 223384.89 | I46: = Cashflow d'Exploitat° Brut | J46: =J41-J43-J44 -> 21487.973 | K46: =K41-K43-K44 -> 31850.081 | L46: =L41-L43-L44 -> 55123.207 | M46: =M41-M43-M44 -> 53922.055 | N46: =N41-N43-N44 -> 23727.177
A48: - Achats et sous-traitance | D48: =Saisie!E126 -> 365232.29 | E48: =Saisie!F126 -> 639351.23 | F48: =Saisie!G126 -> 765768.86 | G48: =Saisie!H126 -> 1379090.5 | H48: =Saisie!I126 -> 153580.2 | I48: Variation du BFR (brut) | J48: =J49+J50-J51+J52 -> 77529.42 | K48: =K49+K50-K51+K52 -> 64151.468 | L48: =L49+L50-L51+L52 -> 153535.45 | M48: =M49+M50-M51+M52 -> 238176.75 | N48: =N49+N50-N51+N52 -> -511683.85
A49: + Variat° des stocks de march. | D49: =Saisie!E130 -> 0 | E49: =Saisie!F130 -> 0 | F49: =Saisie!G130 -> 0 | G49: =Saisie!H130 -> 0 | H49: =Saisie!I130 -> 0 | I49: - Variation des Stocks (bruts) | J49: =IF(Saisie!E120=0,"0,0",SUM(Saisie!E38:'Saisie'!E41)-SUM(Saisie!D38:'Saisie'!D41)) -> 108697.29 | K49: =IF(Saisie!F120=0,"0,0",SUM(Saisie!F38:'Saisie'!F41)-SUM(Saisie!E38:'Saisie'!E41)) -> 154012.03 | L49: =IF(Saisie!G120=0,"0,0",SUM(Saisie!G38:'Saisie'!G41)-SUM(Saisie!F38:'Saisie'!F41)) -> 213034.48 | M49: =IF(Saisie!H120=0,"0,0",SUM(Saisie!H38:'Saisie'!H41)-SUM(Saisie!G38:'Saisie'!G41)) -> -31121.869 | N49: =IF(Saisie!I120=0,"0,0",SUM(Saisie!I38:'Saisie'!I41)-SUM(Saisie!H38:'Saisie'!H41)) -> -424663.5
I50: - Variation des Clients (bruts) | J50: =IF(Saisie!E120=0,"0,0",Saisie!E47+Saisie!E115-Saisie!D47-Saisie!D115) -> 109918.14 | K50: =IF(Saisie!F120=0,"0,0",Saisie!F47+Saisie!F115-Saisie!E47-Saisie!E115) -> -50323.409 | L50: =IF(Saisie!G120=0,"0,0",Saisie!G47+Saisie!G115-Saisie!F47-Saisie!F115) -> 60191.986 | M50: =IF(Saisie!H120=0,"0,0",Saisie!H47+Saisie!H115-Saisie!G47-Saisie!G115) -> 266121.62 | N50: =IF(Saisie!I120=0,"0,0",Saisie!I47+Saisie!I115-Saisie!H47-Saisie!H115) -> -382412.71
A51: = Marge commerciale | D51: =D46-D48+D49 -> 50994.626 | E51: =E46-E48+E49 -> 78615.446 | F51: =F46-F48+F49 -> 161491.38 | G51: =G46-G48+G49 -> 237966.49 | H51: =H46-H48+H49 -> 69804.683 | I51: + Variation des Fournisseurs | J51: =IF(Saisie!E120=0,"0,0",J26-Saisie!D100) -> 68995.586 | K51: =IF(Saisie!F120=0,"0,0",K26-Saisie!E100) -> 136989.13 | L51: =IF(Saisie!G120=0,"0,0",L26-Saisie!F100) -> -75891.518 | M51: =IF(Saisie!H120=0,"0,0",M26-Saisie!G100) -> 201339.3 | N51: =IF(Saisie!I120=0,"0,0",N26-Saisie!H100) -> -321565.31
I52: - Var. autr. créances+var. autr. dettes | J52: =IF(Saisie!E120=0,"0,0",((Saisie!E49+Saisie!E52-Saisie!E56)-(Saisie!D49+Saisie!D52-Saisie!D56))-((J25+J27-J28)-(Saisie!D98+Saisie!D102-Saisie!D105-Saisie!D106-Saisie!D110-Saisie!D111))) -> -72090.427 | K52: =IF(Saisie!F120=0,"0,0",((Saisie!F49+Saisie!F52-Saisie!F56)-(Saisie!E49+Saisie!E52-Saisie!E56))-((K25+K27-K28)-(Saisie!E98+Saisie!E102-Saisie!E105-Saisie!E106-Saisie!E110-Saisie!E111))) -> 97451.981 | L52: =IF(Saisie!G120=0,"0,0",((Saisie!G49+Saisie!G52-Saisie!G56)-(Saisie!F49+Saisie!F52-Saisie!F56))-((L25+L27-L28)-(Saisie!F98+Saisie!F102-Saisie!F105-Saisie!F106-Saisie!F110-Saisie!F111))) -> -195582.53 | M52: =IF(Saisie!H120=0,"0,0",((Saisie!H49+Saisie!H52-Saisie!H56)-(Saisie!G49+Saisie!G52-Saisie!G56))-((M25+M27-M28)-(Saisie!G98+Saisie!G102-Saisie!G105-Saisie!G106-Saisie!G110-Saisie!G111))) -> 204516.3 | N52: =IF(Saisie!I120=0,"0,0",((Saisie!I49+Saisie!I52-Saisie!I56)-(Saisie!H49+Saisie!H52-Saisie!H56))-((N25+N27-N28)-(Saisie!H98+Saisie!H102-Saisie!H105-Saisie!H106-Saisie!H110-Saisie!H111))) -> -26172.946
A53: - Charges de personnel | D53: =Saisie!E134 -> 6520.215 | E53: =Saisie!F134 -> 12668.58 | F53: =Saisie!G134 -> 32841.582 | G53: =Saisie!H134 -> 54011.955 | H53: =Saisie!I134 -> 21966.003
A54: - Autres charges | D54: =Saisie!E140 -> 14635.527 | E54: =Saisie!F140 -> 20833.592 | F54: =Saisie!G140 -> 43265.055 | G54: =Saisie!H140 -> 69910.584 | H54: =Saisie!I140 -> 22356.761 | I54: = Cashflow d'Exploitat° Net (CFEN) | J54: =J46-J48 -> -56041.446 | K54: =K46-K48 -> -32301.387 | L54: =L46-L48 -> -98412.248 | M54: =M46-M48 -> -184254.7 | N54: =N46-N48 -> 535411.02
A56: = EBE | D56: =D51-D53-D54 -> 29838.884 | E56: =E51-E53-E54 -> 45113.275 | F56: =F51-F53-F54 -> 85384.745 | G56: =G51-G53-G54 -> 114043.95 | H56: =H51-H53-H54 -> 25481.919 | I56: - Investissements industriels | J56: =IF( Saisie!E120=0,"0,0",D14-C14+D58+Saisie!E186) -> 75497.752 | K56: =IF( Saisie!F120=0,"0,0",E14-D14+E58+Saisie!F186) -> 61434.208 | L56: =IF( Saisie!G120=0,"0,0",F14-E14+F58+Saisie!G186) -> 12147.064 | M56: =IF( Saisie!H120=0,"0,0",G14-F14+G58+Saisie!H186) -> 26556.55 | N56: =IF( Saisie!I120=0,"0,0",H14-G14+H58+Saisie!I186) -> -39271.946
I57: - Remboursement dettes MLT | J57: =Saisie!E191 -> 0 | K57: =Saisie!F191 -> 0 | L57: =Saisie!G191 -> 0 | M57: =Saisie!H191 -> 0 | N57: =Saisie!I191 -> 0
A58: - Dotation aux amortissements | D58: =Saisie!E149 -> 11388.356 | E58: =Saisie!F149 -> 19363.478 | F58: =Saisie!G149 -> 20879.096 | G58: =Saisie!H149 -> 28354.569 | H58: =Saisie!I149 -> 6668.263 | I58: - Part en capital de l'annuité de crédit-bail | J58: =2/3*D64 -> 0 | K58: =2/3*E64 -> 0 | L58: =2/3*F64 -> 1480.1047 | M58: =2/3*G64 -> 0 | N58: =2/3*H64 -> 0
A59: - Dotat° nette aux provis° d'exploitat° | D59: =Saisie!E151 -> 0 | E59: =Saisie!F151 -> 0 | F59: =Saisie!G151 -> 0 | G59: =Saisie!H151 -> -2199.181 | H59: =Saisie!I151 -> 0
A61: = Résultat économique | D61: =D56-D58-D59 -> 18450.528 | E61: =E56-E58-E59 -> 25749.797 | F61: =F56-F58-F59 -> 64505.649 | G61: =G56-G58-G59 -> 87888.565 | H61: =H56-H58-H59 -> 18813.656
I62: = Cashflow Disponible | J62: =J54-J56-J57-J58 -> -131539.2 | K62: =K54-K56-K57-K58 -> -93735.595 | L62: =L54-L56-L57-L58 -> -112039.42 | M62: =M54-M56-M57-M58 -> -210811.25 | N62: =N54-N56-N57-N58 -> 574682.97
A63: - Frais financiers bruts | D63: =Saisie!E156 -> 5350.758 | E63: =Saisie!F156 -> 7135.5244 | F63: =Saisie!G156 -> 22582.892 | G63: =Saisie!H156 -> 57969.357 | H63: =Saisie!I156 -> 930.338
A64: - Annuités de crédit-bail | D64: =Saisie!E158 -> 0 | E64: =Saisie!F158 -> 0 | F64: =Saisie!G158 -> 2220.157 | G64: =Saisie!H158 -> 0 | H64: =Saisie!I158 -> 0 | I64: - Investissements financiers | J64: =IF(Saisie!E120=0,"0,0",(Saisie!E21+Saisie!E22+Saisie!E23+Saisie!E24+Saisie!E25+Saisie!E26+Saisie!E36+Saisie!E34+Saisie!E35+Saisie!E18-Saisie!D21-Saisie!D22-Saisie!D23-Saisie!D24-Saisie!D25-Saisie!D26-Saisie!D34-Saisie!D35-Saisie!D18)+Saisie!E188+Saisie!E189) -> 51512.928 | K64: =IF(Saisie!F120=0,"0,0",(Saisie!F21+Saisie!F22+Saisie!F23+Saisie!F24+Saisie!F25+Saisie!F26+Saisie!F36+Saisie!F34+Saisie!F35+Saisie!F18-Saisie!E21-Saisie!E22-Saisie!E23-Saisie!E24-Saisie!E25-Saisie!E26-Saisie!E34-Saisie!E35-Saisie!E18)+Saisie!F188+Saisie!F189) -> -0.00035 | L64: =IF(Saisie!G120=0,"0,0",(Saisie!G21+Saisie!G22+Saisie!G23+Saisie!G24+Saisie!G25+Saisie!G26+Saisie!G36+Saisie!G34+Saisie!G35+Saisie!G18-Saisie!F21-Saisie!F22-Saisie!F23-Saisie!F24-Saisie!F25-Saisie!F26-Saisie!F34-Saisie!F35-Saisie!F18)+Saisie!G188+Saisie!G189) -> -47277.543 | M64: =IF(Saisie!H120=0,"0,0",(Saisie!H21+Saisie!H22+Saisie!H23+Saisie!H25+Saisie!#REF!+Saisie!H26+Saisie!H36+Saisie!H34+Saisie!H35+Saisie!H18-Saisie!G21-Saisie!G22-Saisie!G23-Saisie!G24-Saisie!G25-Saisie!G26-Saisie!G34-Saisie!G35-Saisie!G18)+Saisie!H188+Saisie!H189) -> #REF! | N64: =IF(Saisie!I120=0,"0,0",(Saisie!I21+Saisie!I22+Saisie!I23+Saisie!I25+Saisie!#REF!+Saisie!I26+Saisie!I36+Saisie!I34+Saisie!I35+Saisie!I18-Saisie!H21-Saisie!H22-Saisie!H23-Saisie!H24-Saisie!H25-Saisie!H26-Saisie!H34-Saisie!H35-Saisie!H18)+Saisie!I188+Saisie!I189) -> #REF!
A65: + Produits financiers | D65: =Saisie!E161 -> 0 | E65: =Saisie!F161 -> 0 | F65: =Saisie!G161 -> 0 | G65: =Saisie!H161 -> 4837.822 | H65: =Saisie!I161 -> 2756.578 | I65: + Cessions d'actifs | J65: =Saisie!E187 -> 0 | K65: =Saisie!F187 -> 0 | L65: =Saisie!G187 -> 0 | M65: =Saisie!H187 -> 0 | N65: =Saisie!I187 -> 0
I66: + Variation des Dettes MLT | J66: =IF(J17=0,"0,0",J17-(Saisie!D86+Saisie!D96)+Saisie!E191) -> 98967.399 | K66: =IF(K17=0,"0,0",K17-(Saisie!E86+Saisie!E96)+Saisie!F191) -> 30259.744 | L66: =IF(L17=0,"0,0",L17-(Saisie!F86+Saisie!F96)+Saisie!G191) -> -6496.7544 | M66: =M17-(Saisie!G86+Saisie!G96)+Saisie!H191 -> 1043.006 | N66: =N17-(Saisie!H86+Saisie!H96)+Saisie!I191 -> -123773.39
A67: = Résultat courant | D67: =D61-D63-D64+D65 -> 13099.77 | E67: =E61-E63-E64+E65 -> 18614.272 | F67: =F61-F63-F64+F65 -> 39702.6 | G67: =G61-G63-G64+G65 -> 34757.03 | H67: =H61-H63-H64+H65 -> 20639.896 | I67: + Variat° des Dettes financ. CT | J67: =IF(J17=0,"0,0",(J29+J34)-(Saisie!D112+Saisie!D115)) -> 36801.173 | K67: =IF(K17=0,"0,0",(K29+K34)-(Saisie!E112+Saisie!E115)) -> 152095.39 | L67: =IF(L17=0,"0,0",(L29+L34)-(Saisie!F112+Saisie!F115)) -> -21012.505 | M67: =IF(M29=0,"0,0",(M29+M34)-(Saisie!G112+Saisie!G115)) -> 284031.41 | N67: =IF(N29=0,"0,0",(N29+N34)-(Saisie!H112+Saisie!H115)) -> -447816.9
I68: - Dividendes payés dans l'année | J68: =Saisie!D110-Saisie!E110+Saisie!E79 -> 0 | K68: =Saisie!E110-Saisie!F110+Saisie!F79 -> 0 | L68: =Saisie!F110-Saisie!G110+Saisie!G79 -> 0 | M68: =Saisie!G110-Saisie!H110+Saisie!H79 -> 0 | N68: =Saisie!H110-Saisie!I110+Saisie!I79 -> 0
A69: + Exceptionnel et autres | D69: =Saisie!E166 -> -1099.16 | E69: =Saisie!F166 -> 5896.424 | F69: =Saisie!G166 -> -11395.678 | G69: =Saisie!H166 -> 0 | H69: =Saisie!I166 -> 0 | I69: + Autres variations de Fonds Propres | J69: =IF(J8=0,"0,0",J8-(Saisie!D67+Saisie!D71+Saisie!D77+Saisie!D80)-J12+Saisie!E189+Saisie!E190) -> 76587.473 | K69: =IF(K8=0,"0,0",K8-(Saisie!E67+Saisie!E71+Saisie!E77+Saisie!E80)-K12+Saisie!F189+Saisie!F190) -> 1500.0766 | L69: =IF(L8=0,"0,0",L8-(Saisie!F67+Saisie!F71+Saisie!F77+Saisie!F80)-L12+Saisie!G189+Saisie!G190) -> -25.00271 | M69: =IF(M8=0,"0,0",M8-(Saisie!G67+Saisie!G71+Saisie!G77+Saisie!G80)-M12+Saisie!H189+Saisie!H190) -> 2463.141 | N69: =IF(N8=0,"0,0",N8-(Saisie!H67+Saisie!H71+Saisie!H77+Saisie!H80)-N12+Saisie!I189+Saisie!I190) -> -73402.778
A70: (y. c. transferts de charges) | I70: + Produits & charges hors exploitation | J70: =IF(Saisie!E120=0,"0,0",+Saisie!E218) -> 1100.022 | K70: =IF(Saisie!F120=0,"0,0",+Saisie!F218) -> 5896.4235 | L70: =IF(Saisie!G120=0,"0,0",+Saisie!G218) -> -11395.679 | M70: =+Saisie!H218 -> 2776.954 | N70: =+Saisie!I218 -> 3845.169 | P70: vérification de l'ajustement (% CA)
A71: - Impôt sur les sociétés | D71: =Saisie!E181 -> 3000.1525 | E71: =Saisie!F181 -> 6127.6695 | F71: =Saisie!G181 -> 6938.5937 | G71: =Saisie!H181 -> 6990.363 | H71: =Saisie!I181 -> 3580.982 | I71: + Autre | J71: =IF(OR(Saisie!E120=0,J70="A saisir ici"),"0,0",J73-J70-J69+J68-J67-J66-J65+J64-J62) -> 5.8207661e-11 | K71: =IF(OR(Saisie!F120=0,K70="A saisir ici"),"0,0",K73-K70-K69+K68-K67-K66-K65+K64-K62) -> -0.015 | L71: =IF(OR(Saisie!G120=0,L70="A saisir ici"),"0,0",L73-L70-L69+L68-L67-L66-L65+L64-L62) -> -0.09229888 | M71: =+M73-M62+M64-M65-M67-M69-M70-M66 -> #REF! | N71: =+N73-N62+N64-N65-N67-N69-N70-N66 -> #REF! | P71: =+J71/D41 -> 1.3984598e-16 | Q71: =+K71/E41 -> -2.0892335e-08 | R71: =+L71/F41 -> -1.0167361e-07 | S71: =+M71/G41 -> #REF!
P72: =+J39 -> 39417 | Q72: =+K39 -> 39783 | R72: =+L39 -> 40178 | S72: =+M39 -> 40543
A73: = Résultat net publié | D73: =D67+D69-D71 -> 9000.4575 | E73: =E67+E69-E71 -> 18383.027 | F73: =F67+F69-F71 -> 21368.328 | G73: =G67+G69-G71 -> 27766.667 | H73: =H67+H69-H71 -> 17058.914 | I73: = Variation des liquidités | J73: =IF( Saisie!E120=0,"0,0",D28-Saisie!D62+(D27+Saisie!E61)-(Saisie!D58+Saisie!D61)) -> 30403.941 | K73: =IF( Saisie!F120=0,"0,0",E28-Saisie!E62+(E27+Saisie!F61)-(Saisie!E58+Saisie!E61)) -> 96016.02 | L73: =IF( Saisie!G120=0,"0,0",F28-Saisie!F62+(F27+Saisie!G61)-(Saisie!F58+Saisie!F61)) -> -103691.91 | M73: =IF( Saisie!H120=0,"0,0",G28-Saisie!G62+(G27+Saisie!H61)-(Saisie!G58+Saisie!G61)) -> 81891.645 | N73: =IF( Saisie!I120=0,"0,0",H28-Saisie!H62+(H27+Saisie!I61)-(Saisie!H58+Saisie!H61)) -> -102483.54
I74: Variation de cash calculée au bilan | J74: =D28-C28 -> 30403.941 | K74: =E28-D28 -> 96016.02 | L74: =F28-E28 -> -103691.91 | M74: =G28-F28 -> 81891.645 | N74: =H28-G28 -> -102483.54
I75: Difference | J75: =J73-J74 -> 0 | K75: =K73-K74 -> 0 | L75: =L73-L74 -> 0 | M75: =M73-M74 -> 0 | N75: =N73-N74 -> 0
A77: RATIOS | D77: =D39 -> 39417 | E77: =E39 -> 39783 | F77: =F39 -> 40178 | G77: =G39 -> 40543 | H77: =H39 -> 46022 | I77: RATIOS (suite) | J77: =J39 -> 39417 | K77: =K39 -> 39783 | L77: =L39 -> 40178 | M77: =M39 -> 40543 | N77: =N39 -> 46022
A79: Résultat net / Fonds Propres (%) | D79: =IF(OR(D6=0,J8=0),"n/d",D73/D6/J8) -> 0.035053453 | E79: =IF(OR(E6=0,K8=0),"n/d",E73/E6/K8) -> 0.17381837 | F79: =IF(OR(F6=0,L8=0),"n/d",F73/F6/L8) -> 0.15570346 | G79: =IF(OR(G6=0,M8=0),"n/d",G73/G6/M8) -> 0.17680814 | H79: =IF(OR(H6=0,N8=0),"n/d",H73/H6/N8) -> 0.011602908 | I79: EBE / Frais financiers | J79: =IF(D63=0,"n/d",D56/D63) -> 5.5765714 | K79: =IF(E63=0,"n/d",E56/E63) -> 6.3223488 | L79: =IF(F63=0,"n/d",F56/F63) -> 3.7809482 | M79: =IF(G63=0,"n/d",G56/G63) -> 1.9673144 | N79: =IF(H63=0,"n/d",H56/H63) -> 27.389958
A80: Résultat net / CA (%) | D80: =IF(OR(D6=0,D41=0),"n/d",D73/D6/D41) -> 0.0072079734 | E80: =IF(OR(E6=0,E41=0),"n/d",E73/E6/E41) -> 0.025534333 | F80: =IF(OR(F6=0,F41=0),"n/d",F73/F6/F41) -> 0.021750945 | G80: =IF(OR(G6=0,G41=0),"n/d",G73/G6/G41) -> 0.017180167 | H80: =IF(OR(H6=0,H41=0),"n/d",H73/H6/H41) -> 0.0050898002 | I80: EBE / Service de la dette (yc CB) | J80: =IF(J57+D63+D64=0,"n/d",D56/(D63+D64+J57)) -> 5.5765714 | K80: =IF(K57+E63+E64=0,"n/d",E56/(E63+E64+K57)) -> 6.3223488 | L80: =IF(L57+F63+F64=0,"n/d",F56/(F63+F64+L57)) -> 3.44251 | M80: =IF(M57+G63+G64=0,"n/d",G56/(G63+G64+M57)) -> 1.9673144 | N80: =IF(N57+H63+H64=0,"n/d",H56/(H63+H64+N57)) -> 27.389958
A81: Résultat net / Total Actif (%) | D81: =IF(OR(D6=0,D31=0),"n/d",D73/D6/D31) -> 0.0079374145 | E81: =IF(OR(E6=0,E31=0),"n/d",E73/E6/E31) -> 0.028374982 | F81: =IF(OR(F6=0,F31=0),"n/d",F73/F6/F31) -> 0.02538716 | G81: =IF(OR(G6=0,G31=0),"n/d",G73/G6/G31) -> 0.025046892 | H81: =IF(OR(H6=0,H31=0),"n/d",H73/H6/H31) -> 0.013359175 | I81: EBE / Frais financiers + Annuité de CB | J81: =IF(J65+D64+D63=0,"n/d",D56/(D63+D64-J58)) -> 5.5765714 | K81: =IF(K65+E64+E63=0,"n/d",E56/(E63+E64-K58)) -> 6.3223488 | L81: =IF(L65+F64+F63=0,"n/d",F56/(F63+F64-L58)) -> 3.6609762 | M81: =IF(M65+G64+G63=0,"n/d",G56/(G63+G64-M58)) -> 1.9673144 | N81: =IF(N65+H64+H63=0,"n/d",H56/(H63+H64-N58)) -> 27.389958
A83: Marge commerciale / C.A. (%) | D83: =IF(D41=0,"n/d ",D51/D41) -> 0.12251641 | E83: =IF(E41=0,"n/d ",E51/E41) -> 0.10949735 | F83: =IF(F41=0,"n/d ",F51/F41) -> 0.17789395 | G83: =IF(G41=0,"n/d ",G51/G41) -> 0.14723784 | H83: =IF(H41=0,"n/d ",H51/H41) -> 0.31263842 | I83: CFEN / Service de la dette (yc CB) | J83: =IF(OR((J54-D63)<0,(Saisie!D192+D63+D64)=0,(Saisie!E120=0)),"n/d",(J54)/(D63+D64+Saisie!D192)) -> n/d | K83: =IF(OR((K54-E63)<0,(Saisie!E192+E63+E64)=0,(Saisie!F120=0)),"n/d",(K54)/(E63+E64+Saisie!E192)) -> n/d | L83: =IF(OR((L54-F63)<0,(Saisie!F192+F63+F64)=0,(Saisie!G120=0)),"n/d",(L54)/(F63+F64+Saisie!F192)) -> n/d | M83: =IF(OR((M54-G63)<0,(Saisie!G192+G63+G64)=0,(Saisie!H120=0)),"n/d",(M54)/(G63+G64+Saisie!G192)) -> n/d | N83: =IF(OR((N54-H63)<0,(Saisie!H192+H63+H64)=0,(Saisie!I120=0)),"n/d",(N54)/(H63+H64+Saisie!H192)) -> 575.50162
A84: EBE / C.A. (%) | D84: =IF(D41=0,"n/d ",D56/D41) -> 0.071688983 | E84: =IF(E41=0,"n/d ",E56/E41) -> 0.062834775 | F84: =IF(F41=0,"n/d ",F56/F41) -> 0.094057213 | G84: =IF(G41=0,"n/d ",G56/G41) -> 0.070562816 | H84: =IF(H41=0,"n/d ",H56/H41) -> 0.1141274 | I84: CFEN - Invest. / Service de la dette (yc CB) | J84: =IF(OR((J54-J56)<0,Saisie!D192+D64+D63=0,Saisie!E120=0),"n/d",(J54-J56)/(Saisie!D192+D63+D64)) -> n/d | K84: =IF(OR((K54-K56)<0,Saisie!E192+E64+E63=0,Saisie!F120=0),"n/d",(K54-K56)/(Saisie!E192+E63+E64)) -> n/d | L84: =IF(OR((L54-L56)<0,Saisie!F192+F64+F63=0,Saisie!G120=0),"n/d",(L54-L56)/(Saisie!F192+F63+F64)) -> n/d | M84: =IF(OR((M54-M56)<0,Saisie!G192+G64+G63=0,Saisie!H120=0),"n/d",(M54-M56)/(Saisie!G192+G63+G64)) -> n/d | N84: =IF(OR((N54-N56)<0,Saisie!H192+H64+H63=0,Saisie!I120=0),"n/d",(N54-N56)/(Saisie!H192+H63+H64)) -> 617.71417
A85: Résultat économique / CA (%) | D85: =IF(D41=0,"n/d", D61/D41) -> 0.044328052 | E85: =IF(E41=0,"n/d", E61/E41) -> 0.035864891 | F85: =IF(F41=0,"n/d", F61/F41) -> 0.071057442 | G85: =IF(G41=0,"n/d", G61/G41) -> 0.054379601 | H85: =IF(H41=0,"n/d", H61/H41) -> 0.08426185
I86: Dettes Fin. Tot. / CFEN (années) | J86: =IF(OR(J54=0,J54<0,D93<0),"n/d",D93/J54) -> n/d | K86: =IF(OR(K54=0,K54<0,E93<0),"n/d",E93/K54) -> n/d | L86: =IF(OR(L54=0,L54<0,F93<0,Saisie!G120=0),"n/d",F93/L54) -> n/d | M86: =IF(OR(M54=0,M54<0,G93<0),"n/d",G93/M54) -> n/d | N86: =IF(OR(N54=0,N54<0,H93<0),"n/d",H93/N54) -> 0.02259677
A87: Evolution du CA (annualisée) | D87: =IF(OR(C41=0,D41=0,C6=0),"n/d",((D41/C41)*(1/C6))-1) -> n/d | E87: =IF(OR(D41=0,E41=0,D6=0),"n/d",((E41/D41)*(1/D6))-1) -> -0.42501982 | F87: =IF(OR(E41=0,F41=0,E6=0),"n/d",((F41/E41)*(1/E6))-1) -> 0.26094363 | G87: =IF(OR(F41=0,G41=0,F6=0),"n/d",((G41/F41)*(1/F6))-1) -> 0.64514412 | H87: =IF(OR(G41=0,H41=0,G6=0),"n/d",((H41/G41)*(1/G6))-1) -> -0.8618516 | I87: Dettes Fin. MLT / Fonds Propres (%) | J87: =IF(OR(J8=0,D92<0),"n/d",D92/J8) -> 1.1563242 | K87: =IF(OR(K8=0,E92<0),"n/d",E92/K8) -> 1.2252384 | L87: =IF(OR(L8=0,F92<0),"n/d",F92/L8) -> 1.0552379 | M87: =IF(OR(M8=0,G92<0),"n/d",G92/M8) -> 0.83908555 | N87: =IF(OR(N8=0,H92<0),"n/d",H92/N8) -> 0.081679656
A88: % des exportations | D88: =IF(Saisie!E121=0,"n/d",Saisie!E121/D41) -> n/d | E88: =IF(Saisie!F121=0,"n/d",Saisie!F121/E41) -> n/d | F88: =IF(Saisie!G121=0,"n/d",Saisie!G121/F41) -> n/d | G88: =IF(Saisie!H121=0,"n/d",Saisie!H121/G41) -> n/d | H88: =IF(Saisie!I121=0,"n/d",Saisie!I121/H41) -> n/d | I88: Dettes Fin. Tot. / Fonds Propres (%) | J88: =IF(OR(J8=0,D93<0),"n/d",D93/J8) -> 1.5863051 | K88: =IF(OR(K8=0,E93<0),"n/d",E93/K8) -> 3.0162192 | L88: =IF(OR(L8=0,F93<0),"n/d",F93/L8) -> 2.3790958 | M88: =IF(OR(M8=0,G93<0),"n/d",G93/M8) -> 3.7167205 | N88: =IF(OR(N8=0,H93<0),"n/d",H93/N8) -> 0.12352578
A89: Achats & Sous-traitance / CA | D89: =IF(D41=0,"n/d",D48/D41) -> 0.87748359 | E89: =IF(E41=0,"n/d",E48/E41) -> 0.89050265 | F89: =IF(F41=0,"n/d",F48/F41) -> 0.84354746 | G89: =IF(G41=0,"n/d",G48/G41) -> 0.85328948 | H89: =IF(H41=0,"n/d",H48/H41) -> 0.68784888 | I89: Dettes Fin. Tot. Nettes / Fonds Propres (%) | J89: =IF(OR(J8=0,D94<0),"n/d",D94/J8) -> 1.2310688 | K89: =IF(OR(K8=0,E94<0),"n/d",E94/K8) -> 1.8175964 | L89: =IF(OR(L8=0,F94<0),"n/d",F94/L8) -> 2.1998726 | M89: =IF(OR(M8=0,G94<0),"n/d",G94/M8) -> 3.0505399 | N89: =IF(OR(N8=0,H94<0),"n/d",H94/N8) -> 0.10171574
I90: Dettes Fin. Tot. / EBE (années) | J90: =IF(OR(D56=0,D56<0,D93<0),"n/d",D93/D56) -> 4.5500553 | K90: =IF(OR(E56=0,E56<0,E93<0),"n/d",E93/E56) -> 7.051665 | L90: =IF(OR(F56=0,F56<0,F93<0),"n/d",F93/F56) -> 3.5334562 | M90: =IF(OR(G56=0,G56<0,G93<0),"n/d",G93/G56) -> 5.1181044 | N90: =IF(OR(H56=0,H56<0,H93<0),"n/d",H93/H56) -> 0.47478999
A91: Dettes Fin. Court Terme (yc Part CT DMLT) | D91: =J29+J96 -> 36801.173 | E91: =K29+K96 -> 188896.56 | F91: =L29+L96 -> 167884.05 | G91: =M29+M96 -> 451915.46 | H91: =N29+N96 -> 4098.56 | I91: Dettes Fin. Tot. Nettes / EBE (années) | J91: =IF(OR(D56=0,D56<0,D94<0),"n/d",D94/D56) -> 3.5311184 | K91: =IF(OR(E56=0,E56<0,E94<0),"n/d",E94/E56) -> 4.2493865 | L91: =IF(OR(F56=0,F56<0,F94<0),"n/d",F94/F56) -> 3.2672722 | M91: =IF(OR(G56=0,G56<0,G94<0),"n/d",G94/G56) -> 4.2007414 | N91: =IF(OR(H56=0,H56<0,H94<0),"n/d",H94/H56) -> 0.3909598
A92: Dettes Fin. Moyen & Long Terme (yc Hors Bilan) | D92: =J17+2/3*(J35)+J34 -> 98967.399 | E92: =K17+2/3*(K35)+K34 -> 129227.14 | F92: =L17+2/3*(L35)+L34 -> 133819.2 | G92: =M17+2/3*(M35)+M34 -> 131773.39 | H92: =N17+2/3*(N35)+N34 -> 8000
A93: Dettes Fin. Totales (yc Hors Bilan) | D93: =D92+D91-J96 -> 135768.57 | E93: =E92+E91-K96 -> 318123.7 | F93: =F92+F91-L96 -> 301703.26 | G93: =G92+G91-M96 -> 583688.85 | H93: =H92+H91-N96 -> 12098.56 | I93: Rotation des stocks (J. de C.A.) | J93: =IF(D41=0,"n/d ",(D23/D41)*360*D6) -> 282.04105 | K93: =IF(E41=0,"n/d ",(E23/E41)*360*E6) -> 132.08756 | L93: =IF(F41=0,"n/d ",(F23/F41)*360*F6) -> 204.16989 | M93: =IF(G41=0,"n/d ",(G23/G41)*360*G6) -> 99.036897 | N93: =IF(H41=0,"n/d ",(H23/H41)*360*H6) -> 483.0536
A94: Dettes Fin. Totales Nettes | D94: =D93-D28-D27 -> 105364.63 | E94: =E93-E28-E27 -> 191703.74 | F94: =F93-F28-F27 -> 278975.2 | G94: =G93-G28-G27 -> 479069.15 | H94: =H93-H28-H27 -> 9962.406 | I94: Délais clients (J. de C.A.) | J94: =IF(D41=0,"n/d ",((D25+J34)/D41)*360*D6) -> 279.50253 | K94: =IF(E41=0,"n/d ",((E25+K34)/E41)*360*E6) -> 28.857895 | L94: =IF(F41=0,"n/d ",((F25+L34)/F41)*360*F6) -> 50.463787 | M94: =IF(G41=0,"n/d ",((G25+M34)/G41)*360*G6) -> 85.468937 | N94: =IF(H41=0,"n/d ",((H25+N34)/H41)*360*H6) -> 31.377752
I95: Crédit fournisseurs (J. d'achats) | J95: =IF(D48=0,"n/d ",(J26/D48)*360*D6) -> 204.02148 | K95: =IF(E48=0,"n/d ",(K26/E48)*360*E6) -> 116.30174 | L95: =IF(F48=0,"n/d ",(L26/F48)*360*F6) -> 66.185619 | M95: =IF(G48=0,"n/d ",(M26/G48)*360*G6) -> 86.517676 | N95: =IF(H48=0,"n/d ",(N26/H48)*360*H6) -> 347.19172
A96: Commentaires | I96: Echéancier de la dette MLT 1an | J96: =Saisie!E192 -> 0 | K96: =Saisie!F192 -> 0 | L96: =Saisie!G192 -> 0 | M96: =Saisie!H192 -> 0 | N96: =Saisie!I192 -> 0
I97: 2 ans
I98: 2/5 ans
I99: > 5ans
I100: Total | J100: =SUM(J96:J99) -> 0 | K100: =SUM(K96:K99) -> 0 | L100: =SUM(L96:L99) -> 0 | M100: =SUM(M96:M99) -> 0 | N100: =SUM(N96:N99) -> 0
A101: (*) Total du bilan actif & passif = Total du bilan publié - amortissements dérogatoires - capital non appelé ou non versé
A102: N.B.: Résultat financier retraité = Charges financières - Produits financiers + 1/3 de l'annuité de crédit-bail

Sheet Ratios
A1: RATIOS | D1: Société : | E1: =IF(Etatsfin!D2="","",Etatsfin!D2) -> MERIPLAST
A2: =TODAY() -> 46304 | D2: Groupe : | E2: =IF(Etatsfin!D3="","",Etatsfin!D3) -> SARL
A3: =IF(OR(Etatsfin!D1="",Etatsfin!D1="A saisir ici"),CONCATENATE(" Unité de compte : ",Etatsfin!P1),CONCATENATE(" Unité de compte : ",Etatsfin!D1)) -> Unité de compte : 000' DZD | D3: =Etatsfin!D5 -> 39417 | E3: =Etatsfin!E5 -> 39783 | F3: =Etatsfin!F5 -> 40178 | G3: =Etatsfin!G5 -> 40543
A4: (Exploitation)
A5: =CONCATENATE(" Rappel du Chiffre d'Affaires (en ",Etatsfin!O1,")") -> Rappel du Chiffre d'Affaires (en 000' DZD) | D5: =Saisie!E120 -> 416226.91 | E5: =Saisie!F120 -> 717966.67 | F5: =Saisie!G120 -> 907795.82 | G5: =Saisie!H120 -> 1616204.7
A6: Evolution du CA (annualisée) | D6: =IF(OR(Saisie!D120=0,Saisie!E120=0,Etatsfin!D6=0),"n/d ",((Saisie!E120/Saisie!D120)*(1/Etatsfin!D6))-1) -> n/d | E6: =IF(OR(Saisie!E120=0,Saisie!F120=0,Etatsfin!E6=0),"n/d ",((Saisie!F120/Saisie!E120)*(1/Etatsfin!E6))-1) -> 0.72022759 | F6: =IF(OR(Saisie!F120=0,Saisie!G120=0,Etatsfin!F6=0),"n/d ",((Saisie!G120/Saisie!F120)*(1/Etatsfin!F6))-1) -> 0.16836802 | G6: =IF(OR(Saisie!G120=0,Saisie!H120=0,Etatsfin!G6=0),"n/d ",((Saisie!H120/Saisie!G120)*(1/Etatsfin!G6))-1) -> 0.78036144
A7: % des exportations | D7: =IF(Saisie!E120=0,"n/d ",Saisie!E121/Saisie!E120) -> 0 | E7: =IF(Saisie!F120=0,"n/d ",Saisie!F121/Saisie!F120) -> 0 | F7: =IF(Saisie!G120=0,"n/d ",Saisie!G121/Saisie!G120) -> 0 | G7: =IF(Saisie!H120=0,"n/d ",Saisie!H121/Saisie!H120) -> 0
A9: Marge commerciale / CA | D9: =IF(D5=0,"n/d",Saisie!E133/D5) -> 0.12251641 | E9: =IF(E5=0,"n/d",Saisie!F133/E5) -> 0.10949735 | F9: =IF(F5=0,"n/d",Saisie!G133/F5) -> 0.17789395 | G9: =IF(G5=0,"n/d",Saisie!H133/G5) -> 0.14723784
A10: EBE / CA | D10: =IF(D5=0,"n/d",Saisie!E148/D5) -> 0.071688983 | E10: =IF(E5=0,"n/d",Saisie!F148/E5) -> 0.062834775 | F10: =IF(F5=0,"n/d",Saisie!G148/F5) -> 0.094057213 | G10: =IF(G5=0,"n/d",Saisie!H148/G5) -> 0.070562816
A11: Résultat économique / CA | D11: =IF(D5=0,"n/d ", Saisie!E155/D5) -> 0.044328052 | E11: =IF(E5=0,"n/d ", Saisie!F155/E5) -> 0.035864891 | F11: =IF(F5=0,"n/d ", Saisie!G155/F5) -> 0.071057442 | G11: =IF(G5=0,"n/d ", Saisie!H155/G5) -> 0.054379601
A12: Achats & Sous-traitance / CA | D12: =IF(D5=0,"n/d ",Saisie!E126/D5) -> 0.87748359 | E12: =IF(E5=0,"n/d ",Saisie!F126/E5) -> 0.89050265 | F12: =IF(F5=0,"n/d ",Saisie!G126/F5) -> 0.84354746 | G12: =IF(G5=0,"n/d ",Saisie!H126/G5) -> 0.85328948
A13: Charges de personnel / CA | D13: =IF(D5=0,"n/d ",Saisie!E134/D5) -> 0.015665049 | E13: =IF(E5=0,"n/d ",Saisie!F134/E5) -> 0.01764508 | F13: =IF(F5=0,"n/d ",Saisie!G134/F5) -> 0.036177278 | G13: =IF(G5=0,"n/d ",Saisie!H134/G5) -> 0.033419007
A14: Autres charges / CA | D14: =IF(D5=0,"n/d ",Saisie!E140/D5) -> 0.035162376 | E14: =IF(E5=0,"n/d ",Saisie!F140/E5) -> 0.029017492 | F14: =IF(F5=0,"n/d ",Saisie!G140/F5) -> 0.047659456 | G14: =IF(G5=0,"n/d ",Saisie!H140/G5) -> 0.043256021
A15: (Rentabilité)
A16: Résultat net / CA | D16: =IF(D5=0,"n/d",Saisie!E183/D5) -> 0.02162392 | E16: =IF(E5=0,"n/d",Saisie!F183/E5) -> 0.02560429 | F16: =IF(F5=0,"n/d",Saisie!G183/F5) -> 0.023538694 | G16: =IF(G5=0,"n/d",Saisie!H183/G5) -> 0.017180167
A17: Résultat net / Fonds Propres | D17: =IF(OR(Etatsfin!J8=0,Etatsfin!D6=0),"n/d",Etatsfin!D73/Etatsfin!D6/Etatsfin!J8) -> 0.035053453 | E17: =IF(OR(Etatsfin!K8=0,Etatsfin!E6=0),"n/d",Etatsfin!E73/Etatsfin!E6/Etatsfin!K8) -> 0.17381837 | F17: =IF(OR(Etatsfin!L8=0,Etatsfin!F6=0),"n/d",Etatsfin!F73/Etatsfin!F6/Etatsfin!L8) -> 0.15570346 | G17: =IF(OR(Etatsfin!M8=0,Etatsfin!G6=0),"n/d",Etatsfin!G73/Etatsfin!G6/Etatsfin!M8) -> 0.17680814
A18: Résultat net / Total Actif | D18: =IF(OR(Etatsfin!D31=0,Etatsfin!D6=0),"n/d ",(Etatsfin!D73/Etatsfin!D6)/Etatsfin!D31) -> 0.0079374145 | E18: =IF(OR(Etatsfin!E31=0,Etatsfin!E6=0),"n/d ",(Etatsfin!E73/Etatsfin!E6)/Etatsfin!E31) -> 0.028374982 | F18: =IF(OR(Etatsfin!F31=0,Etatsfin!F6=0),"n/d ",(Etatsfin!F73/Etatsfin!F6)/Etatsfin!F31) -> 0.02538716 | G18: =IF(OR(Etatsfin!G31=0,Etatsfin!G6=0),"n/d ",(Etatsfin!G73/Etatsfin!G6)/Etatsfin!G31) -> 0.025046892
A19: CA / Total Actif (en X) | D19: =IF(OR(Etatsfin!D31=0,Etatsfin!D6=0),"n/d ",(D5/Etatsfin!D6)/Etatsfin!D31) -> 0.3670664 | E19: =IF(OR(Etatsfin!E31=0,Etatsfin!E6=0),"n/d ",(E5/Etatsfin!E6)/Etatsfin!E31) -> 1.108212 | F19: =IF(OR(Etatsfin!F31=0,Etatsfin!F6=0),"n/d ",(F5/Etatsfin!F6)/Etatsfin!F31) -> 1.0785288 | G19: =IF(OR(Etatsfin!G31=0,Etatsfin!G6=0),"n/d ",(G5/Etatsfin!G6)/Etatsfin!G31) -> 1.4578957
A20: Total Actif / Fonds Propres (en X) | D20: =IF(OR(Etatsfin!J8=0,Etatsfin!D6=0),"n/d",Etatsfin!D31/Etatsfin!D6/Etatsfin!J8) -> 1.4720769 | E20: =IF(OR(Etatsfin!K8=0,Etatsfin!E6=0),"n/d",Etatsfin!E31/Etatsfin!E6/Etatsfin!K8) -> 6.1090243 | F20: =IF(OR(Etatsfin!L8=0,Etatsfin!F6=0),"n/d",Etatsfin!F31/Etatsfin!F6/Etatsfin!L8) -> 5.6673483 | G20: =IF(OR(Etatsfin!M8=0,Etatsfin!G6=0),"n/d",Etatsfin!G31/Etatsfin!G6/Etatsfin!M8) -> 7.0590852
A21: Tx de distrib. dividendes [=Dividendes au titre de n / RN(n)] | D21: =IF(Etatsfin!J68=0,"n/d ",(Etatsfin!J68/Etatsfin!J12)) -> n/d | E21: =IF(Etatsfin!K68=0,"n/d ",(Etatsfin!K68/Etatsfin!K12)) -> n/d | F21: =IF(Etatsfin!L68=0,"n/d ",(Etatsfin!L68/Etatsfin!L12)) -> n/d | G21: =IF(Etatsfin!M68=0,"n/d ",(Etatsfin!M68/Etatsfin!M12)) -> n/d
A22: (Dette)
A23: Résultat financier retraité / CA | D23: =IF(D5=0,"n/d",(Saisie!E156-Saisie!E161+Saisie!E158/3)/D5) -> 0.012855387 | E23: =IF(E5=0,"n/d",(Saisie!F156-Saisie!F161+Saisie!F158/3)/E5) -> 0.0099385176 | F23: =IF(F5=0,"n/d",(Saisie!G156-Saisie!G161+Saisie!G158/3)/F5) -> 0.025691839 | G23: =IF(G5=0,"n/d",(Saisie!H156-Saisie!H161+Saisie!H158/3)/G5) -> 0.032874261
A24: EBE / Résultat fin. retraité | D24: =IF((Saisie!E156+Saisie!E158/3-Saisie!E161=0),"n/d",Saisie!E148/(Saisie!E156+Saisie!E158/3-Saisie!E161)) -> 5.5765714 | E24: =IF((Saisie!F156+Saisie!F158/3-Saisie!F161=0),"n/d",Saisie!F148/(Saisie!F156+Saisie!F158/3-Saisie!F161)) -> 6.3223488 | F24: =IF((Saisie!G156+Saisie!G158/3-Saisie!G161=0),"n/d",Saisie!G148/(Saisie!G156+Saisie!G158/3-Saisie!G161)) -> 3.6609762 | G24: =IF((Saisie!H156+Saisie!H158/3-Saisie!H161=0),"n/d",Saisie!H148/(Saisie!H156+Saisie!H158/3-Saisie!H161)) -> 2.1464457
A25: EBE - Invest. indust. / Résultat financier retraité | D25: =IF(Etatsfin!J43=0,"n/d ",(Etatsfin!D56-Etatsfin!J56)/Etatsfin!J43) -> -8.5331589 | E25: =IF(Etatsfin!K43=0,"n/d ",(Etatsfin!E56-Etatsfin!K56)/Etatsfin!K43) -> -2.2872787 | F25: =IF(Etatsfin!L43=0,"n/d ",(Etatsfin!F56-Etatsfin!L56)/Etatsfin!L43) -> 3.1401559 | G25: =IF(Etatsfin!M43=0,"n/d ",(Etatsfin!G56-Etatsfin!M56)/Etatsfin!M43) -> 1.6466192
A27: EBE / Service de la dette (=frais fin.+échéance DLMT+ann.cdt-bail) | D27: =IF(OR(Etatsfin!D63+Saisie!D192+Etatsfin!D64=0,Saisie!E192=0,Etatsfin!D6>1.003,Etatsfin!D6<1),"n/d ",Etatsfin!D56/(Etatsfin!D63+Saisie!E192+Etatsfin!D64)) -> n/d | E27: =IF(OR(Etatsfin!E63+Saisie!E192+Etatsfin!E64=0,Saisie!F192=0,Etatsfin!E6>1.003,Etatsfin!E6<1),"n/d ",Etatsfin!E56/(Etatsfin!E63+Saisie!F192+Etatsfin!E64)) -> n/d | F27: =IF(OR(Etatsfin!F63+Saisie!F192+Etatsfin!F64=0,Saisie!G192=0,Etatsfin!F6>1.003,Etatsfin!F6<1),"n/d ",Etatsfin!F56/(Etatsfin!F63+Saisie!G192+Etatsfin!F64)) -> n/d | G27: =IF(OR(Etatsfin!G63+Saisie!G192+Etatsfin!G64=0,Saisie!H192=0,Etatsfin!G6>1.003,Etatsfin!G6<1),"n/d ",Etatsfin!G56/(Etatsfin!G63+Saisie!H192+Etatsfin!G64)) -> n/d
A28: EBE - Invest. indust. / Service de la dette | D28: =IF(OR(Etatsfin!D63+Saisie!D192+Etatsfin!D64=0,Saisie!E192=0,Etatsfin!D6>1.003,Etatsfin!D6<1),"n/d ",(Etatsfin!D56-Etatsfin!J56)/(Etatsfin!D63+Saisie!E192+Etatsfin!D64)) -> n/d | E28: =IF(OR(Etatsfin!E63+Saisie!E192+Etatsfin!E64=0,Saisie!F192=0,Etatsfin!E6>1.003,Etatsfin!E6<1),"n/d ",(Etatsfin!E56-Etatsfin!K56)/(Etatsfin!E63+Saisie!F192+Etatsfin!E64)) -> n/d | F28: =IF(OR(Etatsfin!F63+Saisie!F192+Etatsfin!F64=0,Saisie!G192=0,Etatsfin!F6>1.003,Etatsfin!F6<1),"n/d ",(Etatsfin!F56-Etatsfin!L56)/(Etatsfin!F63+Saisie!G192+Etatsfin!F64)) -> n/d | G28: =IF(OR(Etatsfin!G63+Saisie!G192+Etatsfin!G64=0,Saisie!H192=0,Etatsfin!G6>1.003,Etatsfin!G6<1),"n/d ",(Etatsfin!G56-Etatsfin!M56)/(Etatsfin!G63+Saisie!H192+Etatsfin!G64)) -> n/d
A29: CFEN+(Frais fin.+1/3 Ann.cdt-bail) - Inv. ind. / Serv. de la dette | D29: =IF(OR(Etatsfin!D63+Saisie!D192+Etatsfin!D64=0,Saisie!E192=0,Etatsfin!D6>1.003,Etatsfin!D6<1),"n/d ",(Etatsfin!J54+(Etatsfin!D63+(Etatsfin!D64/3))-Etatsfin!J56)/(Etatsfin!D63+Saisie!E192+Etatsfin!D64)) -> n/d | E29: =IF(OR(Etatsfin!E63+Saisie!E192+Etatsfin!E64=0,Saisie!F192=0,Etatsfin!E6>1.003,Etatsfin!E6<1),"n/d ",(Etatsfin!K54+(Etatsfin!E63+(Etatsfin!E64/3))-Etatsfin!K56)/(Etatsfin!E63+Saisie!F192+Etatsfin!E64)) -> n/d | F29: =IF(OR(Etatsfin!F63+Saisie!F192+Etatsfin!F64=0,Saisie!G192=0,Etatsfin!F6>1.003,Etatsfin!F6<1),"n/d ",(Etatsfin!L54+(Etatsfin!F63+(Etatsfin!F64/3))-Etatsfin!L56)/(Etatsfin!F63+Saisie!G192+Etatsfin!F64)) -> n/d | G29: =IF(OR(Etatsfin!G63+Saisie!G192+Etatsfin!G64=0,Saisie!H192=0,Etatsfin!G6>1.003,Etatsfin!G6<1),"n/d ",(Etatsfin!M54+(Etatsfin!G63+(Etatsfin!G64/3))-Etatsfin!M56)/(Etatsfin!G63+Saisie!H192+Etatsfin!G64)) -> n/d
A31: =CONCATENATE(" Dettes financières totales (en ",Etatsfin!O1,")") -> Dettes financières totales (en 000' DZD) | D31: =Etatsfin!J17+Etatsfin!J29+Etatsfin!J34+(2*Etatsfin!J35/3) -> 135768.57 | E31: =Etatsfin!K17+Etatsfin!K29+Etatsfin!K34+(2*Etatsfin!K35/3) -> 318123.7 | F31: =Etatsfin!L17+Etatsfin!L29+Etatsfin!L34+(2*Etatsfin!L35/3) -> 301703.26 | G31: =Etatsfin!M17+Etatsfin!M29+Etatsfin!M34+(2*Etatsfin!M35/3) -> 583688.85
A32: =CONCATENATE(" Dettes financières totales nettes (en ",Etatsfin!O1,")") -> Dettes financières totales nettes (en 000' DZD) | D32: =D31-Etatsfin!D27-Etatsfin!D28 -> 105364.63 | E32: =E31-Etatsfin!E27-Etatsfin!E28 -> 191703.74 | F32: =F31-Etatsfin!F27-Etatsfin!F28 -> 278975.2 | G32: =G31-Etatsfin!G27-Etatsfin!G28 -> 479069.15
A33: Dettes financières Court Terme (yc part CT de la Dette LT) | D33: =Saisie!E113+Saisie!E192 -> 36801.173 | E33: =Saisie!F113+Saisie!F192 -> 188896.56 | F33: =Saisie!G113+Saisie!G192 -> 167884.05 | G33: =Saisie!H113+Saisie!H192 -> 451915.46
A34: Dettes financières MLT (yc part en capital du CB et hors bilan) | D34: =Saisie!E86-Saisie!E90+2/3*(Saisie!E116)+Saisie!E115 -> 45584 | E34: =Saisie!F86-Saisie!F90+2/3*(Saisie!F116)+Saisie!F115 -> 50953.402 | F34: =Saisie!G86-Saisie!G90+2/3*(Saisie!G116)+Saisie!G115 -> 61088.814 | G34: =Saisie!H86-Saisie!H90+2/3*(Saisie!H116)+Saisie!H115 -> 59043.006
A36: Dettes financières totales / Fonds propres | D36: =IF(Etatsfin!J8=0,"n/d",D31/Etatsfin!J8) -> 1.5863051 | E36: =IF(Etatsfin!K8=0,"n/d",E31/Etatsfin!K8) -> 3.0162192 | F36: =IF(Etatsfin!L8=0,"n/d",F31/Etatsfin!L8) -> 2.3790958 | G36: =IF(Etatsfin!M8=0,"n/d",G31/Etatsfin!M8) -> 3.7167205
A37: Dettes financières totales nettes / Fonds propres | D37: =IF(Etatsfin!J8=0,"n/d",D32/Etatsfin!J8) -> 1.2310688 | E37: =IF(Etatsfin!K8=0,"n/d",E32/Etatsfin!K8) -> 1.8175964 | F37: =IF(Etatsfin!L8=0,"n/d",F32/Etatsfin!L8) -> 2.1998726 | G37: =IF(Etatsfin!M8=0,"n/d",G32/Etatsfin!M8) -> 3.0505399
A38: Dettes fin. tot. / F. propres nets d'incorporels (=Gross Gearing) | D38: =IF((Etatsfin!J8-Etatsfin!D15-Etatsfin!D17)=0,"n/d ",D31/(Etatsfin!J8-Etatsfin!D15-Etatsfin!D17)) -> 1.5863051 | E38: =IF((Etatsfin!K8-Etatsfin!E15-Etatsfin!E17)=0,"n/d ",E31/(Etatsfin!K8-Etatsfin!E15-Etatsfin!E17)) -> 3.0173993 | F38: =IF((Etatsfin!L8-Etatsfin!F15-Etatsfin!F17)=0,"n/d ",F31/(Etatsfin!L8-Etatsfin!F15-Etatsfin!F17)) -> 2.3793685 | G38: =IF((Etatsfin!M8-Etatsfin!G15-Etatsfin!G17)=0,"n/d ",G31/(Etatsfin!M8-Etatsfin!G15-Etatsfin!G17)) -> 3.7266674
A39: Dettes fin. tot. nettes / F. prop. nets d'incorporels (=Net Gearing) | D39: =IF((Etatsfin!J8-Etatsfin!D15-Etatsfin!D17)=0,"n/d ",D32/(Etatsfin!J8-Etatsfin!D15-Etatsfin!D17)) -> 1.2310688 | E39: =IF((Etatsfin!K8-Etatsfin!E15-Etatsfin!E17)=0,"n/d ",E32/(Etatsfin!K8-Etatsfin!E15-Etatsfin!E17)) -> 1.8183076 | F39: =IF((Etatsfin!L8-Etatsfin!F15-Etatsfin!F17)=0,"n/d ",F32/(Etatsfin!L8-Etatsfin!F15-Etatsfin!F17)) -> 2.2001248 | G39: =IF((Etatsfin!M8-Etatsfin!G15-Etatsfin!G17)=0,"n/d ",G32/(Etatsfin!M8-Etatsfin!G15-Etatsfin!G17)) -> 3.0587039
A40: Dettes totales / F. prop. nets d'incorporels (=Leverage) | D40: =IF((Etatsfin!J8-Etatsfin!D15-Etatsfin!D17)=0,"n/d ",(D31+Etatsfin!J23-Etatsfin!J29)/(Etatsfin!J8-Etatsfin!D15-Etatsfin!D17)) -> 3.4162306 | E40: =IF((Etatsfin!K8-Etatsfin!E15-Etatsfin!E17)=0,"n/d ",(E31+Etatsfin!K23-Etatsfin!K29)/(Etatsfin!K8-Etatsfin!E15-Etatsfin!E17)) -> 5.1277668 | F40: =IF((Etatsfin!L8-Etatsfin!F15-Etatsfin!F17)=0,"n/d ",(F31+Etatsfin!L23-Etatsfin!L29)/(Etatsfin!L8-Etatsfin!F15-Etatsfin!F17)) -> 5.2211975 | G40: =IF((Etatsfin!M8-Etatsfin!G15-Etatsfin!G17)=0,"n/d ",(G31+Etatsfin!M23-Etatsfin!M29)/(Etatsfin!M8-Etatsfin!G15-Etatsfin!G17)) -> 6.1263782
A42: Dettes financières totales / EBE (en années) | D42: =IF(Etatsfin!D56=0,"n/d",Etatsfin!D6*(D31/Etatsfin!D56)) -> 13.650166 | E42: =IF(Etatsfin!E56=0,"n/d",Etatsfin!E6*(E31/Etatsfin!E56)) -> 7.0709847 | F42: =IF(Etatsfin!F56=0,"n/d",Etatsfin!F6*(F31/Etatsfin!F56)) -> 3.8238772 | G42: =IF(Etatsfin!G56=0,"n/d",Etatsfin!G6*(G31/Etatsfin!G56)) -> 5.1181044
A43: Dettes financières totales nettes / EBE (en années) | D43: =IF(Etatsfin!D56=0,"n/d ",Etatsfin!D6*(D32/Etatsfin!D56)) -> 10.593355 | E43: =IF(Etatsfin!E56=0,"n/d ",Etatsfin!E6*(E32/Etatsfin!E56)) -> 4.2610287 | F43: =IF(Etatsfin!F56=0,"n/d ",Etatsfin!F6*(F32/Etatsfin!F56)) -> 3.5358151 | G43: =IF(Etatsfin!G56=0,"n/d ",Etatsfin!G6*(G32/Etatsfin!G56)) -> 4.2007414
A44: Dettes financières MLT / EBE (en années) | D44: =IF(OR(Saisie!D148=0,Etatsfin!D56=0),"n/d ",Etatsfin!D6*(D34/Saisie!E148)) -> n/d | E44: =IF(OR(Saisie!E148=0,Etatsfin!E56=0),"n/d ",Etatsfin!E6*(E34/Saisie!F148)) -> 1.1325491 | F44: =IF(OR(Saisie!F148=0,Etatsfin!F56=0),"n/d ",Etatsfin!F6*(F34/Saisie!G148)) -> 0.77425789 | G44: =IF(OR(Saisie!G148=0,Etatsfin!G56=0),"n/d ",Etatsfin!G6*(G34/Saisie!H148)) -> 0.5177215
A45: Dettes financières totales / CFEN (en années) | D45: =IF(OR(Etatsfin!J54<0,Etatsfin!J54=0),"n/d",Etatsfin!D6*D31/Etatsfin!J54) -> n/d | E45: =IF(OR(Etatsfin!K54<0,Etatsfin!K54=0),"n/d",Etatsfin!E6*E31/Etatsfin!K54) -> n/d | F45: =IF(OR(Etatsfin!L54<0,Etatsfin!L54=0),"n/d",Etatsfin!F6*F31/Etatsfin!L54) -> n/d | G45: =IF(OR(Etatsfin!M54<0,Etatsfin!M54=0),"n/d",Etatsfin!G6*G31/Etatsfin!M54) -> n/d
A46: Frais fi. / Dette fi. totale moyenne de l'année (hors cdt-bail) | D46: =IF(OR((Saisie!E86+Saisie!E96+Saisie!E112+Saisie!E115)+(Etatsfin!J17+Etatsfin!J29+Etatsfin!J34)=0,Etatsfin!D6=0),"n/d ",(Etatsfin!D63/Etatsfin!D6)/((Saisie!E86+Saisie!E96+Saisie!E112+Saisie!E115+Etatsfin!J17+Etatsfin!J29+Etatsfin!J34)/2)) -> 0.013136958 | E46: =IF(OR((Saisie!F86+Saisie!F96+Saisie!F112+Saisie!F115)+(Etatsfin!K17+Etatsfin!K29+Etatsfin!K34)=0,Etatsfin!E6=0),"n/d ",(Etatsfin!E63/Etatsfin!E6)/((Saisie!F86+Saisie!F96+Saisie!F112+Saisie!F115+Etatsfin!K17+Etatsfin!K29+Etatsfin!K34)/2)) -> 0.022368747 | F46: =IF(OR((Saisie!G86+Saisie!G96+Saisie!G112+Saisie!G115)+(Etatsfin!L17+Etatsfin!L29+Etatsfin!L34)=0,Etatsfin!F6=0),"n/d ",(Etatsfin!F63/Etatsfin!F6)/((Saisie!G86+Saisie!G96+Saisie!G112+Saisie!G115+Etatsfin!L17+Etatsfin!L29+Etatsfin!L34)/2)) -> 0.07180557 | G46: =IF(OR((Saisie!H86+Saisie!H96+Saisie!H112+Saisie!H115)+(Etatsfin!M17+Etatsfin!M29+Etatsfin!M34)=0,Etatsfin!G6=0),"n/d ",(Etatsfin!G63/Etatsfin!G6)/((Saisie!H86+Saisie!H96+Saisie!H112+Saisie!H115+Etatsfin!M17+Etatsfin!M29+Etatsfin!M34)/2)) -> 0.10069564
A48: Ratio "courant" (Liquidité générale; "Current Ratio") (=Act.circ./Exig.CT) | D48: =IF(Etatsfin!J23=0,"n/d ",Etatsfin!D21/Etatsfin!J23) -> 1.356389 | E48: =IF(Etatsfin!K23=0,"n/d ",Etatsfin!E21/Etatsfin!K23) -> 1.1871818 | F48: =IF(Etatsfin!L23=0,"n/d ",Etatsfin!F21/Etatsfin!L23) -> 1.2799196 | G48: =IF(Etatsfin!M23=0,"n/d ",Etatsfin!G21/Etatsfin!M23) -> 1.221463
A49: Liquidité réduite ("Quick Ratio") [(=Actifs Circulants - Stocks) /Exig.CT] | D49: =IF(Etatsfin!J23=0,"n/d ",(Etatsfin!D21-Etatsfin!D23)/Etatsfin!J23) -> 0.79441557 | E49: =IF(Etatsfin!K23=0,"n/d ",(Etatsfin!E21-Etatsfin!E23)/Etatsfin!K23) -> 0.54859559 | F49: =IF(Etatsfin!L23=0,"n/d ",(Etatsfin!F21-Etatsfin!F23)/Etatsfin!L23) -> 0.3792772 | G49: =IF(Etatsfin!M23=0,"n/d ",(Etatsfin!G21-Etatsfin!G23)/Etatsfin!M23) -> 0.68433068
A50: (Investissement)
A51: Investissements industriels / Dot. aux amts | D51: =IF(Etatsfin!D58=0,"n/d ",Etatsfin!J56/Etatsfin!D58) -> 6.6293811 | E51: =IF(Etatsfin!E58=0,"n/d ",Etatsfin!K56/Etatsfin!E58) -> 3.1726846 | F51: =IF(Etatsfin!F58=0,"n/d ",Etatsfin!L56/Etatsfin!F58) -> 0.58178113 | G51: =IF(Etatsfin!G58=0,"n/d ",Etatsfin!M56/Etatsfin!G58) -> 0.93658803
A52: Dotation aux amortissements / Immo. d'exploitation brutes | D52: =IF(OR(Etatsfin!D10=0,Etatsfin!D6=0),"n/d ",(Etatsfin!D58/Etatsfin!D6)/Etatsfin!D10) -> 0.043095567 | E52: =IF(OR(Etatsfin!E10=0,Etatsfin!E6=0),"n/d ",(Etatsfin!E58/Etatsfin!E6)/Etatsfin!E10) -> 0.1291502 | F52: =IF(OR(Etatsfin!F10=0,Etatsfin!F6=0),"n/d ",(Etatsfin!F58/Etatsfin!F6)/Etatsfin!F10) -> 0.11933342 | G52: =IF(OR(Etatsfin!G10=0,Etatsfin!G6=0),"n/d ",(Etatsfin!G58/Etatsfin!G6)/Etatsfin!G10) -> 0.15127617
A53: (Besoin en fonds de roulement)
A54: Rotation des stocks (Jours de CA) | D54: =IF(D5=0,"n/d",Saisie!E37/D5*360*Etatsfin!D6) -> 282.04105 | E54: =IF(E5=0,"n/d",Saisie!F37/E5*360*Etatsfin!E6) -> 132.08756 | F54: =IF(F5=0,"n/d",Saisie!G37/F5*360*Etatsfin!F6) -> 204.16989 | G54: =IF(G5=0,"n/d",Saisie!H37/G5*360*Etatsfin!G6) -> 99.036897
A55: Délais clients (Jours de CA) | D55: =IF(D5=0,"n/d",Saisie!E46/D5*360*Etatsfin!D6) -> 279.50253 | E55: =IF(E5=0,"n/d",Saisie!F46/E5*360*Etatsfin!E6) -> 28.857895 | F55: =IF(F5=0,"n/d",Saisie!G46/F5*360*Etatsfin!F6) -> 50.463787 | G55: =IF(G5=0,"n/d",Saisie!H46/G5*360*Etatsfin!G6) -> 85.468937
A56: Crédit fournisseurs (Jours de CA) | D56: =IF(D5=0,"n/d",Saisie!E100/D5*360*Etatsfin!D6) -> 179.0255 | E56: =IF(E5=0,"n/d",Saisie!F100/E5*360*Etatsfin!E6) -> 103.56701 | F56: =IF(F5=0,"n/d",Saisie!G100/F5*360*Etatsfin!F6) -> 55.830711 | G56: =IF(G5=0,"n/d",Saisie!H100/G5*360*Etatsfin!G6) -> 73.824623
A57: Crédit fournisseurs (Jours d'achats) | D57: =IF(Saisie!E126=0,"n/d",Saisie!E100/Saisie!E126*360*Etatsfin!D6) -> 204.02148 | E57: =IF(Saisie!F126=0,"n/d",Saisie!F100/Saisie!F126*360*Etatsfin!E6) -> 116.30174 | F57: =IF(Saisie!G126=0,"n/d",Saisie!G100/Saisie!G126*360*Etatsfin!F6) -> 66.185619 | G57: =IF(Saisie!H126=0,"n/d",Saisie!H100/Saisie!H126*360*Etatsfin!G6) -> 86.517676
A58: BFR (Jours de CA) | D58: =Etatsfin!D37 -> 195.46227 | E58: =Etatsfin!E37 -> 70.129975 | F58: =Etatsfin!F37 -> 125.75105 | G58: =Etatsfin!G37 -> 118.32029

Sheet Hypo
L1: Zone réservée.
A2: Voulez-vous des hypothèses plus détaillées que ci-dessous ? (O / N) : | H2: (En l'absence de saisie "O" ou "N", | L2: Ne rien modifier.
A3: (Pour des explications, cliquer le "bouton de dégroupage" ci-dessous à gauche) | H3: la réponse par défaut est "N") | L3: =IF(OR(G2="O",G2="Oui"),0,1) -> 1 | M3: =IF(L3=1,0,1) -> 0
A5: a) En cas de réponse négative à la question ci-dessus, l'utilisateur saisit ses hypothèses dans les cellules de
A6: cette Feuille "Hypo", sans aucune autre action particulière.
A8: b) En cas de réponse positive, l'utilisateur doit saisir 8 postes d'hypothèses (CA, Marge Commerciale, Frais de
A9: personnel, Autres charges, et EBE, ainsi que Nouveaux Emprunts à MLT, Rembts de DLMT et Investissements
A10: financiers), dans les zones Compte de Résultat et Tableau de Flux de "PrSept".
A12: Il devra alors dans "PrSept" afficher les lignes de saisie détaillée (cellules jaunes) avec les "boutons de
A13: dégroupage" (à gauche, bord du cadre). S'il ne veut pas détailler l'un de ces 8 postes, il devra quand même saisir
A14: un total de celui-ci dans une quelconque des cellules jaunes, puis le masquer à l'aide du "bouton de dégroupage".
A15: Il convient d'ailleurs de noter que l'utilisateur peut ajouter ou retirer autant de lignes de détails qu'il souhaite dans
A16: ces 8 postes, si et seulement si il en "insère" ou en "supprime" entre la première ligne et la dernière ligne
A17: existantes. (Dans ce cas, Excel met en effet automatiquement à jour tout ce qui est nécessaire.)
A19: Pour l'impression et l'affichage, l'utilisateur peut, toujours grâce aux "boutons", imprimer et/ou masquer ce qu'il
A20: souhaite : il lui incombe de régler les paramètres qui lui conviennent, puisqu' il n'a pas choisi l'option par défaut.
L23: Date: | M23: =TODAY() -> 46304 | N23: =TODAY() -> 46304
A24: Société : | B24: =IF(PrSept!B19="Saisir sur Saisie ou Etatsfin",CONCATENATE(PrSept!B19," ou PrSept"),PrSept!B19) -> MERIPLAST
A25: Groupe : | B25: =IF(PrSept!B20="Saisir sur Saisie ou Etatsfin",CONCATENATE(PrSept!B20," ou PrSept"),PrSept!B20) -> MERIPLAST | L25: Scénario : | M25: A saisir ici
E29: =PrSept!E25 -> Historique | H29: =PrSept!H25 -> Prévisions
A30: Hypothèses retenues : | E30: =PrSept!E26 -> 39783 | F30: =PrSept!F26 -> 40178 | G30: =PrSept!G26 -> 40543 | H30: =PrSept!H26 -> 40909 | I30: =PrSept!I26 -> 41275 | J30: =PrSept!J26 -> 41641 | K30: =PrSept!K26 -> 42007 | L30: =PrSept!L26 -> 42373 | ... N30: =PrSept!N26 -> 43105 | O30: Hypothèses retenues :
A31: =IF(OR(PrSept!T27<1,PrSept!T27>1.003)," (Message à effacer après lecture) La durée de l'un des exercices de l'historique n'est pas de 12 mois. Comme pour toutes les autres Feuilles, les chiffres ci-dessous exprimés en % ou en jours sont annualisés; ceux exprimés en montant ne le sont pas.","")
A32: Eléments de l'exploitation : | B32: (en %) | O32: Eléments de l'exploitation : (en %)
A33: Evolution du CA (annualisée) | E33: =PrSept!E105 -> 4.1606828 | F33: =PrSept!F105 -> 0.17156903 | G33: =PrSept!G105 -> 0.92669252 | O33: Evolution du CA (annualisée)
A34: =CONCATENATE("CA (en ",PrSept!O21,")") -> CA (en KF) | B34: (calculé) | E34: =PrSept!E104 -> 717966.67 | F34: =PrSept!F104 -> 907795.82 | G34: =PrSept!G104 -> 1616204.7 | O34: =A34 -> CA (en KF) | Q34: (calculé)
A35: Marge commerciale / CA | E35: =PrSept!E119 -> 0.10949735 | F35: =PrSept!F119 -> 0.17789395 | G35: =PrSept!G119 -> 0.14723784 | O35: Marge commerciale / CA
A36: EBE / CA | E36: =PrSept!E136 -> 0.062834775 | F36: =PrSept!F136 -> 0.094057213 | G36: =PrSept!G136 -> 0.070562816 | O36: EBE / CA
A37: Dotation aux amortiss. / Immo. d'exploitation brutes | E37: =IF(OR(PrSept!E29=0,PrSept!R27=0),"n/d ",(PrSept!E143/PrSept!R27)/PrSept!E29) -> 0.1291502 | F37: =IF(OR(PrSept!F29=0,PrSept!S27=0),"n/d ",(PrSept!F143/PrSept!S27)/PrSept!F29) -> 0.11933342 | G37: =IF(OR(PrSept!G29=0,PrSept!T27=0),"n/d ",(PrSept!G143/PrSept!T27)/PrSept!G29) -> 0.15127617 | O37: Dotation aux amortiss. / Immo. d'exploitation brutes
A38: Eléments de coût du capital : | B38: (en %) | O38: Eléments de coût du capital : (en %)
A39: Frais fi. / Dette fi. totale moyenne de l'année (hors cdt-bail) | E39: =PrSept!E16 -> 0.031355583 | F39: =PrSept!F16 -> 0.068560631 | G39: =PrSept!G16 -> 0.13383155 | O39: Frais fi. / Dette fi. totale moyenne de l'année (hors cdt-bail)
A40: Produits financiers / VMP et Disponible moyens de l'année | E40: =IF(OR((Etatsfin!D27+Etatsfin!D28+PrSept!E47=0),PrSept!R27=0,Etatsfin!D31=0,Etatsfin!J31=0),"n/d ",(PrSept!E151/PrSept!R27)/((Etatsfin!D27+Etatsfin!D28+PrSept!E47)/2)) -> 0 | F40: =IF(OR((PrSept!E47+PrSept!F47=0),PrSept!S27=0,PrSept!E49=0,PrSept!E82=0),"n/d ",(PrSept!F151/PrSept!S27)/((PrSept!E47+PrSept!F47)/2)) -> 0 | G40: =IF(OR((PrSept!F47+PrSept!G47=0),PrSept!T27=0,PrSept!F49=0,PrSept!F82=0),"n/d ",(PrSept!G151/PrSept!T27)/((PrSept!F47+PrSept!G47)/2)) -> 0.075978129 | O40: Produits financiers / VMP et Disponible moyens de l'année
A41: Taux d'IS (= IS / Résultat avant IS) | E41: =PrSept!E17 -> 0.24999982 | F41: =PrSept!F17 -> 0.24512003 | G41: =PrSept!G17 -> 0.20112084 | O41: Taux d'IS (= IS / Résultat avant IS)
A42: Tx de distrib. de dividendes [=Dividendes au titre de n / RN(n)] | E42: =IF(PrSept!E165=0,"n/d ",(PrSept!E165-PrSept!E57)/PrSept!E165) -> 9.7916411e-07 | F42: =IF(PrSept!F165=0,"n/d ",(PrSept!F165-PrSept!F57)/PrSept!F165) -> 4.225828e-06 | G42: =IF(PrSept!G165=0,"n/d ",(PrSept!G165-PrSept!G57)/PrSept!G165) -> 2.1608643e-07 | O42: Tx de distrib. de dividendes [=Dividendes au titre de n / RN(n)]
A43: Eléments de haut-de-bilan : | B43: =CONCATENATE("(en ",PrSept!O21,")") -> (en KF) | E43: =IF(OR(H41<0,I41<0,J41<0,K41<0,L41<0,M41<0,N41<0,H42<0,I42<0,J42<0,K42<0,L42<0,M42<0,N42<0),"Les 2 taux ci-dessus (IS et Divid.) doivent être >0; ceux qui sont <0 seront convertis en ''0'' pour les calculs, sauf à procéder comme indiqué en cellule R67/68 >>>","") | O43: Elémts de haut-de-bil. : | Q43: =B43 -> (en KF) | R43: =IF(E43="",""," a) Si vous souhaitez de l' IS malgré des pertes, vous pouvez considérer celui-ci comme une ''Charge hors exploitation ''cash'' '' à saisir dans cette Feuille, sur la ligne 91.")
A44: Investissement industriel | E44: =PrSept!E218 -> 61434.208 | F44: =PrSept!F218 -> 12147.064 | G44: =PrSept!G218 -> 26556.55 | O44: Invest. industr. (hors pduct° immobilisée) | R44: =IF(E43="",""," b) Si vous souhaitez des dividendes malgré des pertes, vous pouvez directement saisir ceux-ci à partir de l'année ''H'' dans le Tableau de Flux de ''PrSept'' en écrasant les formules.")
A45: Nouveaux Emprunts à LMT | E45: =IF(PrSept!E233+PrSept!E234<0,"n/d ",PrSept!E233+PrSept!E234) -> 30259.744 | F45: =IF(PrSept!F233+PrSept!F234<0,"n/d ",PrSept!F233+PrSept!F234) -> n/d | G45: =IF(PrSept!G233+PrSept!G234<0,"n/d ",PrSept!G233+PrSept!G234) -> 1043.006 | O45: Nouveaux Emprunts à LMT
A46: Remboursement de DLMT | E46: =PrSept!E234 -> 0 | F46: =PrSept!F234 -> 0 | G46: =PrSept!G234 -> 0 | O46: Remboursement de DLMT
A47: Nouveau Crédit-bail | E47: =IF(PrSept!E90-Etatsfin!J35+PrSept!E150<0,"n/d ",PrSept!E90-Etatsfin!J35+PrSept!E150) -> 0 | F47: =IF(PrSept!F90-PrSept!E90+PrSept!F150<0,"n/d ",PrSept!F90-PrSept!E90+PrSept!F150) -> 18853.378 | G47: =IF(PrSept!G90-PrSept!F90+PrSept!G150<0,"n/d ",PrSept!G90-PrSept!F90+PrSept!G150) -> n/d | O47: Nouveau Crédit-bail
A48: Annuités de crédit-bail | E48: =PrSept!E150 -> 0 | F48: =PrSept!F150 -> 2220.157 | G48: =PrSept!G150 -> 0 | O48: Annuités de crédit-bail
A49: Eléments du BFR : | B49: (en Jours) | O49: Eléments du BFR : (en Jours)
A50: Rotation des stocks (J. de CA) | E50: =PrSept!E12 -> 132.08756 | F50: =PrSept!F12 -> 204.16989 | G50: =PrSept!G12 -> 99.036897 | O50: Rotation des stocks (J. de CA)
A51: Délais clients hors EENE (J. de CA) | E51: =IF(PrSept!E104=0,"n/d ",(PrSept!E45/PrSept!E104)*360*PrSept!R27) -> 28.857895 | F51: =IF(PrSept!F104=0,"n/d ",(PrSept!F45/PrSept!F104)*360*PrSept!S27) -> 50.463787 | G51: =IF(PrSept!G104=0,"n/d ",(PrSept!G45/PrSept!G104)*360*PrSept!T27) -> 85.468937 | O51: Délais clients hors EENE (J. de CA)
A52: Autres créances (exprimées en J. de CA) | E52: =IF(PrSept!E104=0,"n/d ",(PrSept!E46/PrSept!E104)*360*PrSept!R27) -> 21.053007 | F52: =IF(PrSept!F104=0,"n/d ",(PrSept!F46/PrSept!F104)*360*PrSept!S27) -> 25.761974 | G52: =IF(PrSept!G104=0,"n/d ",(PrSept!G46/PrSept!G104)*360*PrSept!T27) -> 17.405104 | O52: Autres créances (exprimées en J. de CA)
A53: Crédit Fournisseurs (exprimé en J. d' Achats) | E53: =PrSept!E14 -> 116.30174 | F53: =PrSept!F14 -> 66.185619 | G53: =PrSept!G14 -> 86.517676 | O53: Crédit Fournisseurs (exprimé en J. d' Achats)
A54: Avances et acomptes reçus (exprimés en J. de CA) | E54: =IF(PrSept!E104=0,"n/d ",(PrSept!E76/PrSept!E104)*360*PrSept!R27) -> 0.14883156 | F54: =IF(PrSept!F104=0,"n/d ",(PrSept!F76/PrSept!F104)*360*PrSept!S27) -> 0 | G54: =IF(PrSept!G104=0,"n/d ",(PrSept!G76/PrSept!G104)*360*PrSept!T27) -> 0 | O54: Avances et acomptes reçus (exprimés en J. de CA)
A55: Autres dettes (hors Prov.et Divid.) (exprimées en J. de CA) | E55: =IF(PrSept!E104=0,"n/d ",((PrSept!E78-PrSept!E79)/PrSept!E104)*360*PrSept!R27) -> 8.1526451 | F55: =IF(PrSept!F104=0,"n/d ",((PrSept!F78-PrSept!F79)/PrSept!F104)*360*PrSept!S27) -> 98.813894 | G55: =IF(PrSept!G104=0,"n/d ",((PrSept!G78-PrSept!G79)/PrSept!G104)*360*PrSept!T27) -> 9.7066689 | O55: Autres dettes (hors Prov.et Divid.) (exprimées en J. de CA)
A56: Eléments spécifiques / exceptionnels : | B56: =CONCATENATE("(en ",PrSept!O21,")") -> (en KF) | O56: Eléments spécif. / exceptionnels : | R56: =B56 -> (en KF)
A57: Augmentation de capital (au sens large) | E57: =PrSept!E257 -> 1500.0766 | F57: =PrSept!F257 -> -25.00271 | G57: =PrSept!G257 -> 2463.141 | O57: Augmentation de capital (au sens large)
A58: Investissements financiers (Goodwill, Stés appar., Immo. fin.) | E58: =PrSept!E224 -> -0.00035 | F58: =PrSept!F224 -> -47277.543 | G58: =PrSept!G224 -> #REF! | O58: Investissements financiers (Goodwill, Stés appar., Immo. fin.)
A59: Prix de cession des actifs (Immo.d'expl. et Titres) | E59: =PrSept!E232 -> 0 | F59: =PrSept!F232 -> 0 | G59: =PrSept!G232 -> 0 | O59: Prix de cession des actifs (Immo.d'expl. et Titres)
A60: Valeur brute comptable des immo. d'exploitation cédées | E60: A saisir à titre d'info pour l'historique | O60: Valeur brute comptable des immo. d'exploitation cédées
A61: Valeur nette comptable des immo. d'exploitation cédées | E61: =E44-(PrSept!E32-Etatsfin!D14)-PrSept!E143+PrSept!E113 -> 3.6379788e-12 | F61: =F44-(PrSept!F32-PrSept!E32)-PrSept!F143+PrSept!F113 -> 23322.944 | G61: =G44-(PrSept!G32-PrSept!F32)-PrSept!G143+PrSept!G113 -> 53131.535 | O61: Valeur nette comptable des immo. d'exploitation cédées
A62: Valeur nette comptable des titres cédés | E62: A saisir le cas échéant | O62: Valeur nette comptable des titres cédés
A63: Dotat° nette aux prov. risques et charges non stables | E63: =PrSept!E156 -> -0.018 | F63: =PrSept!F156 -> -0.09029888 | G63: =PrSept!G156 -> 844.242 | O63: Dotat° nette aux prov. risques et charges non stables
A64: Dotat° nette aux prov. risques et charges stables | E64: =PrSept!E157 -> 0 | F64: =PrSept!F157 -> 0 | G64: =PrSept!G157 -> 0 | O64: Dotat° nette aux prov. risques et charges stables
A65: Dotation aux amortissements du Goodwill (Survaleur) | E65: =Saisie!F180 -> 0 | F65: =Saisie!G180 -> 0 | G65: =Saisie!H180 -> 0 | O65: Dotation aux amortissements du Goodwill (survaleur)
A66: Participation des salariés | E66: =PrSept!E160 -> 0 | F66: =PrSept!F160 -> 0 | G66: =PrSept!G160 -> 0 | O66: Participation des salariés
A67: Autres produits ( - charges) "cash" hors exploitation | E67: =PrSept!E161 -> 5896.4235 | F67: =PrSept!F161 -> -11395.679 | G67: =PrSept!G161 -> 2776.954 | O67: Autres produits ( - charges) "cash" hors exploitation
A68: Acomptes sur dividend. versés éventuellemnt l'année "G" | G68: =Saisie!H79-Saisie!H110 -> 0 | O68: Acomptes sur dividend. versés éventuellement l'année "G"
A69: Effets escomptés non échus (exprimés en J. de CA) | E69: =IF(PrSept!E104=0,"n/d ",(PrSept!E89/PrSept!E104)*360*PrSept!R27) -> 0 | F69: =IF(PrSept!F104=0,"n/d ",(PrSept!F89/PrSept!F104)*360*PrSept!S27) -> 0 | G69: =IF(PrSept!G104=0,"n/d ",(PrSept!G89/PrSept!G104)*360*PrSept!T27) -> 0 | O69: Effets escomptés non échus (exprimés en J. de CA)
A70: VMP & Disponible (Pour les années de Prévisions, il s'agit du niveau minimum souhaité) | E70: =PrSept!E47 -> 126419.96 | F70: =PrSept!F47 -> 22728.054 | G70: =PrSept!G47 -> 104619.7 | O70: VMP & Disponible (Pour les années de Prévisions, il s'agit du niveau minimum souhaité)
N71: PAGE 1/1
A73: NB : Pour chaque année de Prévision, en ce qui concerne les "VMP & Disponible" :
A75: a) soit le niveau minimum de "VMP & Disponible" ci-dessus a été saisi pour "0", et :
A76: (i) le programme affectera automatiquement les liquidités éventuellement dégagées pendant l'année au
A77: remboursement des "Concours bancaires de trésorerie" à due concurrence,
A78: ou bien (ii) le programme compensera automatiquement l'insuffisance de liquidités éventuellement constatée
A79: pendant l'année par une augmentation des "Concours bancaires de trésorerie" à due concurrence.
A81: b) soit ce niveau minimum de "VMP & Disponible" ci-dessus a été laissé intact (par rapport aux
A82: moyennes proposées) ou bien saisi pour un montant non nul, et :
A83: ... le programme raisonnera comme ci-dessus en a), mais respectera ce "volume d'encaisse minima" fixé par
A84: l'utilisateur (le programme ira par exemple automatiquement augmenter les "Concours bancaires de trésorerie"
A85: pour constituer ou compléter ce volume d'encaisse).
A87: Dans tous les cas ci-dessus, le programme tient compte automatiquement des Frais financiers
... A90: considérée).

Sheet PrSept
A1: Reprise de données pour les Feuilles "Résumé", "PrCinq" et "Dette" (ne pas modifier) : Ne pas non plus ajouter de lignes dans, ou avant, ce bloc gris. | H1: =H26 -> 40909 | I1: =I26 -> 41275 | J1: =J26 -> 41641 | K1: =K26 -> 42007 | L1: =L26 -> 42373 | M1: =M26 -> 42739 | N1: =N26 -> 43105 | O1: Reprise de données pour la Feuille de Résumé (ne pas modifier) : Ne pas non plus ajouter de lignes dans ou avant ce bloc gris.
A2: Scénario : | B2: CA : | H2: =H104 -> 1616204.7 | I2: =I104 -> 1616204.7 | J2: =J104 -> 1616204.7 | K2: =K104 -> 1616204.7 | L2: =L104 -> 1616204.7 | M2: =M104 -> 1616204.7 | N2: =N104 -> 1616204.7 | P2: CA :
A3: =M20 -> A saisir sur Hypo | B3: EBE : | H3: =H135 -> 0 | I3: =I135 -> 0 | J3: =J135 -> 0 | K3: =K135 -> 0 | L3: =L135 -> 0 | M3: =M135 -> 0 | N3: =N135 -> 0 | P3: EBE :
B4: Dettes financières totales : | H4: =H287 -> 131773.39 | I4: =I287 -> 131773.39 | J4: =J287 -> 131773.39 | K4: =K287 -> 131773.39 | L4: =L287 -> 131773.39 | M4: =M287 -> 131773.39 | N4: =N287 -> 131773.39 | P4: Dettes financières totales :
B5: Croissance du CA (%) : | H5: =H105 -> 0 | I5: =I105 -> 0 | J5: =J105 -> 0 | K5: =K105 -> 0 | L5: =L105 -> 0 | M5: =M105 -> 0 | N5: =N105 -> 0 | P5: Croissance du CA (%) :
B6: EBE / CA (%) : | H6: =H272 -> 0 | I6: =I272 -> 0 | J6: =J272 -> 0 | K6: =K272 -> 0 | L6: =L272 -> 0 | M6: =M272 -> 0 | N6: =N272 -> 0 | P6: EBE / CA (%) :
B7: EBE / Résultat financier retraité (%) : | H7: =H281 -> n/d | I7: =I281 -> n/d | J7: =J281 -> n/d | K7: =K281 -> n/d | L7: =L281 -> n/d | M7: =M281 -> n/d | N7: =N281 -> n/d | P7: EBE / Résultat financier retraité (%) :
B8: Dettes financières totales / EBE (années) : | H8: =H293 -> n/d | I8: =I293 -> n/d | J8: =J293 -> n/d | K8: =K293 -> n/d | L8: =L293 -> n/d | M8: =M293 -> n/d | N8: =N293 -> n/d | P8: Dettes financières totales / EBE (années) :
B9: Dettes financières totales CFEN (années) : | H9: =H295 -> 0.24794585 | I9: =I295 -> n/d | J9: =J295 -> n/d | K9: =K295 -> n/d | L9: =L295 -> n/d | M9: =M295 -> n/d | N9: =N295 -> n/d | P9: Dettes financières totales CFEN (années) :
B10: Investissement industriel : | H10: =H218 -> 0 | I10: =I218 -> 0 | J10: =J218 -> 0 | K10: =K218 -> 0 | L10: =L218 -> 0 | M10: =M218 -> 0 | N10: =N218 -> 0 | P10: Investissement industriel :
E11: =E26 -> 39783 | F11: =F26 -> 40178 | G11: =G26 -> 40543
B12: Rotation des stocks (J. de CA) : | E12: =IF(E104=0,"n/d ",(E44/E104)*360*R27) -> 132.08756 | F12: =IF(F104=0,"n/d ",(F44/F104)*360*S27) -> 204.16989 | G12: =IF(G104=0,"n/d ",(G44/G104)*360*T27) -> 99.036897 | H12: =Hypo!H50 -> 0 | I12: =Hypo!I50 -> 0 | J12: =Hypo!J50 -> 0 | K12: =Hypo!K50 -> 0 | L12: =Hypo!L50 -> 0 | M12: =Hypo!M50 -> 0 | N12: =Hypo!N50 -> 0 | P12: Rotation des stocks (J. de CA) :
B13: Délais clients (J. de C.A.) : | E13: =IF(E104=0,"n/d ",((E45+E89)/E104)*360*R27) -> 28.857895 | F13: =IF(F104=0,"n/d ",((F45+F89)/F104)*360*S27) -> 50.463787 | G13: =IF(G104=0,"n/d ",((G45+G89)/G104)*360*T27) -> 85.468937 | H13: =Hypo!H51+Hypo!H69 -> 0 | I13: =Hypo!I51+Hypo!I69 -> 0 | J13: =Hypo!J51+Hypo!J69 -> 0 | K13: =Hypo!K51+Hypo!K69 -> 0 | L13: =Hypo!L51+Hypo!L69 -> 0 | M13: =Hypo!M51+Hypo!M69 -> 0 | N13: =Hypo!N51+Hypo!N69 -> 0 | P13: Délais clients (J. de C.A.) :
B14: Crédit fournisseurs (J. d'achats) : | E14: =IF(E115=0,"n/d ",(E77/E115)*360*R27) -> 116.30174 | F14: =IF(F115=0,"n/d ",(F77/F115)*360*S27) -> 66.185619 | G14: =IF(G115=0,"n/d ",(G77/G115)*360*T27) -> 86.517676 | H14: =Hypo!H53 -> 0 | I14: =Hypo!I53 -> 0 | J14: =Hypo!J53 -> 0 | K14: =Hypo!K53 -> 0 | L14: =Hypo!L53 -> 0 | M14: =Hypo!M53 -> 0 | N14: =Hypo!N53 -> 0 | P14: Crédit fournisseurs (J. d'achats) :
B15: Idem ligne ci-dessous, mais info venant de ''Hypo'' : | E15: =Hypo!E39 -> 0.031355583 | F15: =Hypo!F39 -> 0.068560631 | G15: =Hypo!G39 -> 0.13383155 | H15: (Ces reprises permettent de tenir compte d'un écrasement éventuel des cellules E/F/G 63 dans ''Hypo'') | P15: Idem ligne ci-dessous, mais info venant de ''Hypo'' :
B16: Frais fi. / Dette fi. tot. moyenne de l'année (hors cdt-bail) : | E16: =IF(OR((Etatsfin!J17+Etatsfin!J29+Etatsfin!J34)+(E62+E80+E89)=0,R27=0,Etatsfin!D31=0,Etatsfin!J31=0),"n/d ",(E149/R27)/((Etatsfin!J17+Etatsfin!J29+Etatsfin!J34+E62+E80+E89)/2)) -> 0.031355583 | F16: =IF(OR((E62+E80+E89)+(F62+F80+F89)=0,S27=0,E49=0,E82=0),"n/d ",(F149/S27)/((E62+E80+E89+F62+F80+F89)/2)) -> 0.068560631 | G16: =IF(OR((F62+F80+F89)+(G62+G80+G89)=0,T27=0,F49=0,F82=0),"n/d ",(G149/T27)/((F62+F80+F89+G62+G80+G89)/2)) -> 0.13383155 | H16: =Hypo!H39 -> 0 | I16: =Hypo!I39 -> 0 | J16: =Hypo!J39 -> 0 | K16: =Hypo!K39 -> 0 | L16: =Hypo!L39 -> 0 | M16: =Hypo!M39 -> 0 | N16: =Hypo!N39 -> 0 | P16: Frais fi. / Dette fi. tot. moy. de l'année (hors cdt-bail) :
B17: Taux d'IS (= IS / Résultat avant IS) : | E17: =IF(OR(E165+E163=0,E165<=0,E163<=0),"n/d ",E163/(E165+E163)) -> 0.24999982 | F17: =IF(OR(F165+F163=0,F165<=0,F163<=0),"n/d ",F163/(F165+F163)) -> 0.24512003 | G17: =IF(OR(G165+G163=0,G165<=0,G163<=0),"n/d ",G163/(G165+G163)) -> 0.20112084 | H17: =IF(Hypo!H41<0,0,Hypo!H41) -> 0 | I17: =IF(Hypo!I41<0,0,Hypo!I41) -> 0 | J17: =IF(Hypo!J41<0,0,Hypo!J41) -> 0 | K17: =IF(Hypo!K41<0,0,Hypo!K41) -> 0 | L17: =IF(Hypo!L41<0,0,Hypo!L41) -> 0 | M17: =IF(Hypo!M41<0,0,Hypo!M41) -> 0 | N17: =IF(Hypo!N41<0,0,Hypo!N41) -> 0 | P17: Taux d'IS (= IS / Résultat avant IS) :
L18: Date: | M18: =TODAY() -> 46304
A19: Société : | B19: =Etatsfin!D2 -> MERIPLAST
A20: Groupe : | B20: =+B19 -> MERIPLAST | L20: Scénario : | M20: =IF(OR(Hypo!M25="",Hypo!M25="A saisir ici"),"A saisir sur Hypo",Hypo!M25) -> A saisir sur Hypo | O20: Zone réservée.
A21: Unité de compte : | B21: KF | O21: =IF(OR(B21="",B21="Saisir sur Saisie ou Etatsfin")," montant",B21) -> KF | P21: =IF(OR(B21="",B21="Saisir sur Saisie ou Etatsfin"),"Saisir sur Saisie ou Etatsfin ou PrSept",B21) -> KF
F22: =IF(OR(G26=0,G26=""),"Date d'arrêté à saisir ci-dessous en ''G'' dans la cellule réservée à la date.","") | O22: =Hypo!L3 -> 1 | P22: =Hypo!M3 -> 0
A23: =IF(OR(G26=0,G26=""),"(Il est par ailleurs possible, comme dans ''Saisie'' ou ''Etatsfin'', d'écraser les dates des 2 premières années d'historique.)","")
G24: =IF(OR(O24<=0,O24=""),"Saisir durée, en jours, du 1er exercice historique, dans la cellule ''O'' de cette ligne, à droite >>>","") | O24: =Etatsfin!E5-Etatsfin!D5 -> 366
E25: Historique | H25: Prévisions
A26: Bilan : | E26: =IF(Etatsfin!E5=0,F26-365,Etatsfin!E5) -> 39783 | F26: =IF(Etatsfin!F5=0,G26-365,Etatsfin!F5) -> 40178 | G26: =IF(Etatsfin!G5=0,0,Etatsfin!G5) -> 40543 | H26: =G26+366 -> 40909 | I26: =H26+366 -> 41275 | J26: =I26+366 -> 41641 | K26: =J26+366 -> 42007 | L26: =K26+366 -> 42373 | M26: =L26+366 -> 42739 | N26: =M26+366 -> 43105 | O26: Bilan : | R26: Zone réservée (durée des exercices).
A27: Changement format dates pour graphiques | E27: =E26 -> 39783 | F27: =F26 -> 40178 | G27: =G26 -> 40543 | H27: =H26 -> 40909 | I27: =I26 -> 41275 | J27: =J26 -> 41641 | K27: =K26 -> 42007 | L27: =L26 -> 42373 | ... N27: =N26 -> 43105 | R27: =O24/365 -> 1.0027397 | S27: =(F26-E26)/365 -> 1.0821918 | T27: =(G26-F26)/365 -> 1
A28: Actifs immobilisés (nets) | E28: =E32+E35 -> 157693.05 | F28: =F32+F35 -> 101683.48 | G28: =G32+G35 -> 97497.075 | H28: =H32+H35 -> 97497.075 | I28: =I32+I35 -> 97497.075 | J28: =J32+J35 -> 97497.075 | K28: =K32+K35 -> 97497.075 | L28: =L32+L35 -> 97497.075 | ... N28: =N32+N35 -> 97497.075 | O28: Actifs immobilisés (nets)
A29: Immobilisations d'exploitation brutes | E29: =Etatsfin!E10 -> 149520.27 | F29: =Etatsfin!F10 -> 161675.93 | G29: =Etatsfin!G10 -> 187435.8 | H29: =G29+Hypo!H44-Hypo!H60+H113 -> 187435.8 | I29: =H29+Hypo!I44-Hypo!I60+I113 -> 187435.8 | J29: =I29+Hypo!J44-Hypo!J60+J113 -> 187435.8 | K29: =J29+Hypo!K44-Hypo!K60+K113 -> 187435.8 | L29: =K29+Hypo!L44-Hypo!L60+L113 -> 187435.8 | M29: =L29+Hypo!M44-Hypo!M60+M113 -> 187435.8 | N29: =M29+Hypo!N44-Hypo!N60+N113 -> 187435.8 | O29: Immobilisations d'exploitation brutes
A30: - Amortissements et Provisions | E30: =Etatsfin!E11 -> 43340.142 | F30: =Etatsfin!F11 -> 64227.836 | G30: =Etatsfin!G11 -> 91785.724 | H30: =G30+H143-(Hypo!H60-Hypo!H61) -> 91785.724 | I30: =H30+I143-(Hypo!I60-Hypo!I61) -> 91785.724 | J30: =I30+J143-(Hypo!J60-Hypo!J61) -> 91785.724 | K30: =J30+K143-(Hypo!K60-Hypo!K61) -> 91785.724 | L30: =K30+L143-(Hypo!L60-Hypo!L61) -> 91785.724 | M30: =L30+M143-(Hypo!M60-Hypo!M61) -> 91785.724 | N30: =M30+N143-(Hypo!N60-Hypo!N61) -> 91785.724 | O30: - Amortissements et Provisions
A32: = Immobilisations d'exploitation nettes | E32: =E29-E30 -> 106180.13 | F32: =F29-F30 -> 97448.094 | G32: =G29-G30 -> 95650.075 | H32: =H29-H30 -> 95650.075 | I32: =I29-I30 -> 95650.075 | J32: =J29-J30 -> 95650.075 | K32: =K29-K30 -> 95650.075 | L32: =L29-L30 -> 95650.075 | ... N32: =N29-N30 -> 95650.075 | O32: = Immobilisations d'exploitation nettes
A33: (dont immobilisations d'expl. incorporelles nettes) | E33: =Etatsfin!E15 -> 41.25 | F33: =Etatsfin!F15 -> 14.534 | G33: =Etatsfin!G15 -> 419.167 | O33: (dont immobilisations d'expl. incorporelles nettes)
A35: Immobilisat. hors expl. nettes (Goodw./Stés appar./Immo. fin.) | E35: =SUM(Etatsfin!E17:E19) -> 51512.928 | F35: =SUM(Etatsfin!F17:F19) -> 4235.385 | G35: =SUM(Etatsfin!G17:G19) -> 1847 | H35: =G35+H224-Hypo!H65-Hypo!H62 -> 1847 | I35: =H35+I224-Hypo!I65-Hypo!I62 -> 1847 | J35: =I35+J224-Hypo!J65-Hypo!J62 -> 1847 | K35: =J35+K224-Hypo!K65-Hypo!K62 -> 1847 | L35: =K35+L224-Hypo!L65-Hypo!L62 -> 1847 | M35: =L35+M224-Hypo!M65-Hypo!M62 -> 1847 | N35: =M35+N224-Hypo!N65-Hypo!N62 -> 1847 | O35: Immobilisat. hors expl. nettes (Goodw./Stés appar./Immo. fin.)
A36: =IF(AND(P22=1,Saisie!F120=0,Saisie!G120=0,Saisie!H120=0,Etatsfin!G19=0,E40=0,E41=0,F40=0,F41=0,G40=0,G41=0),"Décomposition historique des ''Titres'' et ''Autres immo. financières'' à saisir car ''Saisie'' semble incomplète... ","") -> #REF!
A37: Détail de 100% des Immobilisations hors exploitat° nettes | E37: =IF(O22=1,"",IF(AND((E35-SUM(E38:E41))>=-0.1,(E35-SUM(E38:E41)<=0.1)),"","Erreur !")) | F37: =IF(O22=1,"",IF(AND((F35-SUM(F38:F41))>=-0.1,(F35-SUM(F38:F41)<=0.1)),"","Erreur !")) | G37: =IF(O22=1,"",IF(AND((G35-SUM(G38:G41))>=-0.1,(G35-SUM(G38:G41)<=0.1)),"","Erreur !")) | O37: Détail de 100% des Immobilisations hors exploitat° nettes
A38: Survaleur/ Goodwill | E38: =Etatsfin!E17 -> 0 | F38: =Etatsfin!F17 -> 0 | G38: =Etatsfin!G17 -> 0 | H38: =G38+H227-Hypo!H65 -> 0 | I38: =H38+I227-Hypo!I65 -> 0 | J38: =I38+J227-Hypo!J65 -> 0 | K38: =J38+K227-Hypo!K65 -> 0 | L38: =K38+L227-Hypo!L65 -> 0 | M38: =L38+M227-Hypo!M65 -> 0 | N38: =M38+N227-Hypo!N65 -> 0 | O38: Survaleur/ Goodwill
A39: Sociétés apparentées | E39: =Etatsfin!E19 -> 0 | F39: =Etatsfin!F19 -> 421.393 | G39: =Etatsfin!G19 -> 0 | H39: =G39+H228 -> 0 | I39: =H39+I228 -> 0 | J39: =I39+J228 -> 0 | K39: =J39+K228 -> 0 | L39: =K39+L228 -> 0 | M39: =L39+M228 -> 0 | N39: =M39+N228 -> 0 | O39: Sociétés apparentées
A40: Titres (de stés non consolidées en intégration globale) | E40: =SUM(Saisie!F21:'Saisie'!F24)-SUM(Saisie!F27:'Saisie'!F30) -> 0 | F40: =SUM(Saisie!G21:'Saisie'!G24)-SUM(Saisie!G27:'Saisie'!G30) -> 0 | G40: =SUM(Saisie!H21:'Saisie'!H25)-SUM(Saisie!H27:'Saisie'!H30) -> 1847 | H40: =G40+H229-Hypo!H62 -> 1847 | I40: =H40+I229-Hypo!I62 -> 1847 | J40: =I40+J229-Hypo!J62 -> 1847 | K40: =J40+K229-Hypo!K62 -> 1847 | L40: =K40+L229-Hypo!L62 -> 1847 | M40: =L40+M229-Hypo!M62 -> 1847 | N40: =M40+N229-Hypo!N62 -> 1847 | O40: Titres (de stés non consolidées en intégration globale)
A41: Autres Immo. Financières | E41: =(Saisie!F25+Saisie!F26)-(Saisie!F31+Saisie!F32) -> 51512.928 | F41: =(Saisie!G25+Saisie!G26)-(Saisie!G31+Saisie!G32) -> 3813.992 | G41: =(Saisie!#REF!+Saisie!H26)-(Saisie!H31+Saisie!H32) -> #REF! | H41: =G41+H230 -> #REF! | I41: =H41+I230 -> #REF! | J41: =I41+J230 -> #REF! | K41: =J41+K230 -> #REF! | L41: =K41+L230 -> #REF! | M41: =L41+M230 -> #REF! | N41: =M41+N230 -> #REF! | O41: Autres Immo. Financières
A42: =IF(AND(P22=1,T226>4),"Vous avez décidé d'ajouter une(des) ligne(s) au bloc ci-dessus : il faut donc en outre, pour cette(ces) nouvelle(s) ligne(s), ''copier & coller'' les formules ad hoc à partir d'une ligne similaire de ce bloc.","")
A43: Actifs circulants (nets) | E43: =SUM(E44:E47) -> 488397.22 | F43: =SUM(F44:F47) -> 676088.32 | G43: =SUM(G44:G47) -> 1011090.3 | H43: =SUM(H44:H47) -> 184164.62 | I43: =SUM(I44:I47) -> 184164.62 | J43: =SUM(J44:J47) -> 184164.62 | K43: =SUM(K44:K47) -> 184164.62 | L43: =SUM(L44:L47) -> 184164.62 | ... N43: =SUM(N44:N47) -> 184164.62 | O43: Actifs circulants (nets)
A44: Stocks | E44: =Etatsfin!E23 -> 262709.32 | F44: =Etatsfin!F23 -> 475743.81 | G44: =Etatsfin!G23 -> 444621.94 | H44: =Hypo!H50*H104/360 -> 0 | I44: =Hypo!I50*I104/360 -> 0 | J44: =Hypo!J50*J104/360 -> 0 | K44: =Hypo!K50*K104/360 -> 0 | L44: =Hypo!L50*L104/360 -> 0 | M44: =Hypo!M50*M104/360 -> 0 | N44: =Hypo!N50*N104/360 -> 0 | O44: Stocks
A45: Clients | E45: =Etatsfin!E25 -> 57395.55 | F45: =Etatsfin!F25 -> 117587.54 | G45: =Etatsfin!G25 -> 383709.16 | H45: =Hypo!H51*H104/360 -> 0 | I45: =Hypo!I51*I104/360 -> 0 | J45: =Hypo!J51*J104/360 -> 0 | K45: =Hypo!K51*K104/360 -> 0 | L45: =Hypo!L51*L104/360 -> 0 | M45: =Hypo!M51*M104/360 -> 0 | N45: =Hypo!N51*N104/360 -> 0 | O45: Clients
A46: Autres créances | E46: =Etatsfin!E26 -> 41872.384 | F46: =Etatsfin!F26 -> 60028.927 | G46: =Etatsfin!G26 -> 78139.476 | H46: =Hypo!H52*H104/360 -> 0 | I46: =Hypo!I52*I104/360 -> 0 | J46: =Hypo!J52*J104/360 -> 0 | K46: =Hypo!K52*K104/360 -> 0 | L46: =Hypo!L52*L104/360 -> 0 | M46: =Hypo!M52*M104/360 -> 0 | N46: =Hypo!N52*N104/360 -> 0 | O46: Autres créances
A47: VMP et Disponible | E47: =Etatsfin!E27+Etatsfin!E28 -> 126419.96 | F47: =Etatsfin!F27+Etatsfin!F28 -> 22728.054 | G47: =Etatsfin!G27+Etatsfin!G28 -> 104619.7 | H47: =IF(H97>=Hypo!H70,H97,Hypo!H70) -> 184164.62 | I47: =IF(I97>=Hypo!I70,I97,Hypo!I70) -> 184164.62 | J47: =IF(J97>=Hypo!J70,J97,Hypo!J70) -> 184164.62 | K47: =IF(K97>=Hypo!K70,K97,Hypo!K70) -> 184164.62 | L47: =IF(L97>=Hypo!L70,L97,Hypo!L70) -> 184164.62 | M47: =IF(M97>=Hypo!M70,M97,Hypo!M70) -> 184164.62 | N47: =IF(N97>=Hypo!N70,N97,Hypo!N70) -> 184164.62 | O47: VMP et Disponible
A49: Total Actif | E49: =E28+E43 -> 646090.27 | F49: =F28+F43 -> 777771.8 | G49: =G28+G43 -> 1108587.3 | H49: =H28+H43 -> 281661.7 | I49: =I28+I43 -> 281661.7 | J49: =J28+J43 -> 281661.7 | K49: =K28+K43 -> 281661.7 | L49: =L28+L43 -> 281661.7 | ... N49: =N28+N43 -> 281661.7 | O49: Total Actif
E52: =E25 -> Historique | H52: =H25 -> Prévisions
E53: =E26 -> 39783 | F53: =F26 -> 40178 | G53: =G26 -> 40543 | H53: =H26 -> 40909 | I53: =I26 -> 41275 | J53: =J26 -> 41641 | K53: =K26 -> 42007 | L53: =L26 -> 42373 | ... N53: =N26 -> 43105
A55: Fonds propres | E55: =SUM(E56:E58) -> 105471.02 | F55: =SUM(F56:F58) -> 126814.25 | G55: =SUM(G56:G58) -> 157044.05 | H55: =SUM(H56:H58) -> 157044.05 | I55: =SUM(I56:I58) -> 157044.05 | J55: =SUM(J56:J58) -> 157044.05 | K55: =SUM(K56:K58) -> 157044.05 | L55: =SUM(L56:L58) -> 157044.05 | ... N55: =SUM(N56:N58) -> 157044.05 | O55: Fonds propres
A56: Capital + Réserves | E56: =Etatsfin!K10+Etatsfin!K11 -> 87088.007 | F56: =Etatsfin!L10+Etatsfin!L11 -> 105446.01 | G56: =Etatsfin!M10+Etatsfin!M11 -> 129277.39 | H56: =G56+G57+Hypo!H57 -> 157044.05 | I56: =H56+H57+Hypo!I57 -> 157044.05 | J56: =I56+I57+Hypo!J57 -> 157044.05 | K56: =J56+J57+Hypo!K57 -> 157044.05 | L56: =K56+K57+Hypo!L57 -> 157044.05 | M56: =L56+L57+Hypo!M57 -> 157044.05 | N56: =M56+M57+Hypo!N57 -> 157044.05 | O56: Capital + Réserves
A57: Bénéfice après dividendes | E57: =Etatsfin!K12 -> 18383.009 | F57: =Etatsfin!L12 -> 21368.238 | G57: =Etatsfin!M12 -> 27766.661 | H57: =H165-I256 -> 0 | I57: =I165-J256 -> 0 | J57: =J165-K256 -> 0 | K57: =K165-L256 -> 0 | L57: =L165-M256 -> 0 | M57: =M165-N256 -> 0 | N57: =N165-R256 -> 0 | O57: Bénéfice après dividendes
A58: Intérêts minoritaires | E58: =Etatsfin!K13 -> 0 | F58: =Etatsfin!L13 -> 0 | G58: =Etatsfin!M13 -> 0 | H58: =G58 -> 0 | I58: =H58 -> 0 | J58: =I58 -> 0 | K58: =J58 -> 0 | L58: =K58 -> 0 | M58: =L58 -> 0 | N58: =M58 -> 0 | O58: Intérêts minoritaires
A60: Provisions risques et charges stables | E60: =Etatsfin!K15 -> 0 | F60: =Etatsfin!L15 -> 0 | G60: =Etatsfin!M15 -> 0 | H60: =G60+H157 -> 0 | I60: =H60+I157 -> 0 | J60: =I60+J157 -> 0 | K60: =J60+K157 -> 0 | L60: =K60+L157 -> 0 | M60: =L60+M157 -> 0 | N60: =M60+N157 -> 0 | O60: Provisions risques et charges stables
A62: Dettes à long / moyen terme | E62: =Etatsfin!K17 -> 129227.14 | F62: =Etatsfin!L17 -> 122730.39 | G62: =Etatsfin!M17 -> 123773.39 | H62: =G62+H233 -> 123773.39 | I62: =H62+I233 -> 123773.39 | J62: =I62+J233 -> 123773.39 | K62: =J62+K233 -> 123773.39 | L62: =K62+L233 -> 123773.39 | M62: =L62+M233 -> 123773.39 | N62: =M62+N233 -> 123773.39 | O62: Dettes à long / moyen terme
B63: =IF(AND(T238=4,T244=4,T250=3),"","Vous avez ajouté (supprimé) une(des) ligne(s) de mouvements de DLMT dans le Tableau de Flux; donc il faut en ajouter (supprimer) autant ci-dessous, en respectant l'ordre.")
A64: Détail de tout ou partie des DLMT | B64: =IF(OR(T238>4,T244>4,T250>3),"En fait, vous avez ajouté une(des) ligne(s) : il faut donc en outre ''copier & coller'' les formules à partir de la ligne supérieure ou infér. déjà existante.","") | O64: Détail de tout ou partie des DLMT
A65: Nouvelles Dettes à LMT :
A66: =IF(OR(A239="Saisir un nom",A239=""),"Nom à saisir dans le Tableau de Flux",A239) -> Saisir un nom ex Dette 1 | H66: =H239-H245 -> 0 | I66: =H66+I239-I245 -> 0 | J66: =I66+J239-J245 -> 0 | K66: =J66+K239-K245 -> 0 | L66: =K66+L239-L245 -> 0 | M66: =L66+M239-M245 -> 0 | N66: =M66+N239-N245 -> 0 | O66: =A66 -> Saisir un nom ex Dette 1
A67: =IF(OR(A240="Saisir un nom",A240=""),"Nom à saisir dans le Tableau de Flux",A240) -> Saisir un nom ex Dette 2 | F67: Zone vide | H67: =H240-H246 -> 0 | I67: =H67+I240-I246 -> 0 | J67: =I67+J240-J246 -> 0 | K67: =J67+K240-K246 -> 0 | L67: =K67+L240-L246 -> 0 | M67: =L67+M240-M246 -> 0 | N67: =M67+N240-N246 -> 0 | O67: =A67 -> Saisir un nom ex Dette 2
A68: =IF(OR(A241="Saisir un nom",A241=""),"Nom à saisir dans le Tableau de Flux",A241) -> Saisir un nom ex Dette 3 | H68: =H241-H247 -> 0 | I68: =H68+I241-I247 -> 0 | J68: =I68+J241-J247 -> 0 | K68: =J68+K241-K247 -> 0 | L68: =K68+L241-L247 -> 0 | M68: =L68+M241-M247 -> 0 | N68: =M68+N241-N247 -> 0 | O68: =A68 -> Saisir un nom ex Dette 3
A69: =IF(OR(A242="Saisir un nom",A242=""),"Nom à saisir dans le Tableau de Flux",A242) -> Saisir un nom ex Dette 4 | H69: =H242-H248 -> 0 | I69: =H69+I242-I248 -> 0 | J69: =I69+J242-J248 -> 0 | K69: =J69+K242-K248 -> 0 | L69: =K69+L242-L248 -> 0 | M69: =L69+M242-M248 -> 0 | N69: =M69+N242-N248 -> 0 | O69: =A69 -> Saisir un nom ex Dette 4
A70: Anciennes Dettes à LMT : | E70: =IF(O22=1,"",IF(AND((E62-SUM(E71:E73))>=-0.1,(E62-SUM(E71:E73)<=0.1)),"","Erreur !")) | F70: =IF(O22=1,"",IF(AND((F62-SUM(F71:F73))>=-0.1,(F62-SUM(F71:F73)<=0.1)),"","Erreur !")) | G70: =IF(O22=1,"",IF(AND((G62-SUM(G71:G73))>=-0.1,(G62-SUM(G71:G73)<=0.1)),"","Saisie erronée !")) | O70: =A70 -> Anciennes Dettes à LMT :
A71: =IF(OR(A251="Saisir un nom",A251=""),"Nom à saisir dans le Tableau de Flux",A251) -> Nom à saisir dans le Tableau de Flux | E71: =F71-F251 -> 0 | F71: =IF(G71="A saisir",0,G71-G251) -> 0 | G71: A saisir | H71: =IF(G71="A saisir",0,G71+H251) -> 0 | I71: =H71+I251 -> 0 | J71: =I71+J251 -> 0 | K71: =J71+K251 -> 0 | L71: =K71+L251 -> 0 | M71: =L71+M251 -> 0 | N71: =M71+N251 -> 0 | O71: =A71 -> Nom à saisir dans le Tableau de Flux
A72: =IF(OR(A252="Saisir un nom",A252=""),"Nom à saisir dans le Tableau de Flux",A252) -> Nom à saisir dans le Tableau de Flux | E72: =F72-F252 -> 0 | F72: =IF(G72="A saisir",0,G72-G252) -> 0 | G72: A saisir | H72: =IF(G72="A saisir",0,G72+H252) -> 0 | I72: =H72+I252 -> 0 | J72: =I72+J252 -> 0 | K72: =J72+K252 -> 0 | L72: =K72+L252 -> 0 | M72: =L72+M252 -> 0 | N72: =M72+N252 -> 0 | O72: =A72 -> Nom à saisir dans le Tableau de Flux
A73: =IF(OR(A253="Saisir un nom",A253=""),"Nom à saisir dans le Tableau de Flux",A253) -> Autres ''anciennes DLMT'' | E73: =F73-F253 -> 0 | F73: =IF(G73="A saisir",0,G73-G253) -> 0 | G73: A saisir | H73: =IF(G73="A saisir",0,G73+H253) -> 0 | I73: =H73+I253 -> 0 | J73: =I73+J253 -> 0 | K73: =J73+K253 -> 0 | L73: =K73+L253 -> 0 | M73: =L73+M253 -> 0 | N73: =M73+N253 -> 0 | O73: =A73 -> Autres ''anciennes DLMT''
A75: Exigibles court terme | E75: =SUM(E76:E78)+E80 -> 411392.11 | F75: =SUM(F76:F78)+F80 -> 528227.16 | G75: =SUM(G76:G78)+G80 -> 827769.89 | H75: =SUM(H76:H78)+H80 -> 844.242 | I75: =SUM(I76:I78)+I80 -> 844.242 | J75: =SUM(J76:J78)+J80 -> 844.242 | K75: =SUM(K76:K78)+K80 -> 844.242 | L75: =SUM(L76:L78)+L80 -> 844.242 | ... N75: =SUM(N76:N78)+N80 -> 844.242 | O75: Exigibles court terme
A76: Avances et acomptes reçus | E76: =Etatsfin!K25 -> 296.0115 | F76: =Etatsfin!L25 -> 0 | G76: =Etatsfin!M25 -> 0 | H76: =Hypo!H54*H104/360 -> 0 | I76: =Hypo!I54*I104/360 -> 0 | J76: =Hypo!J54*J104/360 -> 0 | K76: =Hypo!K54*K104/360 -> 0 | L76: =Hypo!L54*L104/360 -> 0 | M76: =Hypo!M54*M104/360 -> 0 | N76: =Hypo!N54*N104/360 -> 0 | O76: Avances et acomptes reçus
A77: Fournisseurs | E77: =Etatsfin!K26 -> 205984.72 | F77: =Etatsfin!L26 -> 130093.2 | G77: =Etatsfin!M26 -> 331432.5 | H77: =Hypo!H53*H115/360 -> 0 | I77: =Hypo!I53*I115/360 -> 0 | J77: =Hypo!J53*J115/360 -> 0 | K77: =Hypo!K53*K115/360 -> 0 | L77: =Hypo!L53*L115/360 -> 0 | M77: =Hypo!M53*M115/360 -> 0 | N77: =Hypo!N53*N115/360 -> 0 | O77: Fournisseurs
A78: Autres dettes | E78: =Etatsfin!K27 -> 16214.819 | F78: =Etatsfin!L27 -> 230249.91 | G78: =Etatsfin!M27 -> 44421.925 | H78: =(Hypo!H55*H104/360)+H79 -> 844.242 | I78: =(Hypo!I55*I104/360)+I79 -> 844.242 | J78: =(Hypo!J55*J104/360)+J79 -> 844.242 | K78: =(Hypo!K55*K104/360)+K79 -> 844.242 | L78: =(Hypo!L55*L104/360)+L79 -> 844.242 | M78: =(Hypo!M55*M104/360)+M79 -> 844.242 | N78: =(Hypo!N55*N104/360)+N79 -> 844.242 | O78: Autres dettes
A79: <dont provisions et dividendes> | E79: =Etatsfin!K28 -> 0 | F79: =Etatsfin!L28 -> 0 | G79: =Etatsfin!M28 -> 844.248 | H79: =(G79+H156)-H256+I256 -> 844.242 | I79: =(H79+I156)-I256+J256 -> 844.242 | J79: =(I79+J156)-J256+K256 -> 844.242 | K79: =(J79+K156)-K256+L256 -> 844.242 | L79: =(K79+L156)-L256+M256 -> 844.242 | M79: =(L79+M156)-M256+N256 -> 844.242 | N79: =(M79+N156)-N256+R256 -> 844.242 | O79: <dont provisions et dividendes>
A80: Concours bancaires de trésorerie | E80: =Etatsfin!K29 -> 188896.56 | F80: =Etatsfin!L29 -> 167884.05 | G80: =Etatsfin!M29 -> 451915.46 | H80: =IF(H97>=Hypo!H70,H98,H98+H197) -> 0 | I80: =IF(I97>=Hypo!I70,I98,I98+I197) -> 0 | J80: =IF(J97>=Hypo!J70,J98,J98+J197) -> 0 | K80: =IF(K97>=Hypo!K70,K98,K98+K197) -> 0 | L80: =IF(L97>=Hypo!L70,L98,L98+L197) -> 0 | M80: =IF(M97>=Hypo!M70,M98,M98+M197) -> 0 | N80: =IF(N97>=Hypo!N70,N98,N98+N197) -> 0 | O80: Concours bancaires de trésorerie
A82: Total Passif | E82: =E55+E60+E62+E75 -> 646090.27 | F82: =F55+F60+F62+F75 -> 777771.8 | G82: =G55+G60+G62+G75 -> 1108587.3 | H82: =H55+H60+H62+H75 -> 281661.69 | I82: =I55+I60+I62+I75 -> 281661.69 | J82: =J55+J60+J62+J75 -> 281661.69 | K82: =K55+K60+K62+K75 -> 281661.69 | L82: =L55+L60+L62+L75 -> 281661.69 | ... N82: =N55+N60+N62+N75 -> 281661.69 | O82: Total Passif
A85: Besoin en fonds de roulement (net et hors EENE) | E85: =Etatsfin!E36 -> 139481.71 | F85: =Etatsfin!F36 -> 293017.16 | G85: =Etatsfin!G36 -> 531193.91 | H85: =SUM(H44:H46)-SUM(H76:H78)+H79 -> 0 | I85: =SUM(I44:I46)-SUM(I76:I78)+I79 -> 0 | J85: =SUM(J44:J46)-SUM(J76:J78)+J79 -> 0 | K85: =SUM(K44:K46)-SUM(K76:K78)+K79 -> 0 | L85: =SUM(L44:L46)-SUM(L76:L78)+L79 -> 0 | M85: =SUM(M44:M46)-SUM(M76:M78)+M79 -> 0 | N85: =SUM(N44:N46)-SUM(N76:N78)+N79 -> 0 | O85: Besoin en fonds de roulement (net et hors EENE)
A86: =Ratios!A58 -> BFR (Jours de CA) | E86: =IF(E104=0,"n/d ",(E85/E104)*360*R27) -> 70.129975 | F86: =IF(F104=0,"n/d ",(F85/F104)*360*S27) -> 125.75105 | G86: =IF(G104=0,"n/d ",(G85/G104)*360*T27) -> 118.32029 | H86: =H301 -> 0 | I86: =I301 -> 0 | J86: =J301 -> 0 | K86: =K301 -> 0 | L86: =L301 -> 0 | M86: =M301 -> 0 | N86: =N301 -> 0 | O86: =Ratios!A58 -> BFR (Jours de CA)
A88: Hors bilan | O88: Hors bilan
A89: Effets escomptés non échus | E89: =Etatsfin!K34 -> 0 | F89: =Etatsfin!L34 -> 0 | G89: =Etatsfin!M34 -> 0 | H89: =Hypo!H69*H104/360 -> 0 | I89: =Hypo!I69*I104/360 -> 0 | J89: =Hypo!J69*J104/360 -> 0 | K89: =Hypo!K69*K104/360 -> 0 | L89: =Hypo!L69*L104/360 -> 0 | M89: =Hypo!M69*M104/360 -> 0 | N89: =Hypo!N69*N104/360 -> 0 | O89: Effets escomptés non échus
A90: Engagements de crédit-bail | E90: =Etatsfin!K35 -> 0 | F90: =Etatsfin!L35 -> 16633.221 | G90: =Etatsfin!M35 -> 12000 | H90: =G90+Hypo!H47-Hypo!H48 -> 12000 | I90: =H90+Hypo!I47-Hypo!I48 -> 12000 | J90: =I90+Hypo!J47-Hypo!J48 -> 12000 | K90: =J90+Hypo!K47-Hypo!K48 -> 12000 | L90: =K90+Hypo!L47-Hypo!L48 -> 12000 | M90: =L90+Hypo!M47-Hypo!M48 -> 12000 | N90: =M90+Hypo!N47-Hypo!N48 -> 12000 | O90: Engagements de crédit-bail
M92: =NOW() -> 46304.723 | N92: PAGE 1/4
A94: Contrôle Actif =? Passif | E94: =IF(AND(E49=0,E82=0),"n/d",IF(AND((E49-E82)>=-0.1,(E49-E82)<=0.1,E49>0,E82>0),"ok","Erreur !")) -> ok | F94: =IF(AND(F49=0,F82=0),"n/d",IF(AND((F49-F82)>=-0.1,(F49-F82)<=0.1,F49>0,F82>0),"ok","Erreur !")) -> ok | G94: =IF(AND(G49=0,G82=0),"n/d",IF(AND((G49-G82)>=-0.1,(G49-G82)<=0.1,G49>0,G82>0),"ok","Erreur !")) -> ok | H94: =IF(AND(H49=0,H82=0),"n/d",IF(AND((H49-H82)>=-0.1,(H49-H82)<=0.1,H49>0,H82>0),"ok","Erreur !")) -> ok | I94: =IF(AND(I49=0,I82=0),"n/d",IF(AND((I49-I82)>=-0.1,(I49-I82)<=0.1,I49>0,I82>0),"ok","Erreur !")) -> ok | J94: =IF(AND(J49=0,J82=0),"n/d",IF(AND((J49-J82)>=-0.1,(J49-J82)<=0.1,J49>0,J82>0),"ok","Erreur !")) -> ok | K94: =IF(AND(K49=0,K82=0),"n/d",IF(AND((K49-K82)>=-0.1,(K49-K82)<=0.1,K49>0,K82>0),"ok","Erreur !")) -> ok | L94: =IF(AND(L49=0,L82=0),"n/d",IF(AND((L49-L82)>=-0.1,(L49-L82)<=0.1,L49>0,L82>0),"ok","Erreur !")) -> ok | ... N94: =IF(AND(N49=0,N82=0),"n/d",IF(AND((N49-N82)>=-0.1,(N49-N82)<=0.1,N49>0,N82>0),"ok","Erreur !")) -> ok | O94: Contrôle Actif =? Passif
A97: Calcul de la Trésorerie Nette positive | B97: (Merci de ne rien modifier dans les zones grises de droite et de gauche, réservées à des calculs intermédiaires. | G97: =IF((G47-G80)>0,G47-G80,0) -> 0 | H97: =IF(H182>=0,G97-G98+(Hypo!H57+H165)+(H60-G60)+(H62-G62)+H76+H77+(Hypo!H55*H104/360)+(G79+H156)-H256-SUM(G76:G78)-(H28-G28)-SUM(H44:H46)+SUM(G44:G46),0) -> 184164.62 | I97: =IF(I182>=0,H47-H80+(Hypo!I57+I165)+(I60-H60)+(I62-H62)+I76+I77+(Hypo!I55*I104/360)+(H79+I156)-I256-SUM(H76:H78)-(I28-H28)-SUM(I44:I46)+SUM(H44:H46),0) -> 184164.62 | J97: =IF(J182>=0,I47-I80+(Hypo!J57+J165)+(J60-I60)+(J62-I62)+J76+J77+(Hypo!J55*J104/360)+(I79+J156)-J256-SUM(I76:I78)-(J28-I28)-SUM(J44:J46)+SUM(I44:I46),0) -> 184164.62 | K97: =IF(K182>=0,J47-J80+(Hypo!K57+K165)+(K60-J60)+(K62-J62)+K76+K77+(Hypo!K55*K104/360)+(J79+K156)-K256-SUM(J76:J78)-(K28-J28)-SUM(K44:K46)+SUM(J44:J46),0) -> 184164.62 | L97: =IF(L182>=0,K47-K80+(Hypo!L57+L165)+(L60-K60)+(L62-K62)+L76+L77+(Hypo!L55*L104/360)+(K79+L156)-L256-SUM(K76:K78)-(L28-K28)-SUM(L44:L46)+SUM(K44:K46),0) -> 184164.62 | M97: =IF(M182>=0,L47-L80+(Hypo!M57+M165)+(M60-L60)+(M62-L62)+M76+M77+(Hypo!M55*M104/360)+(L79+M156)-M256-SUM(L76:L78)-(M28-L28)-SUM(M44:M46)+SUM(L44:L46),0) -> 184164.62 | N97: =IF(N182>=0,M47-M80+(Hypo!N57+N165)+(N60-M60)+(N62-M62)+N76+N77+(Hypo!N55*N104/360)+(M79+N156)-N256-SUM(M76:M78)-(N28-M28)-SUM(N44:N46)+SUM(M44:M46),0) -> 184164.62
A98: Calcul de la Trésorerie Nette négative | B98: Ces zones ne seront pas imprimées) | G98: =IF((G47-G80)<=0,G80-G47,0) -> 347295.76 | H98: =IF(H182<0,G98-G97-(Hypo!H57+(H165-I256))-(H60-G60)-(H62-G62)-SUM(H76:H78)+SUM(G76:G78)+(H28-G28)+SUM(H44:H46)-SUM(G44:G46),0) -> 0 | I98: =IF(I182<0,H80-H47-(Hypo!I57+(I165-J256))-(I60-H60)-(I62-H62)-SUM(I76:I78)+SUM(H76:H78)+(I28-H28)+SUM(I44:I46)-SUM(H44:H46),0) -> 0 | J98: =IF(J182<0,I80-I47-(Hypo!J57+(J165-K256))-(J60-I60)-(J62-I62)-SUM(J76:J78)+SUM(I76:I78)+(J28-I28)+SUM(J44:J46)-SUM(I44:I46),0) -> 0 | K98: =IF(K182<0,J80-J47-(Hypo!K57+(K165-L256))-(K60-J60)-(K62-J62)-SUM(K76:K78)+SUM(J76:J78)+(K28-J28)+SUM(K44:K46)-SUM(J44:J46),0) -> 0 | L98: =IF(L182<0,K80-K47-(Hypo!L57+(L165-M256))-(L60-K60)-(L62-K62)-SUM(L76:L78)+SUM(K76:K78)+(L28-K28)+SUM(L44:L46)-SUM(K44:K46),0) -> 0 | M98: =IF(M182<0,L80-L47-(Hypo!M57+(M165-N256))-(M60-L60)-(M62-L62)-SUM(M76:M78)+SUM(L76:L78)+(M28-L28)+SUM(M44:M46)-SUM(L44:L46),0) -> 0 | N98: =IF(N182<0,M80-M47-(Hypo!N57+(N165-R256))-(N60-M60)-(N62-M62)-SUM(N76:N78)+SUM(M76:M78)+(N28-M28)+SUM(N44:N46)-SUM(M44:M46),0) -> 0
E100: =E25 -> Historique | H100: =H25 -> Prévisions
A101: Compte de Résultat : | E101: =E26 -> 39783 | F101: =F26 -> 40178 | G101: =G26 -> 40543 | H101: =H26 -> 40909 | I101: =I26 -> 41275 | J101: =J26 -> 41641 | K101: =K26 -> 42007 | L101: =L26 -> 42373 | ... N101: =N26 -> 43105 | O101: Compte de Résultat :
H103: =IF(Hypo!H33="",0,Hypo!H33) -> 0 | I103: =IF(Hypo!I33="",0,Hypo!I33) -> 0 | J103: =IF(Hypo!J33="",0,Hypo!J33) -> 0 | K103: =IF(Hypo!K33="",0,Hypo!K33) -> 0 | L103: =IF(Hypo!L33="",0,Hypo!L33) -> 0 | M103: =IF(Hypo!M33="",0,Hypo!M33) -> 0 | N103: =IF(Hypo!N33="",0,Hypo!N33) -> 0
A104: Chiffre d'affaires H.T. | E104: =Etatsfin!E41 -> 717966.67 | F104: =Etatsfin!F41 -> 907795.82 | G104: =Etatsfin!G41 -> 1616204.7 | H104: =IF(T27=0,0,(O22*(G104/T27)*(1+H103))+(P22*SUM(H107:H110))) -> 1616204.7 | I104: =(O22*H104*(1+I103))+(P22*SUM(I107:I110)) -> 1616204.7 | J104: =(O22*I104*(1+J103))+(P22*SUM(J107:J110)) -> 1616204.7 | K104: =(O22*J104*(1+K103))+(P22*SUM(K107:K110)) -> 1616204.7 | L104: =(O22*K104*(1+L103))+(P22*SUM(L107:L110)) -> 1616204.7 | M104: =(O22*L104*(1+M103))+(P22*SUM(M107:M110)) -> 1616204.7 | N104: =(O22*M104*(1+N103))+(P22*SUM(N107:N110)) -> 1616204.7 | O104: Chiffre d'affaires H.T.
A105: (Evolution du CA, annualisée, en %) | B105: =IF(OR(Etatsfin!D6<=0,Etatsfin!D6=""),365,Etatsfin!D6) -> 3 | E105: =IF(OR(R27=0,Etatsfin!D41=0),"n/d ",((Etatsfin!E41/Etatsfin!D41)*(B105/R27))-1) -> 4.1606828 | F105: =IF(OR(S27=0,E104=0),"n/d ",((F104/E104)*(R27/S27))-1) -> 0.17156903 | G105: =IF(OR(T27=0,F104=0),"n/d ",((G104/F104)*(S27/T27))-1) -> 0.92669252 | H105: =IF(G104=0,"n/d ",((H104/G104)*T27)-1) -> 0 | I105: =IF(H104=0,"n/d ",(I104-H104)/H104) -> 0 | J105: =IF(I104=0,"n/d ",(J104-I104)/I104) -> 0 | K105: =IF(J104=0,"n/d ",(K104-J104)/J104) -> 0 | L105: =IF(K104=0,"n/d ",(L104-K104)/K104) -> 0 | M105: =IF(L104=0,"n/d ",(M104-L104)/L104) -> 0 | N105: =IF(M104=0,"n/d ",(N104-M104)/M104) -> 0 | O105: (Evolution du CA, annualisée, en %)
A106: Décomposition de 100% du CA : | E106: =IF(O22=1,"",IF(AND((E104-SUM(E107:E110))>=-0.1,(E104-SUM(E107:E110)<=0.1)),"","Erreur de saisie !")) | F106: =IF(O22=1,"",IF(AND((F104-SUM(F107:F110))>=-0.1,(F104-SUM(F107:F110)<=0.1)),"","Erreur de saisie !")) | G106: =IF(O22=1,"",IF(AND((G104-SUM(G107:G110))>=-0.1,(G104-SUM(G107:G110)<=0.1)),"","Erreur de saisie !")) | O106: =A106 -> Décomposition de 100% du CA :
A107: - CA sur ... (tel pays, ou telle Division) | B107: =CONCATENATE("(en ",O21,")") -> (en KF) | O107: =A107 -> - CA sur ... (tel pays, ou telle Division)
A108: - CA sur ... (tel pays, ou telle Division) | B108: =CONCATENATE("(en ",O21,")") -> (en KF) | O108: =A108 -> - CA sur ... (tel pays, ou telle Division)
A109: - CA sur ... (tel pays, ou telle Division) | B109: =CONCATENATE("(en ",O21,")") -> (en KF) | O109: =A109 -> - CA sur ... (tel pays, ou telle Division)
A110: - CA sur ... (tel pays, ou telle Division) | B110: =CONCATENATE("(en ",O21,")") -> (en KF) | O110: =A110 -> - CA sur ... (tel pays, ou telle Division)
A112: + Variation des stocks | E112: =Etatsfin!E43+Etatsfin!E49-Saisie!F123 -> 0 | F112: =Etatsfin!F43+Etatsfin!F49-Etatsfin!L43 -> -6140.1903 | G112: =Etatsfin!G43+Etatsfin!G49-Etatsfin!M43 -> -52900.385 | H112: =H44-G44 -> -444621.94 | I112: =I44-H44 -> 0 | J112: =J44-I44 -> 0 | K112: =K44-J44 -> 0 | L112: =L44-K44 -> 0 | M112: =M44-L44 -> 0 | N112: =N44-M44 -> 0 | O112: + Variation des stocks
A113: + Production immobilisée | E113: =Saisie!F123 -> 0 | F113: =Etatsfin!L43 -> 23322.944 | G113: =Etatsfin!M43 -> 53131.535 | H113: 0 | I113: 0 | J113: 0 | K113: 0 | L113: 0 | M113: 0 | N113: 0 | O113: + Production immobilisée
A114: + Autres produits | E114: =Etatsfin!E44 -> 0 | F114: =Etatsfin!F44 -> 2281.665 | G114: =Etatsfin!G44 -> 621.118 | H114: 0 | I114: 0 | J114: 0 | K114: 0 | L114: 0 | M114: 0 | N114: 0 | O114: + Autres produits
A115: - Achats et sous-traitance | E115: =Etatsfin!E48 -> 639351.23 | F115: =Etatsfin!F48 -> 765768.86 | G115: =Etatsfin!G48 -> 1379090.5 | H115: =-(H118-H104-H112-H113-H114) -> 1171582.7 | I115: =-(I118-I104-I112-I113-I114) -> 1616204.7 | J115: =-(J118-J104-J112-J113-J114) -> 1616204.7 | K115: =-(K118-K104-K112-K113-K114) -> 1616204.7 | L115: =-(L118-L104-L112-L113-L114) -> 1616204.7 | M115: =-(M118-M104-M112-M113-M114) -> 1616204.7 | N115: =-(N118-N104-N112-N113-N114) -> 1616204.7 | O115: - Achats et sous-traitance
H117: =IF(Hypo!H35="",0,Hypo!H35) -> 0 | I117: =IF(Hypo!I35="",0,Hypo!I35) -> 0 | J117: =IF(Hypo!J35="",0,Hypo!J35) -> 0 | K117: =IF(Hypo!K35="",0,Hypo!K35) -> 0 | L117: =IF(Hypo!L35="",0,Hypo!L35) -> 0 | M117: =IF(Hypo!M35="",0,Hypo!M35) -> 0 | N117: =IF(Hypo!N35="",0,Hypo!N35) -> 0
A118: = Marge commerciale | E118: =E104+E112+E113+E114-E115 -> 78615.446 | F118: =F104+F112+F113+F114-F115 -> 161491.38 | G118: =G104+G112+G113+G114-G115 -> 237966.49 | H118: =(O22*H104*H117)+(P22*SUM(H121:H124)) -> 0 | I118: =(O22*I104*I117)+(P22*SUM(I121:I124)) -> 0 | J118: =(O22*J104*J117)+(P22*SUM(J121:J124)) -> 0 | K118: =(O22*K104*K117)+(P22*SUM(K121:K124)) -> 0 | L118: =(O22*L104*L117)+(P22*SUM(L121:L124)) -> 0 | M118: =(O22*M104*M117)+(P22*SUM(M121:M124)) -> 0 | N118: =(O22*N104*N117)+(P22*SUM(N121:N124)) -> 0 | O118: = Marge commerciale
A119: (en % du CA) | E119: =IF(E104=0,"n/d ",E118/E104) -> 0.10949735 | F119: =IF(F104=0,"n/d ",F118/F104) -> 0.17789395 | G119: =IF(G104=0,"n/d ",G118/G104) -> 0.14723784 | H119: =IF(H104=0,"n/d ",H118/H104) -> 0 | I119: =IF(I104=0,"n/d ",I118/I104) -> 0 | J119: =IF(J104=0,"n/d ",J118/J104) -> 0 | K119: =IF(K104=0,"n/d ",K118/K104) -> 0 | L119: =IF(L104=0,"n/d ",L118/L104) -> 0 | ... N119: =IF(N104=0,"n/d ",N118/N104) -> 0 | O119: (en % du CA)
A120: Décomposit° de 100% de la Marge Commerc. : | E120: =IF(O22=1,"",IF(AND((E118-SUM(E121:E124))>=-0.1,(E118-SUM(E121:E124)<=0.1)),"","Erreur de saisie !")) | F120: =IF(O22=1,"",IF(AND((F118-SUM(F121:F124))>=-0.1,(F118-SUM(F121:F124)<=0.1)),"","Erreur de saisie!")) | G120: =IF(O22=1,"",IF(AND((G118-SUM(G121:G124))>=-0.1,(G118-SUM(G121:G124)<=0.1)),"","Erreur de saisie !")) | O120: =A120 -> Décomposit° de 100% de la Marge Commerc. :
A121: - Marge sur ... (tel pays, ou telle Division) | B121: =CONCATENATE("(en ",O21,")") -> (en KF) | O121: =A121 -> - Marge sur ... (tel pays, ou telle Division)
...

Sheet Dette
A1: =CONCATENATE(" Unité de compte : ",PrSept!P21) -> Unité de compte : KF
L2: Date: | M2: =TODAY() -> 46304
A3: Société : | B3: =IF(PrSept!B19="Saisir sur Saisie ou Etatsfin",CONCATENATE(PrSept!B19," ou PrSept"),PrSept!B19) -> MERIPLAST
A4: Groupe : | B4: =IF(PrSept!B20="Saisir sur Saisie ou Etatsfin",CONCATENATE(PrSept!B20," ou PrSept"),PrSept!B20) -> MERIPLAST | L4: Scénario : | M4: =PrSept!M20 -> A saisir sur Hypo
E10: =PrSept!E25 -> Historique | H10: =PrSept!H25 -> Prévisions
A11: Capacité d'endettement : | E11: =PrSept!E26 -> 39783 | F11: =PrSept!F26 -> 40178 | G11: =PrSept!G26 -> 40543 | H11: =PrSept!H26 -> 40909 | I11: =PrSept!I26 -> 41275 | J11: =PrSept!J26 -> 41641 | K11: =PrSept!K26 -> 42007 | L11: =PrSept!L26 -> 42373 | ... N11: =PrSept!N26 -> 43105 | O11: =N11+366 -> 43471 | P11: =O11+366 -> 43837 | Q11: =P11+366 -> 44203 | R11: =Q11+366 -> 44569 | S11: =R11+366 -> 44935 | T11: Capacité d'endettement :
A13: EBE | E13: =PrSept!E135 -> 45113.275 | F13: =PrSept!F135 -> 85384.745 | G13: =PrSept!G135 -> 114043.95 | H13: =IF(B26<1,"--",PrSept!H135) -> 0 | I13: =IF(B26<2,"--",PrSept!I135) -> 0 | J13: =IF(B26<3,"--",PrSept!J135) -> 0 | K13: =IF(B26<4,"--",PrSept!K135) -> 0 | L13: =IF(B26<5,"--",PrSept!L135) -> 0 | M13: =IF(B26<6,"--",PrSept!M135) -> 0 | N13: =IF(B26<7,"--",PrSept!N135) -> 0 | O13: =IF(B26<8,"--",N13) -> 0 | P13: =IF(B26<9,"--",O13) -> 0 | Q13: =IF(B26<10,"--",P13) -> 0 | R13: =IF(B26<11,"--",Q13) -> 0 | S13: =IF(B26<12,"--",R13) -> 0 | T13: EBE
A14: - Investissement industriel (hors production immobilisée) | E14: =PrSept!E218 -> 61434.208 | F14: =PrSept!F218 -> 12147.064 | G14: =PrSept!G218 -> 26556.55 | H14: =IF(B26<1,"--",PrSept!H218) -> 0 | I14: =IF(B26<2,"--",PrSept!I218) -> 0 | J14: =IF(B26<3,"--",PrSept!J218) -> 0 | K14: =IF(B26<4,"--",PrSept!K218) -> 0 | L14: =IF(B26<5,"--",PrSept!L218) -> 0 | M14: =IF(B26<6,"--",PrSept!M218) -> 0 | N14: =IF(B26<7,"--",PrSept!N218) -> 0 | O14: =IF(B26<8,"--",N14) -> 0 | P14: =IF(B26<9,"--",O14) -> 0 | Q14: =IF(B26<10,"--",P14) -> 0 | R14: =IF(B26<11,"--",Q14) -> 0 | S14: =IF(B26<12,"--",R14) -> 0 | T14: - Investissement industriel (hors production immobilisée)
A15: - Variation du BFR (hors EENE) | E15: =PrSept!E210-(PrSept!E89-Etatsfin!K34) -> 64151.468 | F15: =PrSept!F210-(PrSept!F89-PrSept!E89) -> 153535.45 | G15: =PrSept!G210-(PrSept!G89-PrSept!F89) -> 238176.75 | H15: =IF(B26<1,"--",PrSept!H85-PrSept!G85) -> -531193.91 | I15: =IF(B26<2,"--",PrSept!I85-PrSept!H85) -> 0 | J15: =IF(B26<3,"--",PrSept!J85-PrSept!I85) -> 0 | K15: =IF(B26<4,"--",PrSept!K85-PrSept!J85) -> 0 | L15: =IF(B26<5,"--",PrSept!L85-PrSept!K85) -> 0 | M15: =IF(B26<6,"--",PrSept!M85-PrSept!L85) -> 0 | N15: =IF(B26<7,"--",PrSept!N85-PrSept!M85) -> 0 | O15: 0 | P15: 0 | Q15: 0 | R15: 0 | S15: 0 | T15: - Variation du BFR (hors EENE)
A16: - Impôt sur les sociétés | E16: =PrSept!E163 -> 6127.6695 | F16: =PrSept!F163 -> 6938.5937 | G16: =PrSept!G163 -> 6990.363 | H16: =IF(B26<1,"--",PrSept!H163) -> 0 | I16: =IF(B26<2,"--",PrSept!I163) -> 0 | J16: =IF(B26<3,"--",PrSept!J163) -> 0 | K16: =IF(B26<4,"--",PrSept!K163) -> 0 | L16: =IF(B26<5,"--",PrSept!L163) -> 0 | M16: =IF(B26<6,"--",PrSept!M163) -> 0 | N16: =IF(B26<7,"--",PrSept!N163) -> 0 | O16: =IF(B26<8,"--",N16) -> 0 | P16: =IF(B26<9,"--",O16) -> 0 | Q16: =IF(B26<10,"--",P16) -> 0 | R16: =IF(B26<11,"--",Q16) -> 0 | S16: =IF(B26<12,"--",R16) -> 0 | T16: - Impôt sur les sociétés
A17: - Dividendes payés dans l'année | E17: =PrSept!E256 -> 0 | F17: =PrSept!F256 -> 0 | G17: =PrSept!G256 -> 0 | H17: =IF(B26<1,"--",PrSept!H256) -> 0.0060000001 | I17: =IF(B26<2,"--",PrSept!I256) -> 0 | J17: =IF(B26<3,"--",PrSept!J256) -> 0 | K17: =IF(B26<4,"--",PrSept!K256) -> 0 | L17: =IF(B26<5,"--",PrSept!L256) -> 0 | M17: =IF(B26<6,"--",PrSept!M256) -> 0 | N17: =IF(B26<7,"--",PrSept!N256) -> 0 | O17: =IF(B26<8,"--",PrSept!R256) -> 0 | P17: =IF(B26<9,"--",O17) -> 0 | Q17: =IF(B26<10,"--",P17) -> 0 | R17: =IF(B26<11,"--",Q17) -> 0 | S17: =IF(B26<12,"--",R17) -> 0 | T17: - Dividendes payés dans l'année
A18: +/- Divers (Augm. de capital, Cessions d'actifs, ...) | G18: A saisir le cas échéant | T18: +/- Divers (Augm. de capital, Cessions d'actifs, ...)
A19: = Cash disponible pour le service de la dette | E19: =E13-E14-E15-E16-E17+E18 -> -86600.071 | F19: =F13-F14-F15-F16-F17+F18 -> -87236.367 | G19: =IF(G18="A saisir le cas échéant",G13-G14-G15-G16-G17,G13-G14-G15-G16-G17+G18) -> -157679.71 | H19: =IF(B26<1,"--",H13-H14-H15-H16-H17+H18) -> 531193.91 | I19: =IF(B26<2,"--",I13-I14-I15-I16-I17+I18) -> 0 | J19: =IF(B26<3,"--",J13-J14-J15-J16-J17+J18) -> 0 | K19: =IF(B26<4,"--",K13-K14-K15-K16-K17+K18) -> 0 | L19: =IF(B26<5,"--",L13-L14-L15-L16-L17+L18) -> 0 | M19: =IF(B26<6,"--",M13-M14-M15-M16-M17+M18) -> 0 | N19: =IF(B26<7,"--",N13-N14-N15-N16-N17+N18) -> 0 | O19: =IF(B26<8,"--",O13-O14-O15-O16-O17+O18) -> 0 | P19: =IF(B26<9,"--",P13-P14-P15-P16-P17+P18) -> 0 | Q19: =IF(B26<10,"--",Q13-Q14-Q15-Q16-Q17+Q18) -> 0 | R19: =IF(B26<11,"--",R13-R14-R15-R16-R17+R18) -> 0 | S19: =IF(B26<12,"--",S13-S14-S15-S16-S17+S18) -> 0 | T19: = Cash disponible pour le service de la dette
A20: - Service de la dette (crédit-bail inclus) hors remb. CT et EENE | E20: =IF(Etatsfin!K20=0,0,PrSept!E149+Etatsfin!K20+PrSept!E150) -> 0 | F20: =IF(Etatsfin!L20=0,0,PrSept!F149+Etatsfin!L20+PrSept!F150) -> 0 | G20: =IF(Etatsfin!M20=0,0,PrSept!G149+Etatsfin!M20+PrSept!G150) -> 0 | H20: =IF(B26<1,"--",PrSept!H234+PrSept!H149+PrSept!H150) -> 0 | I20: =IF(B26<2,"--",PrSept!I234+PrSept!I149+PrSept!I150) -> 0 | J20: =IF(B26<3,"--",PrSept!J234+PrSept!J149+PrSept!J150) -> 0 | K20: =IF(B26<4,"--",PrSept!K234+PrSept!K149+PrSept!K150) -> 0 | L20: =IF(B26<5,"--",PrSept!L234+PrSept!L149+PrSept!L150) -> 0 | M20: =IF(B26<6,"--",PrSept!M234+PrSept!M149+PrSept!M150) -> 0 | N20: =IF(B26<7,"--",PrSept!N234+PrSept!N149+PrSept!N150) -> 0 | T20: - Service de la dette (crédit-bail inclus) hors remb. CT et EENE
A21: - Rembours. des CT et EENE + économie de frais fin. | E21: Zone vide | H21: =IF(H32="Non",0,PrSept!H80+PrSept!H89-((PrSept!H80+PrSept!H89)/2*H28)) -> 0 | I21: =IF(I32="Non",0,PrSept!I80+PrSept!I89-((PrSept!I80+PrSept!I89)/2*I28)) -> 0 | J21: =IF(J32="Non",0,PrSept!J80+PrSept!J89-((PrSept!J80+PrSept!J89)/2*J28)) -> 0 | K21: =IF(K32="Non",0,PrSept!K80+PrSept!K89-((PrSept!K80+PrSept!K89)/2*K28)) -> 0 | L21: =IF(L32="Non",0,PrSept!L80+PrSept!L89-((PrSept!L80+PrSept!L89)/2*L28)) -> 0 | M21: =IF(M32="Non",0,PrSept!M80+PrSept!M89-((PrSept!M80+PrSept!M89)/2*M28)) -> 0 | N21: =IF(N32="Non",0,PrSept!N80+PrSept!N89-((PrSept!N80+PrSept!N89)/2*N28)) -> 0 | P21: Zone vide | T21: - Rembours. des CT et EENE + économie de frais fin.
A22: = Cash disponible pour le service de la dette Supplémentaire | E22: =IF(E20=0," n/d",E19-E20) -> n/d | F22: =IF(F20=0," n/d",F19-F20) -> n/d | G22: =IF(G20=0," n/d",G19-G20) -> n/d | H22: =IF(B26<1,"--",H19-H20-H21) -> 531193.91 | I22: =IF(B26<2,"--",I19-I20-I21) -> 0 | J22: =IF(B26<3,"--",J19-J20-J21) -> 0 | K22: =IF(B26<4,"--",K19-K20-K21) -> 0 | L22: =IF(B26<5,"--",L19-L20-L21) -> 0 | M22: =IF(B26<6,"--",M19-M20-M21) -> 0 | N22: =IF(B26<7,"--",N19-N20-N21) -> 0 | T22: = Cash disponible pour le service de la dette Supplémentaire
A24: Paramètres retenus : | B24: =IF(OR(B26="A saisir",B26=""),"",IF(B26>12,"12 années au maximum!","")) | G24: [ Les années (n+8) à (n+12) seront identiques à (n+7) ] | T24: Paramètres retenus :
A26: Nombre d'années considérées : | B26: A saisir | E26: (Maximum : 12 années) | G26: (Durée) | H26: (1 an) | I26: (2 ans) | J26: (3 ans) | K26: (4 ans) | L26: (5 ans) | M26: (6 ans) | N26: (7 ans) | O26: (8 ans) | P26: (9 ans) | Q26: (10 ans) | R26: (11 ans) | S26: (12 ans) | T26: Nombre d'années considérées (à saisir) :
A28: Taux d'intérêts après IS (=Ri) | E28: =IF(PrSept!E15="n/d ","n/d ",IF(OR(PrSept!E17<=0,PrSept!E17>=1,PrSept!E17="n/d "),PrSept!E15,PrSept!E15*(1-PrSept!E17))) -> 0.023516693 | F28: =IF(PrSept!F15="n/d ","n/d ",IF(OR(PrSept!F17<=0,PrSept!F17>=1,PrSept!F17="n/d "),PrSept!F15,PrSept!F15*(1-PrSept!F17))) -> 0.051755047 | G28: =IF(PrSept!G15="n/d ","n/d ",IF(OR(PrSept!G17<=0,PrSept!G17>=1,PrSept!G17="n/d "),PrSept!G15,PrSept!G15*(1-PrSept!G17))) -> 0.10691524 | H28: =IF(OR(PrSept!H165<=0,PrSept!H163<=0,PrSept!H165+PrSept!H163=0),PrSept!H16,(PrSept!H16/(1+(PrSept!H163/PrSept!H165)))) -> 0 | I28: =IF(OR(PrSept!I165<=0,PrSept!I163<=0,PrSept!I165+PrSept!I163=0),PrSept!I16,(PrSept!I16/(1+(PrSept!I163/PrSept!I165)))) -> 0 | J28: =IF(OR(PrSept!J165<=0,PrSept!J163<=0,PrSept!J165+PrSept!J163=0),PrSept!J16,(PrSept!J16/(1+(PrSept!J163/PrSept!J165)))) -> 0 | K28: =IF(OR(PrSept!K165<=0,PrSept!K163<=0,PrSept!K165+PrSept!K163=0),PrSept!K16,(PrSept!K16/(1+(PrSept!K163/PrSept!K165)))) -> 0 | L28: =IF(OR(PrSept!L165<=0,PrSept!L163<=0,PrSept!L165+PrSept!L163=0),PrSept!L16,(PrSept!L16/(1+(PrSept!L163/PrSept!L165)))) -> 0 | M28: =IF(OR(PrSept!M165<=0,PrSept!M163<=0,PrSept!M165+PrSept!M163=0),PrSept!M16,(PrSept!M16/(1+(PrSept!M163/PrSept!M165)))) -> 0 | N28: =IF(OR(PrSept!N165<=0,PrSept!N163<=0,PrSept!N165+PrSept!N163=0),PrSept!N16,(PrSept!N16/(1+(PrSept!N163/PrSept!N165)))) -> 0 | O28: =N28 -> 0 | P28: =O28 -> 0 | Q28: =P28 -> 0 | R28: =Q28 -> 0 | S28: =R28 -> 0 | T28: Taux d'intérêts après IS (=R1)
A29: Taux d'intérêts (composés) après IS [ =(1+R1)*(1+R2)*,,,] | H29: =(1+H28) -> 1 | I29: =H29*(1+I28) -> 1 | J29: =I29*(1+J28) -> 1 | K29: =J29*(1+K28) -> 1 | L29: =K29*(1+L28) -> 1 | M29: =L29*(1+M28) -> 1 | N29: =M29*(1+N28) -> 1 | O29: =N29*(1+N28) -> 1 | P29: =O29*(1+N28) -> 1 | Q29: =P29*(1+N28) -> 1 | R29: =Q29*(1+N28) -> 1 | S29: =R29*(1+N28) -> 1 | T29: Taux d'intérêts (composés) après IS [ =(1+R1)*(1+R2)*,,,]
A30: Valeur Actuelle du CDSD | H30: =IF(B26<1,"--",H19/H29) -> 531193.91 | I30: =IF(B26<2,"--",I19/I29) -> 0 | J30: =IF(B26<3,"--",J19/J29) -> 0 | K30: =IF(B26<4,"--",K19/K29) -> 0 | L30: =IF(B26<5,"--",L19/L29) -> 0 | M30: =IF(B26<6,"--",M19/M29) -> 0 | N30: =IF(B26<7,"--",N19/N29) -> 0 | O30: =IF(B26<8,"--",O19/O29) -> 0 | P30: =IF(B26<9,"--",P19/P29) -> 0 | Q30: =IF(B26<10,"--",Q19/Q29) -> 0 | R30: =IF(B26<11,"--",R19/R29) -> 0 | S30: =IF(B26<12,"--",S19/S29) -> 0 | T30: Valeur actuelle du CDSD
A31: VA des CDSD cumulés ( = Capacité d'Endett. sur "n" années) | H31: =IF(B26<1,"--",H30) -> 531193.91 | I31: =IF(B26<2,"--",H31+I30) -> 531193.91 | J31: =IF(B26<3,"--",I31+J30) -> 531193.91 | K31: =IF(B26<4,"--",J31+K30) -> 531193.91 | L31: =IF(B26<5,"--",K31+L30) -> 531193.91 | M31: =IF(B26<6,"--",L31+M30) -> 531193.91 | N31: =IF(B26<7,"--",M31+N30) -> 531193.91 | O31: =IF(B26<8,"--",N31+O30) -> 531193.91 | P31: =IF(B26<9,"--",O31+P30) -> 531193.91 | Q31: =IF(B26<10,"--",P31+Q30) -> 531193.91 | R31: =IF(B26<11,"--",Q31+R30) -> 531193.91 | S31: =IF(B26<12,"--",R31+S30) -> 531193.91 | T31: VA des CDSD cumulés ( = Capacité d'Endett. sur "n" années)
A32: Détermination de l'année de remboursement des CT | E32: Zone vide | H32: =IF(B26=1,"Oui","Non") -> Non | I32: =IF(B26=2,"Oui","Non") -> Non | J32: =IF(B26=3,"Oui","Non") -> Non | K32: =IF(B26=4,"Oui","Non") -> Non | L32: =IF(B26=5,"Oui","Non") -> Non | M32: =IF(B26=6,"Oui","Non") -> Non | N32: =IF(B26=7,"Oui","Non") -> Non | O32: =IF(B26=8,"Oui","Non") -> Non | P32: =IF(B26=9,"Oui","Non") -> Non | Q32: =IF(B26=10,"Oui","Non") -> Non | R32: =IF(B26=11,"Oui","Non") -> Non | S32: =IF(B26=12,"Oui","Non") -> Non | T32: Détermination de l'année de remboursement des CT
A33: Valeur actuelle du CDSD Supplémentaire | H33: =IF(B26<1,"--",H22/H29) -> 531193.91 | I33: =IF(B26<2,"--",I22/I29) -> 0 | J33: =IF(B26<3,"--",J22/J29) -> 0 | K33: =IF(B26<4,"--",K22/K29) -> 0 | L33: =IF(B26<5,"--",L22/L29) -> 0 | M33: =IF(B26<6,"--",M22/M29) -> 0 | N33: =IF(B26<7,"--",N22/N29) -> 0 | T33: Valeur actuelle du CDSD Supplémentaire
A34: Valeur Actuelle des CDSD Supplémentaires cumulés | H34: =IF(B26<1,"--",H33) -> 531193.91 | I34: =IF(B26<2,"--",H34+I33) -> 531193.91 | J34: =IF(B26<3,"--",I34+J33) -> 531193.91 | K34: =IF(B26<4,"--",J34+K33) -> 531193.91 | L34: =IF(B26<5,"--",K34+L33) -> 531193.91 | M34: =IF(B26<6,"--",L34+M33) -> 531193.91 | N34: =IF(B26<7,"--",M34+N33) -> 531193.91 | T34: Valeur actuelle des CDSD Supplémentaires cumulés
A35: (Réservé aux calculs) | H35: =IF(B26=1,H31,0) -> 0 | I35: =IF(B26=2,I31,0) -> 0 | J35: =IF(B26=3,J31,0) -> 0 | K35: =IF(B26=4,K31,0) -> 0 | L35: =IF(B26=5,L31,0) -> 0 | M35: =IF(B26=6,M31,0) -> 0 | N35: =IF(B26=7,N31,0) -> 0 | O35: =IF(B26=8,O31,0) -> 0 | P35: =IF(B26=9,P31,0) -> 0 | Q35: =IF(B26=10,Q31,0) -> 0 | R35: =IF(B26=11,R31,0) -> 0 | S35: =IF(B26=12,S31,0) -> 0 | T35: (Résevé aux calculs)
A36: (Réservé aux calculs) | H36: =IF(B26=1,H34,0) -> 0 | I36: =IF(B26=2,I34,0) -> 0 | J36: =IF(B26=3,J34,0) -> 0 | K36: =IF(B26=4,K34,0) -> 0 | L36: =IF(B26=5,L34,0) -> 0 | M36: =IF(B26=6,M34,0) -> 0 | N36: =IF(B26=7,N34,0) -> 0 | T36: (Résevé aux calculs)
A39: CAPACITE D'ENDETTEMENT : | B39: =IF(OR(B26="A saisir",B26=""),"",IF(B26>12," 12 max !",H35+I35+J35+K35+L35+M35+N35+O35+P35+Q35+R35+S35)) | E39: (Maximum : sur 12 années)
A41: CAPACITE D'END. SUPPLEMENTAIRE : | B41: =IF(OR(B26="A saisir",B26=""),"",IF(B26>7," 7 max !",H36+I36+J36+K36+L36+M36+N36+O36+P36)) | E41: (Maximum : sur 7 années) | N41: =NOW() -> 46304.723
N42: PAGE 1/1

Sheet Graph
A1: =CONCATENATE(" Unité de compte : ",PrSept!P21) -> Unité de compte : KF
A3: Société : | B3: =IF(PrSept!B19="Saisir sur Saisie ou Etatsfin",CONCATENATE(PrSept!B19," ou PrSept"),PrSept!B19) -> MERIPLAST | J3: Date : | K3: =TODAY() -> 46304
A4: Groupe : | B4: =IF(PrSept!B20="Saisir sur Saisie ou Etatsfin",CONCATENATE(PrSept!B20," ou PrSept"),PrSept!B20) -> MERIPLAST
J5: Scénario : | K5: =PrSept!M20 -> A saisir sur Hypo
L52: =NOW() -> 46304.723
L53: PAGE 1/1
